Workbook
Name ACTION: #REF!
Name ACTION: #REF!

Sheet Cover
B2: TEST REPORT DOCUMENT
A4: Project Name | B4: SmartHire-AI | E4: Creator | F4: Nguyễn Minh Hiếu
A5: Project Code | B5: SA | E5: Issue Date | F5: 14/09/2026
A6: Document Code | B6: =B5&"_Test Report_"&F6 -> SA_Test Report_v1.0 | E6: Version | F6: v1.0
A9: Record of change
A10: Effective Date | B10: Version | C10: Change Item | D10: *A,D,M | E10: Change description | F10: Reference
A11: 14/10/2026 | B11: v1.0 | C11: Test Report | D11: A | E11: Initial release: system test cases for 53 features (8 Master platform modules, 45 Tenant modules). | F11: SmartHire-AI feature specifications (docs/features), Report5_Unit Test

Sheet Test Cases
D1: TEST CASE LIST
B3: Project Name | D3: =Cover!B4 -> SmartHire-AI
B4: Project Code | D4: =IF(Cover!B5="","",Cover!B5) -> SA
B5: Test Environment Setup Description | D5: 1. Server: Spring Boot 3 backend (Java 21) and React 19 frontend served by Nginx (Docker Compose). 2. Database: PostgreSQL master DB (smarthire_master) and one MySQL database per tenant; Redis; RabbitMQ. 3. Web browser: latest Google Chrome / Microsoft Edge. 4. Test data: at least two ACTIVE tenants (tenant A, tenant B) with Tenant Admin, HR, Recruiter and Candidate accounts; one Workspace Admin account on the master platform.
B8: No | C8: Function Name | D8: Sheet Name | E8: Description | F8: Pre-Condition
B9: 1 | C9: Tenant Onboarding, Deferred Provisioning & Lifecycle | D9: MASTER-01 | E9: Verify the business rules and APIs of MASTER-01 - Tenant Onboarding, Deferred Provisioning & Lifecycle as specified in docs/features/Authentication/Tenant-Onboarding.md. | F9: Master platform is running; a Workspace Admin account exists.
B10: 2 | C10: Two-Tier B2B Subscription Plans, V27 Snapshot & Quotas | D10: MASTER-02 | E10: Verify the business rules and APIs of MASTER-02 - Two-Tier B2B Subscription Plans, V27 Snapshot & Quotas as specified in docs/features/Master-Platform/Subscription-Plans-Quotas.md. | F10: Master platform is running; a Workspace Admin account exists.
B11: 3 | C11: Billing, VAT Invoicing & Payment Gateways (SePay/VNPay/PayPal) | D11: MASTER-03 | E11: Verify the business rules and APIs of MASTER-03 - Billing, VAT Invoicing & Payment Gateways (SePay/VNPay/PayPal) as specified in docs/features/Master-Platform/Billing-Invoicing-Payment.md. | F11: Master platform is running; a Workspace Admin account exists.
B12: 4 | C12: Self-serve Checkout & Click-wrap Legal Consent (Decree 13/2023/ND-CP) | D12: MASTER-04 | E12: Verify the business rules and APIs of MASTER-04 - Self-serve Checkout & Click-wrap Legal Consent (Decree 13/2023/ND-CP) as specified in docs/features/Master-Platform/Checkout-Clickwrap-Consent.md. | F12: Master platform is running; a Workspace Admin account exists.
B13: 5 | C13: B2B Electronic Contracts & Dropbox Sign API v3 Integration | D13: MASTER-05 | E13: Verify the business rules and APIs of MASTER-05 - B2B Electronic Contracts & Dropbox Sign API v3 Integration as specified in docs/features/Master-Platform/B2B-EContracts-DropboxSign.md. | F13: Master platform is running; a Workspace Admin account exists.
B14: 6 | C14: Enterprise Sales Leads & 4-Step B2B Deal Wizard | D14: MASTER-06 | E14: Verify the business rules and APIs of MASTER-06 - Enterprise Sales Leads & 4-Step B2B Deal Wizard as specified in docs/features/Master-Platform/Sales-Leads-B2B-Deal-Wizard.md. | F14: Master platform is running; a Workspace Admin account exists.
B15: 7 | C15: AI Engine Governance, Model Routing & Token Cost Metering | D15: MASTER-07 | E15: Verify the business rules and APIs of MASTER-07 - AI Engine Governance, Model Routing & Token Cost Metering as specified in docs/features/Master-Platform/AI-Governance-Metering.md. | F15: Master platform is running; a Workspace Admin account exists.
B16: 8 | C16: Platform Financial Analytics (ARR/NRR), Audit Logs & Auto Email Alerts | D16: MASTER-08 | E16: Verify the business rules and APIs of MASTER-08 - Platform Financial Analytics (ARR/NRR), Audit Logs & Auto Email Alerts as specified in docs/features/Master-Platform/Platform-Analytics-Notifications.md. | F16: Master platform is running; a Workspace Admin account exists.
B17: 9 | C17: Multiple Choice Test | D17: ASSESS-01 | E17: Verify the business rules and APIs of ASSESS-01 - Multiple Choice Test as specified in docs/features/Technical-Assessment/Multiple-Choice-Test.md. | F17: Tenant A and tenant B are ACTIVE; a Recruiter account exists in tenant A.
B18: 10 | C18: Coding Challenge | D18: ASSESS-02 | E18: Verify the business rules and APIs of ASSESS-02 - Coding Challenge as specified in docs/features/Technical-Assessment/Coding-Challenge.md. | F18: Tenant A and tenant B are ACTIVE; a Recruiter account exists in tenant A.
B19: 11 | C19: Auto Grading | D19: ASSESS-03 | E19: Verify the business rules and APIs of ASSESS-03 - Auto Grading as specified in docs/features/Technical-Assessment/Auto-Grading.md. | F19: Tenant A and tenant B are ACTIVE; a Recruiter account exists in tenant A.
B20: 12 | C20: Timer Control | D20: ASSESS-04 | E20: Verify the business rules and APIs of ASSESS-04 - Timer Control as specified in docs/features/Technical-Assessment/Timer-Control.md. | F20: Tenant A and tenant B are ACTIVE; a Candidate account exists in tenant A.
... B61: 53 | C61: Hiring Decision Management | D61: WF-03 | E61: Verify the business rules and APIs of WF-03 - Hiring Decision Management as specified in docs/features/Recruitment-Workflow/Hiring-Decision.md. | F61: Tenant A and tenant B are ACTIVE; a Admin account exists in tenant A.

Sheet Test Statistics
B1: TEST STATISTICS
B3: Project Name | C3: =Cover!B4 -> SmartHire-AI | E3: Creator
B4: Project Code | C4: =IF(Cover!B5="","",Cover!B5) -> SA | E4: Reviewer/Approver
B5: Document Code | C5: =Cover!B6 -> SA_Test Report_v1.0 | E5: Issue Date | H5: 14/10/2026
B6: Notes | C6: This release includes 53 features: 8 Master platform modules and 45 Tenant modules.
B10: No | C10: Module code | D10: Passed | E10: Failed | F10: Pending | G10: N/A | H10: Number of test cases
B11: 1 | C11: ='MASTER-01'!B2 -> Tenant Onboarding, Deferred Provisioning & Lifecycle | D11: ='MASTER-01'!B6 -> 0 | E11: ='MASTER-01'!C6 -> 19 | F11: ='MASTER-01'!D6 -> 0 | G11: ='MASTER-01'!E6 -> 0 | H11: ='MASTER-01'!B4 -> 19
B12: 2 | C12: ='MASTER-02'!B2 -> Two-Tier B2B Subscription Plans, V27 Snapshot & Quotas | D12: ='MASTER-02'!B6 -> 16 | E12: ='MASTER-02'!C6 -> 0 | F12: ='MASTER-02'!D6 -> 0 | G12: ='MASTER-02'!E6 -> 0 | H12: ='MASTER-02'!B4 -> 16
B13: 3 | C13: ='MASTER-03'!B2 -> Billing, VAT Invoicing & Payment Gateways (SePay/VNPay/PayPal) | D13: ='MASTER-03'!B6 -> 0 | E13: ='MASTER-03'!C6 -> 20 | F13: ='MASTER-03'!D6 -> 0 | G13: ='MASTER-03'!E6 -> 0 | H13: ='MASTER-03'!B4 -> 20
B14: 4 | C14: ='MASTER-04'!B2 -> Self-serve Checkout & Click-wrap Legal Consent (Decree 13/2023/ND-CP) | D14: ='MASTER-04'!B6 -> 0 | E14: ='MASTER-04'!C6 -> 4 | F14: ='MASTER-04'!D6 -> 0 | G14: ='MASTER-04'!E6 -> 2 | H14: ='MASTER-04'!B4 -> 6
B15: 5 | C15: ='MASTER-05'!B2 -> B2B Electronic Contracts & Dropbox Sign API v3 Integration | D15: ='MASTER-05'!B6 -> 23 | E15: ='MASTER-05'!C6 -> 0 | F15: ='MASTER-05'!D6 -> 0 | G15: ='MASTER-05'!E6 -> 0 | H15: ='MASTER-05'!B4 -> 23
B16: 6 | C16: ='MASTER-06'!B2 -> Enterprise Sales Leads & 4-Step B2B Deal Wizard | D16: ='MASTER-06'!B6 -> 0 | E16: ='MASTER-06'!C6 -> 0 | F16: ='MASTER-06'!D6 -> 8 | G16: ='MASTER-06'!E6 -> 0 | H16: ='MASTER-06'!B4 -> 8
B17: 7 | C17: ='MASTER-07'!B2 -> AI Engine Governance, Model Routing & Token Cost Metering | D17: ='MASTER-07'!B6 -> 0 | E17: ='MASTER-07'!C6 -> 27 | F17: ='MASTER-07'!D6 -> 0 | G17: ='MASTER-07'!E6 -> 0 | H17: ='MASTER-07'!B4 -> 27
B18: 8 | C18: ='MASTER-08'!B2 -> Platform Financial Analytics (ARR/NRR), Audit Logs & Auto Email Alerts | D18: ='MASTER-08'!B6 -> 0 | E18: ='MASTER-08'!C6 -> 0 | F18: ='MASTER-08'!D6 -> 5 | G18: ='MASTER-08'!E6 -> 0 | H18: ='MASTER-08'!B4 -> 5
B19: 9 | C19: ='ASSESS-01'!B2 -> Multiple Choice Test | D19: ='ASSESS-01'!B6 -> 38 | E19: ='ASSESS-01'!C6 -> 0 | F19: ='ASSESS-01'!D6 -> 0 | G19: ='ASSESS-01'!E6 -> 0 | H19: ='ASSESS-01'!B4 -> 38
B20: 10 | C20: ='ASSESS-02'!B2 -> Coding Challenge | D20: ='ASSESS-02'!B6 -> 0 | E20: ='ASSESS-02'!C6 -> 0 | F20: ='ASSESS-02'!D6 -> 5 | G20: ='ASSESS-02'!E6 -> 0 | H20: ='ASSESS-02'!B4 -> 5
B21: 11 | C21: ='ASSESS-03'!B2 -> Auto Grading | D21: ='ASSESS-03'!B6 -> 0 | E21: ='ASSESS-03'!C6 -> 0 | F21: ='ASSESS-03'!D6 -> 0 | G21: ='ASSESS-03'!E6 -> 0 | H21: ='ASSESS-03'!B4 -> 0
B22: 12 | C22: ='ASSESS-04'!B2 -> Timer Control | D22: ='ASSESS-04'!B6 -> 5 | E22: ='ASSESS-04'!C6 -> 0 | F22: ='ASSESS-04'!D6 -> 0 | G22: ='ASSESS-04'!E6 -> 0 | H22: ='ASSESS-04'!B4 -> 5
B23: 13 | C23: ='ASSESS-05'!B2 -> Anti-cheating Detection | D23: ='ASSESS-05'!B6 -> 4 | E23: ='ASSESS-05'!C6 -> 0 | F23: ='ASSESS-05'!D6 -> 3 | G23: ='ASSESS-05'!E6 -> 0 | H23: ='ASSESS-05'!B4 -> 7
B24: 14 | C24: ='AUTH-01'!B2 -> User Registration | D24: ='AUTH-01'!B6 -> 0 | E24: ='AUTH-01'!C6 -> 0 | F24: ='AUTH-01'!D6 -> 4 | G24: ='AUTH-01'!E6 -> 0 | H24: ='AUTH-01'!B4 -> 4
B25: 15 | C25: ='AUTH-02'!B2 -> Login & JWT Authentication | D25: ='AUTH-02'!B6 -> 18 | E25: ='AUTH-02'!C6 -> 0 | F25: ='AUTH-02'!D6 -> 0 | G25: ='AUTH-02'!E6 -> 0 | H25: ='AUTH-02'!B4 -> 18
B26: 16 | C26: ='AUTH-03'!B2 -> Google OAuth Login | D26: ='AUTH-03'!B6 -> 2 | E26: ='AUTH-03'!C6 -> 0 | F26: ='AUTH-03'!D6 -> 0 | G26: ='AUTH-03'!E6 -> 2 | H26: ='AUTH-03'!B4 -> 4
B27: 17 | C27: ='AUTH-04'!B2 -> Role-Based Access Control (RBAC) | D27: ='AUTH-04'!B6 -> 17 | E27: ='AUTH-04'!C6 -> 0 | F27: ='AUTH-04'!D6 -> 0 | G27: ='AUTH-04'!E6 -> 0 | H27: ='AUTH-04'!B4 -> 17
B28: 18 | C28: ='AUTH-05'!B2 -> User Profile Management | D28: ='AUTH-05'!B6 -> 0 | E28: ='AUTH-05'!C6 -> 0 | F28: ='AUTH-05'!D6 -> 7 | G28: ='AUTH-05'!E6 -> 0 | H28: ='AUTH-05'!B4 -> 7
B29: 19 | C29: ='COMPANY-01'!B2 -> View & Update Company Profile | D29: ='COMPANY-01'!B6 -> 8 | E29: ='COMPANY-01'!C6 -> 0 | F29: ='COMPANY-01'!D6 -> 0 | G29: ='COMPANY-01'!E6 -> 0 | H29: ='COMPANY-01'!B4 -> 8
B30: 20 | C30: ='COMPANY-02'!B2 -> Invite tenant staff | D30: ='COMPANY-02'!B6 -> 10 | E30: ='COMPANY-02'!C6 -> 0 | F30: ='COMPANY-02'!D6 -> 0 | G30: ='COMPANY-02'!E6 -> 0 | H30: ='COMPANY-02'!B4 -> 10
B31: 21 | C31: ='COMPANY-02-Tenant-Landing-Page'!B2 -> Tenant Landing / Career Page | D31: ='COMPANY-02-Tenant-Landing-Page'!B6 -> 7 | E31: ='COMPANY-02-Tenant-Landing-Page'!C6 -> 0 | F31: ='COMPANY-02-Tenant-Landing-Page'!D6 -> 0 | G31: ='COMPANY-02-Tenant-Landing-Page'!E6 -> 0 | H31: ='COMPANY-02-Tenant-Landing-Page'!B4 -> 7
B32: 22 | C32: ='CV-01'!B2 -> CV Upload | D32: ='CV-01'!B6 -> 9 | E32: ='CV-01'!C6 -> 0 | F32: ='CV-01'!D6 -> 0 | G32: ='CV-01'!E6 -> 0 | H32: ='CV-01'!B4 -> 9
B33: 23 | C33: ='CV-02'!B2 -> CV Parsing | D33: ='CV-02'!B6 -> 5 | E33: ='CV-02'!C6 -> 0 | F33: ='CV-02'!D6 -> 0 | G33: ='CV-02'!E6 -> 0 | H33: ='CV-02'!B4 -> 5
B34: 24 | C34: ='CV-03'!B2 -> Information Extraction | D34: ='CV-03'!B6 -> 5 | E34: ='CV-03'!C6 -> 0 | F34: ='CV-03'!D6 -> 0 | G34: ='CV-03'!E6 -> 0 | H34: ='CV-03'!B4 -> 5
B35: 25 | C35: ='CV-04'!B2 -> AI Skill Analysis | D35: ='CV-04'!B6 -> 4 | E35: ='CV-04'!C6 -> 0 | F35: ='CV-04'!D6 -> 0 | G35: ='CV-04'!E6 -> 0 | H35: ='CV-04'!B4 -> 4
B36: 26 | C36: ='CV-05'!B2 -> Candidate Matching Score | D36: ='CV-05'!B6 -> 7 | E36: ='CV-05'!C6 -> 0 | F36: ='CV-05'!D6 -> 0 | G36: ='CV-05'!E6 -> 0 | H36: ='CV-05'!B4 -> 7
B37: 27 | C37: ='CV-06'!B2 -> CV Builder | D37: ='CV-06'!B6 -> 25 | E37: ='CV-06'!C6 -> 0 | F37: ='CV-06'!D6 -> 0 | G37: ='CV-06'!E6 -> 0 | H37: ='CV-06'!B4 -> 25
B38: 28 | C38: ='DASH-01'!B2 -> Recruitment Statistics | D38: ='DASH-01'!B6 -> 6 | E38: ='DASH-01'!C6 -> 0 | F38: ='DASH-01'!D6 -> 0 | G38: ='DASH-01'!E6 -> 0 | H38: ='DASH-01'!B4 -> 6
B39: 29 | C39: ='DASH-02'!B2 -> Dashboard Charts | D39: ='DASH-02'!B6 -> 5 | E39: ='DASH-02'!C6 -> 0 | F39: ='DASH-02'!D6 -> 0 | G39: ='DASH-02'!E6 -> 0 | H39: ='DASH-02'!B4 -> 5
B40: 30 | C40: ='DASH-03'!B2 -> Recruitment Trend Analysis | D40: ='DASH-03'!B6 -> 4 | E40: ='DASH-03'!C6 -> 0 | F40: ='DASH-03'!D6 -> 0 | G40: ='DASH-03'!E6 -> 0 | H40: ='DASH-03'!B4 -> 4
B41: 31 | C41: ='INT-01'!B2 -> AI Question Generation | D41: ='INT-01'!B6 -> 35 | E41: ='INT-01'!C6 -> 0 | F41: ='INT-01'!D6 -> 6 | G41: ='INT-01'!E6 -> 0 | H41: ='INT-01'!B4 -> 41
B42: 32 | C42: ='INT-02'!B2 -> Speech-to-Text Integration | D42: ='INT-02'!B6 -> 17 | E42: ='INT-02'!C6 -> 0 | F42: ='INT-02'!D6 -> 0 | G42: ='INT-02'!E6 -> 0 | H42: ='INT-02'!B4 -> 17
B43: 33 | C43: ='INT-03'!B2 -> NLP Response Analysis | D43: ='INT-03'!B6 -> 5 | E43: ='INT-03'!C6 -> 0 | F43: ='INT-03'!D6 -> 0 | G43: ='INT-03'!E6 -> 0 | H43: ='INT-03'!B4 -> 5
B44: 34 | C44: ='INT-04'!B2 -> AI Interview Scoring | D44: ='INT-04'!B6 -> 8 | E44: ='INT-04'!C6 -> 0 | F44: ='INT-04'!D6 -> 0 | G44: ='INT-04'!E6 -> 0 | H44: ='INT-04'!B4 -> 8
B45: 35 | C45: ='INT-05'!B2 -> Interview Feedback | D45: ='INT-05'!B6 -> 4 | E45: ='INT-05'!C6 -> 0 | F45: ='INT-05'!D6 -> 3 | G45: ='INT-05'!E6 -> 0 | H45: ='INT-05'!B4 -> 7
B46: 36 | C46: ='JOB-01'!B2 -> Create / Update / Delete Job | D46: ='JOB-01'!B6 -> 22 | E46: ='JOB-01'!C6 -> 0 | F46: ='JOB-01'!D6 -> 0 | G46: ='JOB-01'!E6 -> 0 | H46: ='JOB-01'!B4 -> 22
B47: 37 | C47: ='JOB-02'!B2 -> Job Publishing | D47: ='JOB-02'!B6 -> 15 | E47: ='JOB-02'!C6 -> 0 | F47: ='JOB-02'!D6 -> 0 | G47: ='JOB-02'!E6 -> 0 | H47: ='JOB-02'!B4 -> 15
B48: 38 | C48: ='JOB-03'!B2 -> Skill Requirement Management | D48: ='JOB-03'!B6 -> 5 | E48: ='JOB-03'!C6 -> 0 | F48: ='JOB-03'!D6 -> 0 | G48: ='JOB-03'!E6 -> 0 | H48: ='JOB-03'!B4 -> 5
B49: 39 | C49: ='JOB-04'!B2 -> Recruitment Stage Management | D49: ='JOB-04'!B6 -> 5 | E49: ='JOB-04'!C6 -> 0 | F49: ='JOB-04'!D6 -> 0 | G49: ='JOB-04'!E6 -> 0 | H49: ='JOB-04'!B4 -> 5
B50: 40 | C50: ='JOB-05'!B2 -> Applicant Management | D50: ='JOB-05'!B6 -> 16 | E50: ='JOB-05'!C6 -> 0 | F50: ='JOB-05'!D6 -> 0 | G50: ='JOB-05'!E6 -> 0 | H50: ='JOB-05'!B4 -> 16
B51: 41 | C51: ='JOB-06'!B2 -> Recruiter Job Assignment | D51: ='JOB-06'!B6 -> 11 | E51: ='JOB-06'!C6 -> 0 | F51: ='JOB-06'!D6 -> 0 | G51: ='JOB-06'!E6 -> 0 | H51: ='JOB-06'!B4 -> 11
B52: 42 | C52: ='PRACT-01'!B2 -> Practice Interview Session | D52: ='PRACT-01'!B6 -> 0 | E52: ='PRACT-01'!C6 -> 0 | F52: ='PRACT-01'!D6 -> 6 | G52: ='PRACT-01'!E6 -> 0 | H52: ='PRACT-01'!B4 -> 6
B53: 43 | C53: ='PRACT-02'!B2 -> AI Feedback Generation | D53: ='PRACT-02'!B6 -> 0 | E53: ='PRACT-02'!C6 -> 0 | F53: ='PRACT-02'!D6 -> 5 | G53: ='PRACT-02'!E6 -> 0 | H53: ='PRACT-02'!B4 -> 5
B54: 44 | C54: ='PRACT-03'!B2 -> Practice History Management | D54: ='PRACT-03'!B6 -> 0 | E54: ='PRACT-03'!C6 -> 0 | F54: ='PRACT-03'!D6 -> 6 | G54: ='PRACT-03'!E6 -> 0 | H54: ='PRACT-03'!B4 -> 6
B55: 45 | C55: ='RANK-01'!B2 -> Candidate Ranking Algorithm | D55: ='RANK-01'!B6 -> 12 | E55: ='RANK-01'!C6 -> 0 | F55: ='RANK-01'!D6 -> 0 | G55: ='RANK-01'!E6 -> 0 | H55: ='RANK-01'!B4 -> 12
B56: 46 | C56: ='RANK-02'!B2 -> Recommendation Engine | D56: ='RANK-02'!B6 -> 0 | E56: ='RANK-02'!C6 -> 0 | F56: ='RANK-02'!D6 -> 4 | G56: ='RANK-02'!E6 -> 0 | H56: ='RANK-02'!B4 -> 4
B57: 47 | C57: ='RANK-03'!B2 -> Overall Candidate Score | D57: ='RANK-03'!B6 -> 3 | E57: ='RANK-03'!C6 -> 0 | F57: ='RANK-03'!D6 -> 0 | G57: ='RANK-03'!E6 -> 0 | H57: ='RANK-03'!B4 -> 3
B58: 48 | C58: ='SCHED-01'!B2 -> Interview Scheduling | D58: ='SCHED-01'!B6 -> 28 | E58: ='SCHED-01'!C6 -> 0 | F58: ='SCHED-01'!D6 -> 0 | G58: ='SCHED-01'!E6 -> 0 | H58: ='SCHED-01'!B4 -> 28
B59: 49 | C59: ='SCHED-02'!B2 -> WebSocket Notification | D59: ='SCHED-02'!B6 -> 6 | E59: ='SCHED-02'!C6 -> 0 | F59: ='SCHED-02'!D6 -> 2 | G59: ='SCHED-02'!E6 -> 0 | H59: ='SCHED-02'!B4 -> 8
B60: 50 | C60: ='SCHED-03'!B2 -> Email Notification | D60: ='SCHED-03'!B6 -> 0 | E60: ='SCHED-03'!C6 -> 0 | F60: ='SCHED-03'!D6 -> 0 | G60: ='SCHED-03'!E6 -> 0 | H60: ='SCHED-03'!B4 -> 0
B61: 51 | C61: ='WF-01'!B2 -> Recruitment Pipeline | D61: ='WF-01'!B6 -> 6 | E61: ='WF-01'!C6 -> 0 | F61: ='WF-01'!D6 -> 0 | G61: ='WF-01'!E6 -> 0 | H61: ='WF-01'!B4 -> 6
B62: 52 | C62: ='WF-02'!B2 -> Candidate Status Management | D62: ='WF-02'!B6 -> 8 | E62: ='WF-02'!C6 -> 0 | F62: ='WF-02'!D6 -> 3 | G62: ='WF-02'!E6 -> 0 | H62: ='WF-02'!B4 -> 11
B63: 53 | C63: ='WF-03'!B2 -> Hiring Decision Management | D63: ='WF-03'!B6 -> 0 | E63: ='WF-03'!C6 -> 0 | F63: ='WF-03'!D6 -> 5 | G63: ='WF-03'!E6 -> 0 | H63: ='WF-03'!B4 -> 5
C65: Sub total | D65: =SUM(D11:D63) -> 424 | E65: =SUM(E11:E63) -> 70 | F65: =SUM(F11:F63) -> 72 | G65: =SUM(G11:G63) -> 4 | H65: =SUM(H11:H63) -> 570
C67: Test coverage | E67: =(D65+E65)*100/(H65-G65) -> 87.279152 | F67: %
C68: Test successful coverage | E68: =D65*100/(H65-G65) -> 74.911661 | F68: %

Sheet MASTER-01
A2: Feature | B2: Tenant Onboarding, Deferred Provisioning & Lifecycle | R2: Passed
A3: Test requirement | B3: Verify the business rules and APIs of MASTER-01 - Tenant Onboarding, Deferred Provisioning & Lifecycle as specified in docs/features/Authentication/Tenant-Onboarding.md. | R3: Failed
A4: Number of TCs | B4: =COUNTIF(A11:A2000,"*-TC*") -> 19 | R4: Pending
A5: Testing Round | B5: Passed | C5: Failed | D5: Pending | E5: N/A | R5: N/A
A6: Round 1 | B6: =COUNTIF($F$11:$F$2000,B$5) -> 0 | C6: =COUNTIF($F$11:$F$2000,C$5) -> 19 | D6: =COUNTIF($F$11:$F$2000,D$5) -> 0 | E6: =COUNTIF($F$11:$F$2000,E$5) -> 0
A7: Round 2 | B7: =COUNTIF($I$11:$I$2000,B$5) -> 0 | C7: =COUNTIF($I$11:$I$2000,C$5) -> 0 | D7: =COUNTIF($I$11:$I$2000,D$5) -> 0 | E7: =COUNTIF($I$11:$I$2000,E$5) -> 0
A8: Round 3 | B8: =COUNTIF($L$11:$L$2000,B$5) -> 0 | C8: =COUNTIF($L$11:$L$2000,C$5) -> 0 | D8: =COUNTIF($L$11:$L$2000,D$5) -> 0 | E8: =COUNTIF($L$11:$L$2000,E$5) -> 0
A10: Test Case ID | B10: Test Case Description | C10: Test Case Procedure | D10: Expected Results | E10: Pre-conditions | F10: Round 1 | G10: Test date | H10: Tester | I10: Round 2 | J10: Test date | K10: Tester | L10: Round 3 | M10: Test date | N10: Tester | O10: Note
A11: Get all tenants (GET /api/v1/master/tenants)
A12: MASTER-01-TC24 | B12: Verify get all tenants succeeds with valid input (GET /api/v1/master/tenants). | C12: 1. Log in as Workspace Admin. 2. Send GET /api/v1/master/tenants. 3. Check the response and the data shown in the system. | D12: HTTP 200. Response success = true and contains the requested data. | E12: Master platform is running. The Workspace Admin account has permission for this action. | F12: Failed | G12: 14/10/2026 | H12: Nguyễn Nhất Sinh | O12: Failing automated tests: MultiDatabaseIntegrationTest.authenticatedOnboardApiCreatesTenantAndRejectsDuplicateAliases
A13: Check subdomain exists (GET /api/v1/master/tenants/check-subdomain/{id})
A14: MASTER-01-TC25 | B14: Verify check subdomain exists succeeds with valid input (GET /api/v1/master/tenants/check-subdomain/{id}). | C14: 1. Do not log in (public endpoint). 2. Send GET /api/v1/master/tenants/check-subdomain/{id}. 3. Check the response and the data shown in the system. | D14: HTTP 200. Response success = true and contains the requested data. | E14: Master platform is running. The target resource exists. | F14: Failed | G14: 14/10/2026 | H14: Nguyễn Nhất Sinh | O14: Failing automated tests: MultiDatabaseIntegrationTest.authenticatedOnboardApiCreatesTenantAndRejectsDuplicateAliases
A15: Db (POST /api/v1/master/tenants/onboard)
A16: MASTER-01-TC26 | B16: Verify db succeeds with valid input (POST /api/v1/master/tenants/onboard). | C16: 1. Log in as Workspace Admin. 2. Send POST /api/v1/master/tenants/onboard and a valid request body. 3. Check the response and the data shown in the system. | D16: HTTP 200/201. Response success = true; the record/action is saved and returned in the response. | E16: Master platform is running. The Workspace Admin account has permission for this action. | F16: Failed | G16: 14/10/2026 | H16: Nguyễn Nhất Sinh | O16: Failing automated tests: MultiDatabaseIntegrationTest.authenticatedOnboardApiCreatesTenantAndRejectsDuplicateAliases
A17: MASTER-01-TC27 | B17: Verify db rejects invalid input (POST /api/v1/master/tenants/onboard). | C17: 1. Log in as Workspace Admin. 2. Send POST /api/v1/master/tenants/onboard with missing required fields or invalid values (empty text, wrong format, out-of-range numbers, non-existing IDs). 3. Check the response and the data in the system. | D17: HTTP 400 (or 404 for a non-existing ID) with success = false and an error message / field errors. No data is created or changed. | E17: Master platform is running. The Workspace Admin account has permission for this action. | F17: Failed | G17: 14/10/2026 | H17: Nguyễn Nhất Sinh | O17: Failing automated tests: MultiDatabaseIntegrationTest.authenticatedOnboardApiCreatesTenantAndRejectsDuplicateAliases
A18: Tenant (DELETE /api/v1/master/tenants/{id})
A19: MASTER-01-TC28 | B19: Verify tenant succeeds with valid input (DELETE /api/v1/master/tenants/{id}). | C19: 1. Log in as Workspace Admin. 2. Send DELETE /api/v1/master/tenants/{id}. 3. Check the response and the data shown in the system. | D19: HTTP 200/204. The record is removed (or archived) and no longer appears in lists. | E19: Master platform is running. The Workspace Admin account has permission for this action. The target resource exists. | F19: Failed | G19: 14/10/2026 | H19: Nguyễn Nhất Sinh | O19: Failing automated tests: MultiDatabaseIntegrationTest.authenticatedOnboardApiCreatesTenantAndRejectsDuplicateAliases
A20: MASTER-01-TC29 | B20: Verify tenant rejects invalid input (DELETE /api/v1/master/tenants/{id}). | C20: 1. Log in as Workspace Admin. 2. Send DELETE /api/v1/master/tenants/{id} with missing required fields or invalid values (empty text, wrong format, out-of-range numbers, non-existing IDs). 3. Check the response and the data in the system. | D20: HTTP 400 (or 404 for a non-existing ID) with success = false and an error message / field errors. No data is created or changed. | E20: Master platform is running. The Workspace Admin account has permission for this action. The target resource exists. | F20: Failed | G20: 14/10/2026 | H20: Nguyễn Nhất Sinh | O20: Failing automated tests: MultiDatabaseIntegrationTest.authenticatedOnboardApiCreatesTenantAndRejectsDuplicateAliases
A21: Get tenant by id (GET /api/v1/master/tenants/{id})
A22: MASTER-01-TC30 | B22: Verify get tenant by id succeeds with valid input (GET /api/v1/master/tenants/{id}). | C22: 1. Log in as Workspace Admin. 2. Send GET /api/v1/master/tenants/{id}. 3. Check the response and the data shown in the system. | D22: HTTP 200. Response success = true and contains the requested data. | E22: Master platform is running. The Workspace Admin account has permission for this action. The target resource exists. | F22: Failed | G22: 14/10/2026 | H22: Nguyễn Nhất Sinh | O22: Failing automated tests: MultiDatabaseIntegrationTest.authenticatedOnboardApiCreatesTenantAndRejectsDuplicateAliases
A23: Update tenant (PUT /api/v1/master/tenants/{id})
A24: MASTER-01-TC31 | B24: Verify update tenant succeeds with valid input (PUT /api/v1/master/tenants/{id}). | C24: 1. Log in as Workspace Admin. 2. Send PUT /api/v1/master/tenants/{id} and a valid request body. 3. Check the response and the data shown in the system. | D24: HTTP 200. Response success = true; the changes are saved and returned. | E24: Master platform is running. The Workspace Admin account has permission for this action. The target resource exists. | F24: Failed | G24: 14/10/2026 | H24: Nguyễn Nhất Sinh | O24: Failing automated tests: MultiDatabaseIntegrationTest.authenticatedOnboardApiCreatesTenantAndRejectsDuplicateAliases
A25: MASTER-01-TC32 | B25: Verify update tenant rejects invalid input (PUT /api/v1/master/tenants/{id}). | C25: 1. Log in as Workspace Admin. 2. Send PUT /api/v1/master/tenants/{id} with missing required fields or invalid values (empty text, wrong format, out-of-range numbers, non-existing IDs). 3. Check the response and the data in the system. | D25: HTTP 400 (or 404 for a non-existing ID) with success = false and an error message / field errors. No data is created or changed. | E25: Master platform is running. The Workspace Admin account has permission for this action. The target resource exists. | F25: Failed | G25: 14/10/2026 | H25: Nguyễn Nhất Sinh | O25: Failing automated tests: MultiDatabaseIntegrationTest.authenticatedOnboardApiCreatesTenantAndRejectsDuplicateAliases
A26: Restore tenant (POST /api/v1/master/tenants/{id}/restore)
A27: MASTER-01-TC33 | B27: Verify restore tenant succeeds with valid input (POST /api/v1/master/tenants/{id}/restore). | C27: 1. Log in as Workspace Admin. 2. Send POST /api/v1/master/tenants/{id}/restore and a valid request body. 3. Check the response and the data shown in the system. | D27: HTTP 200/201. Response success = true; the record/action is saved and returned in the response. | E27: Master platform is running. The Workspace Admin account has permission for this action. The target resource exists. | F27: Failed | G27: 14/10/2026 | H27: Nguyễn Nhất Sinh | O27: Failing automated tests: MultiDatabaseIntegrationTest.authenticatedOnboardApiCreatesTenantAndRejectsDuplicateAliases
A28: MASTER-01-TC34 | B28: Verify restore tenant rejects invalid input (POST /api/v1/master/tenants/{id}/restore). | C28: 1. Log in as Workspace Admin. 2. Send POST /api/v1/master/tenants/{id}/restore with missing required fields or invalid values (empty text, wrong format, out-of-range numbers, non-existing IDs). 3. Check the response and the data in the system. | D28: HTTP 400 (or 404 for a non-existing ID) with success = false and an error message / field errors. No data is created or changed. | E28: Master platform is running. The Workspace Admin account has permission for this action. The target resource exists. | F28: Failed | G28: 14/10/2026 | H28: Nguyễn Nhất Sinh | O28: Failing automated tests: MultiDatabaseIntegrationTest.authenticatedOnboardApiCreatesTenantAndRejectsDuplicateAliases
A29: Retry (POST /api/v1/master/tenants/{id}/retry)
A30: MASTER-01-TC35 | B30: Verify retry succeeds with valid input (POST /api/v1/master/tenants/{id}/retry). | C30: 1. Log in as Workspace Admin. 2. Send POST /api/v1/master/tenants/{id}/retry and a valid request body. 3. Check the response and the data shown in the system. | D30: HTTP 200/201. Response success = true; the record/action is saved and returned in the response. | E30: Master platform is running. The Workspace Admin account has permission for this action. The target resource exists. | F30: Failed | G30: 14/10/2026 | H30: Nguyễn Nhất Sinh | O30: Failing automated tests: MultiDatabaseIntegrationTest.authenticatedOnboardApiCreatesTenantAndRejectsDuplicateAliases
A31: MASTER-01-TC36 | B31: Verify retry rejects invalid input (POST /api/v1/master/tenants/{id}/retry). | C31: 1. Log in as Workspace Admin. 2. Send POST /api/v1/master/tenants/{id}/retry with missing required fields or invalid values (empty text, wrong format, out-of-range numbers, non-existing IDs). 3. Check the response and the data in the system. | D31: HTTP 400 (or 404 for a non-existing ID) with success = false and an error message / field errors. No data is created or changed. | E31: Master platform is running. The Workspace Admin account has permission for this action. The target resource exists. | F31: Failed | G31: 14/10/2026 | H31: Nguyễn Nhất Sinh | O31: Failing automated tests: MultiDatabaseIntegrationTest.authenticatedOnboardApiCreatesTenantAndRejectsDuplicateAliases
A32: Delete (PATCH /api/v1/master/tenants/{id}/soft-delete)
A33: MASTER-01-TC37 | B33: Verify delete succeeds with valid input (PATCH /api/v1/master/tenants/{id}/soft-delete). | C33: 1. Log in as Workspace Admin. 2. Send PATCH /api/v1/master/tenants/{id}/soft-delete and a valid request body. 3. Check the response and the data shown in the system. | D33: HTTP 200. Response success = true; the changed fields are saved. | E33: Master platform is running. The Workspace Admin account has permission for this action. The target resource exists. | F33: Failed | G33: 14/10/2026 | H33: Nguyễn Nhất Sinh | O33: Failing automated tests: MultiDatabaseIntegrationTest.authenticatedOnboardApiCreatesTenantAndRejectsDuplicateAliases
A34: MASTER-01-TC38 | B34: Verify delete rejects invalid input (PATCH /api/v1/master/tenants/{id}/soft-delete). | C34: 1. Log in as Workspace Admin. 2. Send PATCH /api/v1/master/tenants/{id}/soft-delete with missing required fields or invalid values (empty text, wrong format, out-of-range numbers, non-existing IDs). 3. Check the response and the data in the system. | D34: HTTP 400 (or 404 for a non-existing ID) with success = false and an error message / field errors. No data is created or changed. | E34: Master platform is running. The Workspace Admin account has permission for this action. The target resource exists. | F34: Failed | G34: 14/10/2026 | H34: Nguyễn Nhất Sinh | O34: Failing automated tests: MultiDatabaseIntegrationTest.authenticatedOnboardApiCreatesTenantAndRejectsDuplicateAliases
A35: Update tenant status (PATCH /api/v1/master/tenants/{id}/status)
A36: MASTER-01-TC39 | B36: Verify update tenant status succeeds with valid input (PATCH /api/v1/master/tenants/{id}/status). | C36: 1. Log in as Workspace Admin. 2. Send PATCH /api/v1/master/tenants/{id}/status and a valid request body. 3. Check the response and the data shown in the system. | D36: HTTP 200. Response success = true; the changed fields are saved. | E36: Master platform is running. The Workspace Admin account has permission for this action. The target resource exists. | F36: Failed | G36: 14/10/2026 | H36: Nguyễn Nhất Sinh | O36: Failing automated tests: MultiDatabaseIntegrationTest.authenticatedOnboardApiCreatesTenantAndRejectsDuplicateAliases
A37: MASTER-01-TC40 | B37: Verify update tenant status rejects invalid input (PATCH /api/v1/master/tenants/{id}/status). | C37: 1. Log in as Workspace Admin. 2. Send PATCH /api/v1/master/tenants/{id}/status with missing required fields or invalid values (empty text, wrong format, out-of-range numbers, non-existing IDs). 3. Check the response and the data in the system. | D37: HTTP 400 (or 404 for a non-existing ID) with success = false and an error message / field errors. No data is created or changed. | E37: Master platform is running. The Workspace Admin account has permission for this action. The target resource exists. | F37: Failed | G37: 14/10/2026 | H37: Nguyễn Nhất Sinh | O37: Failing automated tests: MultiDatabaseIntegrationTest.authenticatedOnboardApiCreatesTenantAndRejectsDuplicateAliases
A38: Security & tenant isolation
A39: MASTER-01-TC41 | B39: Verify platform admin APIs reject unauthenticated requests and tenant users. | C39: 1. Send GET /api/v1/master/tenants without an Authorization header. 2. Send the same request with a valid token of a tenant user (e.g. Tenant Admin). | D39: Step 1: HTTP 401, code UNAUTHORIZED. Step 2: HTTP 403, code FORBIDDEN (requires WORKSPACE_ADMIN). | E39: A tenant user account exists. | F39: Failed | G39: 14/10/2026 | H39: Nguyễn Nhất Sinh | O39: Failing automated tests: MultiDatabaseIntegrationTest.authenticatedOnboardApiCreatesTenantAndRejectsDuplicateAliases
A40: MASTER-01-TC42 | B40: Verify a Workspace Admin token cannot be used to read tenant data through tenant APIs. | C40: 1. Log in as Workspace Admin. 2. Call a tenant API (e.g. GET /api/v1/jobs) with header X-Tenant-ID = tenant A using the master token. | D40: The request is rejected (HTTP 401/403) and no tenant data is returned. | E40: Workspace Admin account exists; tenant A has data. | F40: Failed | G40: 14/10/2026 | H40: Nguyễn Nhất Sinh | O40: Failing automated tests: MultiDatabaseIntegrationTest.authenticatedOnboardApiCreatesTenantAndRejectsDuplicateAliases

Sheet MASTER-02
A2: Feature | B2: Two-Tier B2B Subscription Plans, V27 Snapshot & Quotas | R2: Passed
A3: Test requirement | B3: Verify the business rules and APIs of MASTER-02 - Two-Tier B2B Subscription Plans, V27 Snapshot & Quotas as specified in docs/features/Master-Platform/Subscription-Plans-Quotas.md. | R3: Failed
A4: Number of TCs | B4: =COUNTIF(A11:A2000,"*-TC*") -> 16 | R4: Pending
A5: Testing Round | B5: Passed | C5: Failed | D5: Pending | E5: N/A | R5: N/A
A6: Round 1 | B6: =COUNTIF($F$11:$F$2000,B$5) -> 16 | C6: =COUNTIF($F$11:$F$2000,C$5) -> 0 | D6: =COUNTIF($F$11:$F$2000,D$5) -> 0 | E6: =COUNTIF($F$11:$F$2000,E$5) -> 0
A7: Round 2 | B7: =COUNTIF($I$11:$I$2000,B$5) -> 0 | C7: =COUNTIF($I$11:$I$2000,C$5) -> 0 | D7: =COUNTIF($I$11:$I$2000,D$5) -> 0 | E7: =COUNTIF($I$11:$I$2000,E$5) -> 0
A8: Round 3 | B8: =COUNTIF($L$11:$L$2000,B$5) -> 0 | C8: =COUNTIF($L$11:$L$2000,C$5) -> 0 | D8: =COUNTIF($L$11:$L$2000,D$5) -> 0 | E8: =COUNTIF($L$11:$L$2000,E$5) -> 0
A10: Test Case ID | B10: Test Case Description | C10: Test Case Procedure | D10: Expected Results | E10: Pre-conditions | F10: Round 1 | G10: Test date | H10: Tester | I10: Round 2 | J10: Test date | K10: Tester | L10: Round 3 | M10: Test date | N10: Tester | O10: Note
A11: Get all plans (GET /api/v1/master/subscriptions)
A12: MASTER-02-TC05 | B12: Verify get all plans succeeds with valid input (GET /api/v1/master/subscriptions). | C12: 1. Log in as Workspace Admin. 2. Send GET /api/v1/master/subscriptions. 3. Check the response and the data shown in the system. | D12: HTTP 200. Response success = true and contains the requested data. | E12: Master platform is running. The Workspace Admin account has permission for this action. | F12: Passed | G12: 11/10/2026 | H12: Nguyễn Nhất Sinh | O12: Verified by automated tests: TwoTierSubscriptionArchitectureTest
A13: Create plan (POST /api/v1/master/subscriptions)
A14: MASTER-02-TC06 | B14: Verify create plan succeeds with valid input (POST /api/v1/master/subscriptions). | C14: 1. Log in as Workspace Admin. 2. Send POST /api/v1/master/subscriptions and a valid request body. 3. Check the response and the data shown in the system. | D14: HTTP 200/201. Response success = true; the record/action is saved and returned in the response. | E14: Master platform is running. The Workspace Admin account has permission for this action. | F14: Passed | G14: 11/10/2026 | H14: Nguyễn Nhất Sinh | O14: Verified by automated tests: TwoTierSubscriptionArchitectureTest
A15: MASTER-02-TC07 | B15: Verify create plan rejects invalid input (POST /api/v1/master/subscriptions). | C15: 1. Log in as Workspace Admin. 2. Send POST /api/v1/master/subscriptions with missing required fields or invalid values (empty text, wrong format, out-of-range numbers, non-existing IDs). 3. Check the response and the data in the system. | D15: HTTP 400 (or 404 for a non-existing ID) with success = false and an error message / field errors. No data is created or changed. | E15: Master platform is running. The Workspace Admin account has permission for this action. | F15: Passed | G15: 11/10/2026 | H15: Nguyễn Nhất Sinh | O15: Verified by automated tests: TwoTierSubscriptionArchitectureTest
A16: Get all tenant subscription instances (GET /api/v1/master/subscriptions/tenants)
A17: MASTER-02-TC08 | B17: Verify get all tenant subscription instances succeeds with valid input (GET /api/v1/master/subscriptions/tenants). | C17: 1. Log in as Workspace Admin. 2. Send GET /api/v1/master/subscriptions/tenants. 3. Check the response and the data shown in the system. | D17: HTTP 200. Response success = true and contains the requested data. | E17: Master platform is running. The Workspace Admin account has permission for this action. | F17: Passed | G17: 11/10/2026 | H17: Nguyễn Nhất Sinh | O17: Verified by automated tests: TwoTierSubscriptionArchitectureTest
A18: Get tenant subscription instance (GET /api/v1/master/subscriptions/tenants/{id})
A19: MASTER-02-TC09 | B19: Verify get tenant subscription instance succeeds with valid input (GET /api/v1/master/subscriptions/tenants/{id}). | C19: 1. Log in as Workspace Admin. 2. Send GET /api/v1/master/subscriptions/tenants/{id}. 3. Check the response and the data shown in the system. | D19: HTTP 200. Response success = true and contains the requested data. | E19: Master platform is running. The Workspace Admin account has permission for this action. The target resource exists. | F19: Passed | G19: 11/10/2026 | H19: Nguyễn Nhất Sinh | O19: Verified by automated tests: TwoTierSubscriptionArchitectureTest
A20: Assign or customize tenant subscription (PUT /api/v1/master/subscriptions/tenants/{id})
A21: MASTER-02-TC10 | B21: Verify assign or customize tenant subscription succeeds with valid input (PUT /api/v1/master/subscriptions/tenants/{id}). | C21: 1. Log in as Workspace Admin. 2. Send PUT /api/v1/master/subscriptions/tenants/{id} and a valid request body. 3. Check the response and the data shown in the system. | D21: HTTP 200. Response success = true; the changes are saved and returned. | E21: Master platform is running. The Workspace Admin account has permission for this action. The target resource exists. | F21: Passed | G21: 11/10/2026 | H21: Nguyễn Nhất Sinh | O21: Verified by automated tests: TwoTierSubscriptionArchitectureTest
A22: MASTER-02-TC11 | B22: Verify assign or customize tenant subscription rejects invalid input (PUT /api/v1/master/subscriptions/tenants/{id}). | C22: 1. Log in as Workspace Admin. 2. Send PUT /api/v1/master/subscriptions/tenants/{id} with missing required fields or invalid values (empty text, wrong format, out-of-range numbers, non-existing IDs). 3. Check the response and the data in the system. | D22: HTTP 400 (or 404 for a non-existing ID) with success = false and an error message / field errors. No data is created or changed. | E22: Master platform is running. The Workspace Admin account has permission for this action. The target resource exists. | F22: Passed | G22: 11/10/2026 | H22: Nguyễn Nhất Sinh | O22: Verified by automated tests: TwoTierSubscriptionArchitectureTest
A23: Get plan by id (GET /api/v1/master/subscriptions/{id})
A24: MASTER-02-TC12 | B24: Verify get plan by id succeeds with valid input (GET /api/v1/master/subscriptions/{id}). | C24: 1. Log in as Workspace Admin. 2. Send GET /api/v1/master/subscriptions/{id}. 3. Check the response and the data shown in the system. | D24: HTTP 200. Response success = true and contains the requested data. | E24: Master platform is running. The Workspace Admin account has permission for this action. The target resource exists. | F24: Passed | G24: 11/10/2026 | H24: Nguyễn Nhất Sinh | O24: Verified by automated tests: TwoTierSubscriptionArchitectureTest
A25: Plan (PUT /api/v1/master/subscriptions/{id})
A26: MASTER-02-TC13 | B26: Verify plan succeeds with valid input (PUT /api/v1/master/subscriptions/{id}). | C26: 1. Log in as Workspace Admin. 2. Send PUT /api/v1/master/subscriptions/{id} and a valid request body. 3. Check the response and the data shown in the system. | D26: HTTP 200. Response success = true; the changes are saved and returned. | E26: Master platform is running. The Workspace Admin account has permission for this action. The target resource exists. | F26: Passed | G26: 11/10/2026 | H26: Nguyễn Nhất Sinh | O26: Verified by automated tests: TwoTierSubscriptionArchitectureTest
A27: MASTER-02-TC14 | B27: Verify plan rejects invalid input (PUT /api/v1/master/subscriptions/{id}). | C27: 1. Log in as Workspace Admin. 2. Send PUT /api/v1/master/subscriptions/{id} with missing required fields or invalid values (empty text, wrong format, out-of-range numbers, non-existing IDs). 3. Check the response and the data in the system. | D27: HTTP 400 (or 404 for a non-existing ID) with success = false and an error message / field errors. No data is created or changed. | E27: Master platform is running. The Workspace Admin account has permission for this action. The target resource exists. | F27: Passed | G27: 11/10/2026 | H27: Nguyễn Nhất Sinh | O27: Verified by automated tests: TwoTierSubscriptionArchitectureTest
A28: Clone custom plan (POST /api/v1/master/subscriptions/{id}/clone-custom)
A29: MASTER-02-TC15 | B29: Verify clone custom plan succeeds with valid input (POST /api/v1/master/subscriptions/{id}/clone-custom). | C29: 1. Log in as Workspace Admin. 2. Send POST /api/v1/master/subscriptions/{id}/clone-custom and a valid request body. 3. Check the response and the data shown in the system. | D29: HTTP 200/201. Response success = true; the record/action is saved and returned in the response. | E29: Master platform is running. The Workspace Admin account has permission for this action. The target resource exists. | F29: Passed | G29: 11/10/2026 | H29: Nguyễn Nhất Sinh | O29: Verified by automated tests: TwoTierSubscriptionArchitectureTest
A30: MASTER-02-TC16 | B30: Verify clone custom plan rejects invalid input (POST /api/v1/master/subscriptions/{id}/clone-custom). | C30: 1. Log in as Workspace Admin. 2. Send POST /api/v1/master/subscriptions/{id}/clone-custom with missing required fields or invalid values (empty text, wrong format, out-of-range numbers, non-existing IDs). 3. Check the response and the data in the system. | D30: HTTP 400 (or 404 for a non-existing ID) with success = false and an error message / field errors. No data is created or changed. | E30: Master platform is running. The Workspace Admin account has permission for this action. The target resource exists. | F30: Passed | G30: 11/10/2026 | H30: Nguyễn Nhất Sinh | O30: Verified by automated tests: TwoTierSubscriptionArchitectureTest
A31: Status (PATCH /api/v1/master/subscriptions/{id}/status)
A32: MASTER-02-TC17 | B32: Verify status succeeds with valid input (PATCH /api/v1/master/subscriptions/{id}/status). | C32: 1. Log in as Workspace Admin. 2. Send PATCH /api/v1/master/subscriptions/{id}/status and a valid request body. 3. Check the response and the data shown in the system. | D32: HTTP 200. Response success = true; the changed fields are saved. | E32: Master platform is running. The Workspace Admin account has permission for this action. The target resource exists. | F32: Passed | G32: 11/10/2026 | H32: Nguyễn Nhất Sinh | O32: Verified by automated tests: TwoTierSubscriptionArchitectureTest
A33: MASTER-02-TC18 | B33: Verify status rejects invalid input (PATCH /api/v1/master/subscriptions/{id}/status). | C33: 1. Log in as Workspace Admin. 2. Send PATCH /api/v1/master/subscriptions/{id}/status with missing required fields or invalid values (empty text, wrong format, out-of-range numbers, non-existing IDs). 3. Check the response and the data in the system. | D33: HTTP 400 (or 404 for a non-existing ID) with success = false and an error message / field errors. No data is created or changed. | E33: Master platform is running. The Workspace Admin account has permission for this action. The target resource exists. | F33: Passed | G33: 11/10/2026 | H33: Nguyễn Nhất Sinh | O33: Verified by automated tests: TwoTierSubscriptionArchitectureTest
A34: Security & tenant isolation
A35: MASTER-02-TC19 | B35: Verify platform admin APIs reject unauthenticated requests and tenant users. | C35: 1. Send GET /api/v1/master/subscriptions without an Authorization header. 2. Send the same request with a valid token of a tenant user (e.g. Tenant Admin). | D35: Step 1: HTTP 401, code UNAUTHORIZED. Step 2: HTTP 403, code FORBIDDEN (requires WORKSPACE_ADMIN). | E35: A tenant user account exists. | F35: Passed | G35: 11/10/2026 | H35: Nguyễn Nhất Sinh | O35: Verified by automated tests: TwoTierSubscriptionArchitectureTest
A36: MASTER-02-TC20 | B36: Verify a Workspace Admin token cannot be used to read tenant data through tenant APIs. | C36: 1. Log in as Workspace Admin. 2. Call a tenant API (e.g. GET /api/v1/jobs) with header X-Tenant-ID = tenant A using the master token. | D36: The request is rejected (HTTP 401/403) and no tenant data is returned. | E36: Workspace Admin account exists; tenant A has data. | F36: Passed | G36: 11/10/2026 | H36: Nguyễn Nhất Sinh | O36: Verified by automated tests: TwoTierSubscriptionArchitectureTest

Sheet MASTER-03
A2: Feature | B2: Billing, VAT Invoicing & Payment Gateways (SePay/VNPay/PayPal) | R2: Passed
A3: Test requirement | B3: Verify the business rules and APIs of MASTER-03 - Billing, VAT Invoicing & Payment Gateways (SePay/VNPay/PayPal) as specified in docs/features/Master-Platform/Billing-Invoicing-Payment.md. | R3: Failed
A4: Number of TCs | B4: =COUNTIF(A11:A2000,"*-TC*") -> 20 | R4: Pending
A5: Testing Round | B5: Passed | C5: Failed | D5: Pending | E5: N/A | R5: N/A
A6: Round 1 | B6: =COUNTIF($F$11:$F$2000,B$5) -> 0 | C6: =COUNTIF($F$11:$F$2000,C$5) -> 20 | D6: =COUNTIF($F$11:$F$2000,D$5) -> 0 | E6: =COUNTIF($F$11:$F$2000,E$5) -> 0
A7: Round 2 | B7: =COUNTIF($I$11:$I$2000,B$5) -> 0 | C7: =COUNTIF($I$11:$I$2000,C$5) -> 0 | D7: =COUNTIF($I$11:$I$2000,D$5) -> 0 | E7: =COUNTIF($I$11:$I$2000,E$5) -> 0
A8: Round 3 | B8: =COUNTIF($L$11:$L$2000,B$5) -> 0 | C8: =COUNTIF($L$11:$L$2000,C$5) -> 0 | D8: =COUNTIF($L$11:$L$2000,D$5) -> 0 | E8: =COUNTIF($L$11:$L$2000,E$5) -> 0
A10: Test Case ID | B10: Test Case Description | C10: Test Case Procedure | D10: Expected Results | E10: Pre-conditions | F10: Round 1 | G10: Test date | H10: Tester | I10: Round 2 | J10: Test date | K10: Tester | L10: Round 3 | M10: Test date | N10: Tester | O10: Note
A11: Get all invoices (GET /api/v1/master/invoices)
A12: MASTER-03-TC05 | B12: Verify get all invoices succeeds with valid input (GET /api/v1/master/invoices). | C12: 1. Log in as Workspace Admin. 2. Send GET /api/v1/master/invoices. 3. Check the response and the data shown in the system. | D12: HTTP 200. Response success = true and contains the requested data. | E12: Master platform is running. The Workspace Admin account has permission for this action. | F12: Failed | G12: 14/10/2026 | H12: Nguyễn Nhất Sinh | O12: Failing automated tests: MasterBillingServiceTest.approveInvoice_PendingInvoice_ProvisionsTenantAndSendsMail
A13: Create invoice (POST /api/v1/master/invoices)
A14: MASTER-03-TC06 | B14: Verify create invoice succeeds with valid input (POST /api/v1/master/invoices). | C14: 1. Log in as Workspace Admin. 2. Send POST /api/v1/master/invoices and a valid request body. 3. Check the response and the data shown in the system. | D14: HTTP 200/201. Response success = true; the record/action is saved and returned in the response. | E14: Master platform is running. The Workspace Admin account has permission for this action. | F14: Failed | G14: 14/10/2026 | H14: Nguyễn Nhất Sinh | O14: Failing automated tests: MasterBillingServiceTest.approveInvoice_PendingInvoice_ProvisionsTenantAndSendsMail
A15: MASTER-03-TC07 | B15: Verify create invoice rejects invalid input (POST /api/v1/master/invoices). | C15: 1. Log in as Workspace Admin. 2. Send POST /api/v1/master/invoices with missing required fields or invalid values (empty text, wrong format, out-of-range numbers, non-existing IDs). 3. Check the response and the data in the system. | D15: HTTP 400 (or 404 for a non-existing ID) with success = false and an error message / field errors. No data is created or changed. | E15: Master platform is running. The Workspace Admin account has permission for this action. | F15: Failed | G15: 14/10/2026 | H15: Nguyễn Nhất Sinh | O15: Failing automated tests: MasterBillingServiceTest.approveInvoice_PendingInvoice_ProvisionsTenantAndSendsMail
A16: Get invoice by id (GET /api/v1/master/invoices/{id})
A17: MASTER-03-TC08 | B17: Verify get invoice by id succeeds with valid input (GET /api/v1/master/invoices/{id}). | C17: 1. Log in as Workspace Admin. 2. Send GET /api/v1/master/invoices/{id}. 3. Check the response and the data shown in the system. | D17: HTTP 200. Response success = true and contains the requested data. | E17: Master platform is running. The Workspace Admin account has permission for this action. The target resource exists. | F17: Failed | G17: 14/10/2026 | H17: Nguyễn Nhất Sinh | O17: Failing automated tests: MasterBillingServiceTest.approveInvoice_PendingInvoice_ProvisionsTenantAndSendsMail
A18: Approve invoice (POST /api/v1/master/invoices/{id}/approve)
A19: MASTER-03-TC09 | B19: Verify approve invoice succeeds with valid input (POST /api/v1/master/invoices/{id}/approve). | C19: 1. Log in as Workspace Admin. 2. Send POST /api/v1/master/invoices/{id}/approve and a valid request body. 3. Check the response and the data shown in the system. | D19: HTTP 200/201. Response success = true; the record/action is saved and returned in the response. | E19: Master platform is running. The Workspace Admin account has permission for this action. The target resource exists. | F19: Failed | G19: 14/10/2026 | H19: Nguyễn Nhất Sinh | O19: Failing automated tests: MasterBillingServiceTest.approveInvoice_PendingInvoice_ProvisionsTenantAndSendsMail
A20: MASTER-03-TC10 | B20: Verify approve invoice rejects invalid input (POST /api/v1/master/invoices/{id}/approve). | C20: 1. Log in as Workspace Admin. 2. Send POST /api/v1/master/invoices/{id}/approve with missing required fields or invalid values (empty text, wrong format, out-of-range numbers, non-existing IDs). 3. Check the response and the data in the system. | D20: HTTP 400 (or 404 for a non-existing ID) with success = false and an error message / field errors. No data is created or changed. | E20: Master platform is running. The Workspace Admin account has permission for this action. The target resource exists. | F20: Failed | G20: 14/10/2026 | H20: Nguyễn Nhất Sinh | O20: Failing automated tests: MasterBillingServiceTest.approveInvoice_PendingInvoice_ProvisionsTenantAndSendsMail
A21: Update invoice status (PATCH /api/v1/master/invoices/{id}/status)
A22: MASTER-03-TC11 | B22: Verify update invoice status succeeds with valid input (PATCH /api/v1/master/invoices/{id}/status). | C22: 1. Log in as Workspace Admin. 2. Send PATCH /api/v1/master/invoices/{id}/status and a valid request body. 3. Check the response and the data shown in the system. | D22: HTTP 200. Response success = true; the changed fields are saved. | E22: Master platform is running. The Workspace Admin account has permission for this action. The target resource exists. | F22: Failed | G22: 14/10/2026 | H22: Nguyễn Nhất Sinh | O22: Failing automated tests: MasterBillingServiceTest.approveInvoice_PendingInvoice_ProvisionsTenantAndSendsMail
A23: MASTER-03-TC12 | B23: Verify update invoice status rejects invalid input (PATCH /api/v1/master/invoices/{id}/status). | C23: 1. Log in as Workspace Admin. 2. Send PATCH /api/v1/master/invoices/{id}/status with missing required fields or invalid values (empty text, wrong format, out-of-range numbers, non-existing IDs). 3. Check the response and the data in the system. | D23: HTTP 400 (or 404 for a non-existing ID) with success = false and an error message / field errors. No data is created or changed. | E23: Master platform is running. The Workspace Admin account has permission for this action. The target resource exists. | F23: Failed | G23: 14/10/2026 | H23: Nguyễn Nhất Sinh | O23: Failing automated tests: MasterBillingServiceTest.approveInvoice_PendingInvoice_ProvisionsTenantAndSendsMail
A24: Verify return (POST /api/v1/public/checkout/paypal/verify-return)
A25: MASTER-03-TC13 | B25: Verify verify return succeeds with valid input (POST /api/v1/public/checkout/paypal/verify-return). | C25: 1. Do not log in (public endpoint). 2. Send POST /api/v1/public/checkout/paypal/verify-return and a valid request body. 3. Check the response and the data shown in the system. | D25: HTTP 200/201. Response success = true; the record/action is saved and returned in the response. | E25: Master platform is running. | F25: Failed | G25: 14/10/2026 | H25: Nguyễn Nhất Sinh | O25: Failing automated tests: MasterBillingServiceTest.approveInvoice_PendingInvoice_ProvisionsTenantAndSendsMail
A26: MASTER-03-TC14 | B26: Verify verify return rejects invalid input (POST /api/v1/public/checkout/paypal/verify-return). | C26: 1. Do not log in (public endpoint). 2. Send POST /api/v1/public/checkout/paypal/verify-return with missing required fields or invalid values (empty text, wrong format, out-of-range numbers, non-existing IDs). 3. Check the response and the data in the system. | D26: HTTP 400 (or 404 for a non-existing ID) with success = false and an error message / field errors. No data is created or changed. | E26: Master platform is running. | F26: Failed | G26: 14/10/2026 | H26: Nguyễn Nhất Sinh | O26: Failing automated tests: MasterBillingServiceTest.approveInvoice_PendingInvoice_ProvisionsTenantAndSendsMail
A27: Handle se pay webhook (POST /api/v1/public/checkout/sepay-webhook)
A28: MASTER-03-TC15 | B28: Verify handle se pay webhook succeeds with valid input (POST /api/v1/public/checkout/sepay-webhook). | C28: 1. Do not log in (public endpoint). 2. Send POST /api/v1/public/checkout/sepay-webhook and a valid request body. 3. Check the response and the data shown in the system. | D28: HTTP 200/201. Response success = true; the record/action is saved and returned in the response. | E28: Master platform is running. | F28: Failed | G28: 14/10/2026 | H28: Nguyễn Nhất Sinh | O28: Failing automated tests: MasterBillingServiceTest.approveInvoice_PendingInvoice_ProvisionsTenantAndSendsMail
A29: MASTER-03-TC16 | B29: Verify handle se pay webhook rejects invalid input (POST /api/v1/public/checkout/sepay-webhook). | C29: 1. Do not log in (public endpoint). 2. Send POST /api/v1/public/checkout/sepay-webhook with missing required fields or invalid values (empty text, wrong format, out-of-range numbers, non-existing IDs). 3. Check the response and the data in the system. | D29: HTTP 400 (or 404 for a non-existing ID) with success = false and an error message / field errors. No data is created or changed. | E29: Master platform is running. | F29: Failed | G29: 14/10/2026 | H29: Nguyễn Nhất Sinh | O29: Failing automated tests: MasterBillingServiceTest.approveInvoice_PendingInvoice_ProvisionsTenantAndSendsMail
A30: Create payment url (POST /api/v1/public/checkout/vnpay/create-url)
A31: MASTER-03-TC17 | B31: Verify create payment url succeeds with valid input (POST /api/v1/public/checkout/vnpay/create-url). | C31: 1. Do not log in (public endpoint). 2. Send POST /api/v1/public/checkout/vnpay/create-url and a valid request body. 3. Check the response and the data shown in the system. | D31: HTTP 200/201. Response success = true; the record/action is saved and returned in the response. | E31: Master platform is running. | F31: Failed | G31: 14/10/2026 | H31: Nguyễn Nhất Sinh | O31: Failing automated tests: MasterBillingServiceTest.approveInvoice_PendingInvoice_ProvisionsTenantAndSendsMail
A32: MASTER-03-TC18 | B32: Verify create payment url rejects invalid input (POST /api/v1/public/checkout/vnpay/create-url). | C32: 1. Do not log in (public endpoint). 2. Send POST /api/v1/public/checkout/vnpay/create-url with missing required fields or invalid values (empty text, wrong format, out-of-range numbers, non-existing IDs). 3. Check the response and the data in the system. | D32: HTTP 400 (or 404 for a non-existing ID) with success = false and an error message / field errors. No data is created or changed. | E32: Master platform is running. | F32: Failed | G32: 14/10/2026 | H32: Nguyễn Nhất Sinh | O32: Failing automated tests: MasterBillingServiceTest.approveInvoice_PendingInvoice_ProvisionsTenantAndSendsMail
A33: Handle ipn (GET /api/v1/public/checkout/vnpay/ipn)
A34: MASTER-03-TC19 | B34: Verify handle ipn succeeds with valid input (GET /api/v1/public/checkout/vnpay/ipn). | C34: 1. Do not log in (public endpoint). 2. Send GET /api/v1/public/checkout/vnpay/ipn. 3. Check the response and the data shown in the system. | D34: HTTP 200. Response success = true and contains the requested data. | E34: Master platform is running. | F34: Failed | G34: 14/10/2026 | H34: Nguyễn Nhất Sinh | O34: Failing automated tests: MasterBillingServiceTest.approveInvoice_PendingInvoice_ProvisionsTenantAndSendsMail
A35: Verify return (GET /api/v1/public/checkout/vnpay/verify-return)
A36: MASTER-03-TC20 | B36: Verify verify return succeeds with valid input (GET /api/v1/public/checkout/vnpay/verify-return). | C36: 1. Do not log in (public endpoint). 2. Send GET /api/v1/public/checkout/vnpay/verify-return. 3. Check the response and the data shown in the system. | D36: HTTP 200. Response success = true and contains the requested data. | E36: Master platform is running. | F36: Failed | G36: 14/10/2026 | H36: Nguyễn Nhất Sinh | O36: Failing automated tests: MasterBillingServiceTest.approveInvoice_PendingInvoice_ProvisionsTenantAndSendsMail
A37: Handle se pay webhook (POST /api/v1/public/sepay/webhook)
A38: MASTER-03-TC21 | B38: Verify handle se pay webhook succeeds with valid input (POST /api/v1/public/sepay/webhook). | C38: 1. Do not log in (public endpoint). 2. Send POST /api/v1/public/sepay/webhook and a valid request body. 3. Check the response and the data shown in the system. | D38: HTTP 200/201. Response success = true; the record/action is saved and returned in the response. | E38: Master platform is running. | F38: Failed | G38: 14/10/2026 | H38: Nguyễn Nhất Sinh | O38: Failing automated tests: MasterBillingServiceTest.approveInvoice_PendingInvoice_ProvisionsTenantAndSendsMail
A39: MASTER-03-TC22 | B39: Verify handle se pay webhook rejects invalid input (POST /api/v1/public/sepay/webhook). | C39: 1. Do not log in (public endpoint). 2. Send POST /api/v1/public/sepay/webhook with missing required fields or invalid values (empty text, wrong format, out-of-range numbers, non-existing IDs). 3. Check the response and the data in the system. | D39: HTTP 400 (or 404 for a non-existing ID) with success = false and an error message / field errors. No data is created or changed. | E39: Master platform is running. | F39: Failed | G39: 14/10/2026 | H39: Nguyễn Nhất Sinh | O39: Failing automated tests: MasterBillingServiceTest.approveInvoice_PendingInvoice_ProvisionsTenantAndSendsMail
A40: Security & tenant isolation
A41: MASTER-03-TC23 | B41: Verify platform admin APIs reject unauthenticated requests and tenant users. | C41: 1. Send GET /api/v1/master/invoices without an Authorization header. 2. Send the same request with a valid token of a tenant user (e.g. Tenant Admin). | D41: Step 1: HTTP 401, code UNAUTHORIZED. Step 2: HTTP 403, code FORBIDDEN (requires WORKSPACE_ADMIN). | E41: A tenant user account exists. | F41: Failed | G41: 14/10/2026 | H41: Nguyễn Nhất Sinh | O41: Failing automated tests: MasterBillingServiceTest.approveInvoice_PendingInvoice_ProvisionsTenantAndSendsMail
A42: MASTER-03-TC24 | B42: Verify a Workspace Admin token cannot be used to read tenant data through tenant APIs. | C42: 1. Log in as Workspace Admin. 2. Call a tenant API (e.g. GET /api/v1/jobs) with header X-Tenant-ID = tenant A using the master token. | D42: The request is rejected (HTTP 401/403) and no tenant data is returned. | E42: Workspace Admin account exists; tenant A has data. | F42: Failed | G42: 14/10/2026 | H42: Nguyễn Nhất Sinh | O42: Failing automated tests: MasterBillingServiceTest.approveInvoice_PendingInvoice_ProvisionsTenantAndSendsMail

Sheet MASTER-04
A2: Feature | B2: Self-serve Checkout & Click-wrap Legal Consent (Decree 13/2023/ND-CP) | R2: Passed
A3: Test requirement | B3: Verify the business rules and APIs of MASTER-04 - Self-serve Checkout & Click-wrap Legal Consent (Decree 13/2023/ND-CP) as specified in docs/features/Master-Platform/Checkout-Clickwrap-Consent.md. | R3: Failed
A4: Number of TCs | B4: =COUNTIF(A11:A2000,"*-TC*") -> 6 | R4: Pending
A5: Testing Round | B5: Passed | C5: Failed | D5: Pending | E5: N/A | R5: N/A
A6: Round 1 | B6: =COUNTIF($F$11:$F$2000,B$5) -> 0 | C6: =COUNTIF($F$11:$F$2000,C$5) -> 4 | D6: =COUNTIF($F$11:$F$2000,D$5) -> 0 | E6: =COUNTIF($F$11:$F$2000,E$5) -> 2
A7: Round 2 | B7: =COUNTIF($I$11:$I$2000,B$5) -> 0 | C7: =COUNTIF($I$11:$I$2000,C$5) -> 0 | D7: =COUNTIF($I$11:$I$2000,D$5) -> 0 | E7: =COUNTIF($I$11:$I$2000,E$5) -> 0
A8: Round 3 | B8: =COUNTIF($L$11:$L$2000,B$5) -> 0 | C8: =COUNTIF($L$11:$L$2000,C$5) -> 0 | D8: =COUNTIF($L$11:$L$2000,D$5) -> 0 | E8: =COUNTIF($L$11:$L$2000,E$5) -> 0
A10: Test Case ID | B10: Test Case Description | C10: Test Case Procedure | D10: Expected Results | E10: Pre-conditions | F10: Round 1 | G10: Test date | H10: Tester | I10: Round 2 | J10: Test date | K10: Tester | L10: Round 3 | M10: Test date | N10: Tester | O10: Note
A11: Submit checkout (POST /api/v1/public/checkout)
A12: MASTER-04-TC04 | B12: Verify submit checkout succeeds with valid input (POST /api/v1/public/checkout). | C12: 1. Do not log in (public endpoint). 2. Send POST /api/v1/public/checkout and a valid request body. 3. Check the response and the data shown in the system. | D12: HTTP 200/201. Response success = true; the record/action is saved and returned in the response. | E12: Master platform is running. | F12: Failed | G12: 14/10/2026 | H12: Nguyễn Nhất Sinh | O12: Failing automated tests: MasterBillingServiceTest.approveInvoice_PendingInvoice_ProvisionsTenantAndSendsMail, PublicCheckoutControllerTest.getPublicPlans_ReturnsActivePlansWithVndPricing
A13: MASTER-04-TC05 | B13: Verify submit checkout rejects invalid input (POST /api/v1/public/checkout). | C13: 1. Do not log in (public endpoint). 2. Send POST /api/v1/public/checkout with missing required fields or invalid values (empty text, wrong format, out-of-range numbers, non-existing IDs). 3. Check the response and the data in the system. | D13: HTTP 400 (or 404 for a non-existing ID) with success = false and an error message / field errors. No data is created or changed. | E13: Master platform is running. | F13: Failed | G13: 14/10/2026 | H13: Nguyễn Nhất Sinh | O13: Failing automated tests: MasterBillingServiceTest.approveInvoice_PendingInvoice_ProvisionsTenantAndSendsMail, PublicCheckoutControllerTest.getPublicPlans_ReturnsActivePlansWithVndPricing
A14: Get public plans (GET /api/v1/public/checkout/plans)
A15: MASTER-04-TC06 | B15: Verify get public plans succeeds with valid input (GET /api/v1/public/checkout/plans). | C15: 1. Do not log in (public endpoint). 2. Send GET /api/v1/public/checkout/plans. 3. Check the response and the data shown in the system. | D15: HTTP 200. Response success = true and contains the requested data. | E15: Master platform is running. | F15: Failed | G15: 14/10/2026 | H15: Nguyễn Nhất Sinh | O15: Failing automated tests: MasterBillingServiceTest.approveInvoice_PendingInvoice_ProvisionsTenantAndSendsMail, PublicCheckoutControllerTest.getPublicPlans_ReturnsActivePlansWithVndPricing
A16: Invoice (GET /api/v1/public/checkout/status/{id})
A17: MASTER-04-TC07 | B17: Verify invoice succeeds with valid input (GET /api/v1/public/checkout/status/{id}). | C17: 1. Do not log in (public endpoint). 2. Send GET /api/v1/public/checkout/status/{id}. 3. Check the response and the data shown in the system. | D17: HTTP 200. Response success = true and contains the requested data. | E17: Master platform is running. The target resource exists. | F17: Failed | G17: 14/10/2026 | H17: Nguyễn Nhất Sinh | O17: Failing automated tests: MasterBillingServiceTest.approveInvoice_PendingInvoice_ProvisionsTenantAndSendsMail, PublicCheckoutControllerTest.getPublicPlans_ReturnsActivePlansWithVndPricing
A18: Security & tenant isolation
A19: MASTER-04-TC08 | B19: Verify platform admin APIs reject unauthenticated requests and tenant users. | C19: 1. Send without an Authorization header. 2. Send the same request with a valid token of a tenant user (e.g. Tenant Admin). | D19: Step 1: HTTP 401, code UNAUTHORIZED. Step 2: HTTP 403, code FORBIDDEN (requires WORKSPACE_ADMIN). | E19: A tenant user account exists. | F19: N/A | H19: Nguyễn Nhất Sinh | O19: All endpoints of this feature are public (permitAll).
A20: MASTER-04-TC09 | B20: Verify a Workspace Admin token cannot be used to read tenant data through tenant APIs. | C20: 1. Log in as Workspace Admin. 2. Call a tenant API (e.g. GET /api/v1/jobs) with header X-Tenant-ID = tenant A using the master token. | D20: The request is rejected (HTTP 401/403) and no tenant data is returned. | E20: Workspace Admin account exists; tenant A has data. | F20: N/A | H20: Nguyễn Nhất Sinh | O20: All endpoints of this feature are public (permitAll).

Sheet MASTER-05
A2: Feature | B2: B2B Electronic Contracts & Dropbox Sign API v3 Integration | R2: Passed
A3: Test requirement | B3: Verify the business rules and APIs of MASTER-05 - B2B Electronic Contracts & Dropbox Sign API v3 Integration as specified in docs/features/Master-Platform/B2B-EContracts-DropboxSign.md. | R3: Failed
A4: Number of TCs | B4: =COUNTIF(A11:A2000,"*-TC*") -> 23 | R4: Pending
A5: Testing Round | B5: Passed | C5: Failed | D5: Pending | E5: N/A | R5: N/A
A6: Round 1 | B6: =COUNTIF($F$11:$F$2000,B$5) -> 23 | C6: =COUNTIF($F$11:$F$2000,C$5) -> 0 | D6: =COUNTIF($F$11:$F$2000,D$5) -> 0 | E6: =COUNTIF($F$11:$F$2000,E$5) -> 0
A7: Round 2 | B7: =COUNTIF($I$11:$I$2000,B$5) -> 0 | C7: =COUNTIF($I$11:$I$2000,C$5) -> 0 | D7: =COUNTIF($I$11:$I$2000,D$5) -> 0 | E7: =COUNTIF($I$11:$I$2000,E$5) -> 0
A8: Round 3 | B8: =COUNTIF($L$11:$L$2000,B$5) -> 0 | C8: =COUNTIF($L$11:$L$2000,C$5) -> 0 | D8: =COUNTIF($L$11:$L$2000,D$5) -> 0 | E8: =COUNTIF($L$11:$L$2000,E$5) -> 0
A10: Test Case ID | B10: Test Case Description | C10: Test Case Procedure | D10: Expected Results | E10: Pre-conditions | F10: Round 1 | G10: Test date | H10: Tester | I10: Round 2 | J10: Test date | K10: Tester | L10: Round 3 | M10: Test date | N10: Tester | O10: Note
A11: Get all contracts (GET /api/v1/master/contracts)
A12: MASTER-05-TC04 | B12: Verify get all contracts succeeds with valid input (GET /api/v1/master/contracts). | C12: 1. Log in as Workspace Admin. 2. Send GET /api/v1/master/contracts. 3. Check the response and the data shown in the system. | D12: HTTP 200. Response success = true and contains the requested data. | E12: Master platform is running. The Workspace Admin account has permission for this action. | F12: Passed | G12: 11/10/2026 | H12: Nguyễn Nhất Sinh | O12: Verified by automated tests: DropboxSignContractServiceTest
A13: Create contract (POST /api/v1/master/contracts)
A14: MASTER-05-TC05 | B14: Verify create contract succeeds with valid input (POST /api/v1/master/contracts). | C14: 1. Log in as Workspace Admin. 2. Send POST /api/v1/master/contracts and a valid request body. 3. Check the response and the data shown in the system. | D14: HTTP 200/201. Response success = true; the record/action is saved and returned in the response. | E14: Master platform is running. The Workspace Admin account has permission for this action. | F14: Passed | G14: 11/10/2026 | H14: Nguyễn Nhất Sinh | O14: Verified by automated tests: DropboxSignContractServiceTest
A15: MASTER-05-TC06 | B15: Verify create contract rejects invalid input (POST /api/v1/master/contracts). | C15: 1. Log in as Workspace Admin. 2. Send POST /api/v1/master/contracts with missing required fields or invalid values (empty text, wrong format, out-of-range numbers, non-existing IDs). 3. Check the response and the data in the system. | D15: HTTP 400 (or 404 for a non-existing ID) with success = false and an error message / field errors. No data is created or changed. | E15: Master platform is running. The Workspace Admin account has permission for this action. | F15: Passed | G15: 11/10/2026 | H15: Nguyễn Nhất Sinh | O15: Verified by automated tests: DropboxSignContractServiceTest
A16: Delete contract (DELETE /api/v1/master/contracts/{id})
A17: MASTER-05-TC07 | B17: Verify delete contract succeeds with valid input (DELETE /api/v1/master/contracts/{id}). | C17: 1. Log in as Workspace Admin. 2. Send DELETE /api/v1/master/contracts/{id}. 3. Check the response and the data shown in the system. | D17: HTTP 200/204. The record is removed (or archived) and no longer appears in lists. | E17: Master platform is running. The Workspace Admin account has permission for this action. The target resource exists. | F17: Passed | G17: 11/10/2026 | H17: Nguyễn Nhất Sinh | O17: Verified by automated tests: DropboxSignContractServiceTest
A18: MASTER-05-TC08 | B18: Verify delete contract rejects invalid input (DELETE /api/v1/master/contracts/{id}). | C18: 1. Log in as Workspace Admin. 2. Send DELETE /api/v1/master/contracts/{id} with missing required fields or invalid values (empty text, wrong format, out-of-range numbers, non-existing IDs). 3. Check the response and the data in the system. | D18: HTTP 400 (or 404 for a non-existing ID) with success = false and an error message / field errors. No data is created or changed. | E18: Master platform is running. The Workspace Admin account has permission for this action. The target resource exists. | F18: Passed | G18: 11/10/2026 | H18: Nguyễn Nhất Sinh | O18: Verified by automated tests: DropboxSignContractServiceTest
A19: Get contract by id (GET /api/v1/master/contracts/{id})
A20: MASTER-05-TC09 | B20: Verify get contract by id succeeds with valid input (GET /api/v1/master/contracts/{id}). | C20: 1. Log in as Workspace Admin. 2. Send GET /api/v1/master/contracts/{id}. 3. Check the response and the data shown in the system. | D20: HTTP 200. Response success = true and contains the requested data. | E20: Master platform is running. The Workspace Admin account has permission for this action. The target resource exists. | F20: Passed | G20: 11/10/2026 | H20: Nguyễn Nhất Sinh | O20: Verified by automated tests: DropboxSignContractServiceTest
A21: Update contract (PUT /api/v1/master/contracts/{id})
A22: MASTER-05-TC10 | B22: Verify update contract succeeds with valid input (PUT /api/v1/master/contracts/{id}). | C22: 1. Log in as Workspace Admin. 2. Send PUT /api/v1/master/contracts/{id} and a valid request body. 3. Check the response and the data shown in the system. | D22: HTTP 200. Response success = true; the changes are saved and returned. | E22: Master platform is running. The Workspace Admin account has permission for this action. The target resource exists. | F22: Passed | G22: 11/10/2026 | H22: Nguyễn Nhất Sinh | O22: Verified by automated tests: DropboxSignContractServiceTest
A23: MASTER-05-TC11 | B23: Verify update contract rejects invalid input (PUT /api/v1/master/contracts/{id}). | C23: 1. Log in as Workspace Admin. 2. Send PUT /api/v1/master/contracts/{id} with missing required fields or invalid values (empty text, wrong format, out-of-range numbers, non-existing IDs). 3. Check the response and the data in the system. | D23: HTTP 400 (or 404 for a non-existing ID) with success = false and an error message / field errors. No data is created or changed. | E23: Master platform is running. The Workspace Admin account has permission for this action. The target resource exists. | F23: Passed | G23: 11/10/2026 | H23: Nguyễn Nhất Sinh | O23: Verified by automated tests: DropboxSignContractServiceTest
A24: Trail (GET /api/v1/master/contracts/{id}/pdf)
A25: MASTER-05-TC12 | B25: Verify trail succeeds with valid input (GET /api/v1/master/contracts/{id}/pdf). | C25: 1. Log in as Workspace Admin. 2. Send GET /api/v1/master/contracts/{id}/pdf. 3. Check the response and the data shown in the system. | D25: HTTP 200. Response success = true and contains the requested data. | E25: Master platform is running. The Workspace Admin account has permission for this action. The target resource exists. | F25: Passed | G25: 11/10/2026 | H25: Nguyễn Nhất Sinh | O25: Verified by automated tests: DropboxSignContractServiceTest
A26: Send contract (POST /api/v1/master/contracts/{id}/send)
A27: MASTER-05-TC13 | B27: Verify send contract succeeds with valid input (POST /api/v1/master/contracts/{id}/send). | C27: 1. Log in as Workspace Admin. 2. Send POST /api/v1/master/contracts/{id}/send and a valid request body. 3. Check the response and the data shown in the system. | D27: HTTP 200/201. Response success = true; the record/action is saved and returned in the response. | E27: Master platform is running. The Workspace Admin account has permission for this action. The target resource exists. | F27: Passed | G27: 11/10/2026 | H27: Nguyễn Nhất Sinh | O27: Verified by automated tests: DropboxSignContractServiceTest
A28: MASTER-05-TC14 | B28: Verify send contract rejects invalid input (POST /api/v1/master/contracts/{id}/send). | C28: 1. Log in as Workspace Admin. 2. Send POST /api/v1/master/contracts/{id}/send with missing required fields or invalid values (empty text, wrong format, out-of-range numbers, non-existing IDs). 3. Check the response and the data in the system. | D28: HTTP 400 (or 404 for a non-existing ID) with success = false and an error message / field errors. No data is created or changed. | E28: Master platform is running. The Workspace Admin account has permission for this action. The target resource exists. | F28: Passed | G28: 11/10/2026 | H28: Nguyễn Nhất Sinh | O28: Verified by automated tests: DropboxSignContractServiceTest
A29: Contract (PATCH /api/v1/master/contracts/{id}/status)
A30: MASTER-05-TC15 | B30: Verify contract succeeds with valid input (PATCH /api/v1/master/contracts/{id}/status). | C30: 1. Log in as Workspace Admin. 2. Send PATCH /api/v1/master/contracts/{id}/status and a valid request body. 3. Check the response and the data shown in the system. | D30: HTTP 200. Response success = true; the changed fields are saved. | E30: Master platform is running. The Workspace Admin account has permission for this action. The target resource exists. | F30: Passed | G30: 11/10/2026 | H30: Nguyễn Nhất Sinh | O30: Verified by automated tests: DropboxSignContractServiceTest
A31: MASTER-05-TC16 | B31: Verify contract rejects invalid input (PATCH /api/v1/master/contracts/{id}/status). | C31: 1. Log in as Workspace Admin. 2. Send PATCH /api/v1/master/contracts/{id}/status with missing required fields or invalid values (empty text, wrong format, out-of-range numbers, non-existing IDs). 3. Check the response and the data in the system. | D31: HTTP 400 (or 404 for a non-existing ID) with success = false and an error message / field errors. No data is created or changed. | E31: Master platform is running. The Workspace Admin account has permission for this action. The target resource exists. | F31: Passed | G31: 11/10/2026 | H31: Nguyễn Nhất Sinh | O31: Verified by automated tests: DropboxSignContractServiceTest
A32: Sync esign status (POST /api/v1/master/contracts/{id}/sync-esign)
A33: MASTER-05-TC17 | B33: Verify sync esign status succeeds with valid input (POST /api/v1/master/contracts/{id}/sync-esign). | C33: 1. Log in as Workspace Admin. 2. Send POST /api/v1/master/contracts/{id}/sync-esign and a valid request body. 3. Check the response and the data shown in the system. | D33: HTTP 200/201. Response success = true; the record/action is saved and returned in the response. | E33: Master platform is running. The Workspace Admin account has permission for this action. The target resource exists. | F33: Passed | G33: 11/10/2026 | H33: Nguyễn Nhất Sinh | O33: Verified by automated tests: DropboxSignContractServiceTest
A34: MASTER-05-TC18 | B34: Verify sync esign status rejects invalid input (POST /api/v1/master/contracts/{id}/sync-esign). | C34: 1. Log in as Workspace Admin. 2. Send POST /api/v1/master/contracts/{id}/sync-esign with missing required fields or invalid values (empty text, wrong format, out-of-range numbers, non-existing IDs). 3. Check the response and the data in the system. | D34: HTTP 400 (or 404 for a non-existing ID) with success = false and an error message / field errors. No data is created or changed. | E34: Master platform is running. The Workspace Admin account has permission for this action. The target resource exists. | F34: Passed | G34: 11/10/2026 | H34: Nguyễn Nhất Sinh | O34: Verified by automated tests: DropboxSignContractServiceTest
A35: Events (POST /api/v1/public/contracts/webhook/dropbox-sign)
A36: MASTER-05-TC19 | B36: Verify events succeeds with valid input (POST /api/v1/public/contracts/webhook/dropbox-sign). | C36: 1. Do not log in (public endpoint). 2. Send POST /api/v1/public/contracts/webhook/dropbox-sign and a valid request body. 3. Check the response and the data shown in the system. | D36: HTTP 200/201. Response success = true; the record/action is saved and returned in the response. | E36: Master platform is running. | F36: Passed | G36: 11/10/2026 | H36: Nguyễn Nhất Sinh | O36: Verified by automated tests: DropboxSignContractServiceTest
A37: MASTER-05-TC20 | B37: Verify events rejects invalid input (POST /api/v1/public/contracts/webhook/dropbox-sign). | C37: 1. Do not log in (public endpoint). 2. Send POST /api/v1/public/contracts/webhook/dropbox-sign with missing required fields or invalid values (empty text, wrong format, out-of-range numbers, non-existing IDs). 3. Check the response and the data in the system. | D37: HTTP 400 (or 404 for a non-existing ID) with success = false and an error message / field errors. No data is created or changed. | E37: Master platform is running. | F37: Passed | G37: 11/10/2026 | H37: Nguyễn Nhất Sinh | O37: Verified by automated tests: DropboxSignContractServiceTest
A38: Get contract by token (GET /api/v1/public/contracts/{id})
A39: MASTER-05-TC21 | B39: Verify get contract by token succeeds with valid input (GET /api/v1/public/contracts/{id}). | C39: 1. Do not log in (public endpoint). 2. Send GET /api/v1/public/contracts/{id}. 3. Check the response and the data shown in the system. | D39: HTTP 200. Response success = true and contains the requested data. | E39: Master platform is running. The target resource exists. | F39: Passed | G39: 11/10/2026 | H39: Nguyễn Nhất Sinh | O39: Verified by automated tests: DropboxSignContractServiceTest
A40: Trail (GET /api/v1/public/contracts/{id}/pdf)
A41: MASTER-05-TC22 | B41: Verify trail succeeds with valid input (GET /api/v1/public/contracts/{id}/pdf). | C41: 1. Do not log in (public endpoint). 2. Send GET /api/v1/public/contracts/{id}/pdf. 3. Check the response and the data shown in the system. | D41: HTTP 200. Response success = true and contains the requested data. | E41: Master platform is running. The target resource exists. | F41: Passed | G41: 11/10/2026 | H41: Nguyễn Nhất Sinh | O41: Verified by automated tests: DropboxSignContractServiceTest
A42: Sync esign by token (POST /api/v1/public/contracts/{id}/sync-esign)
A43: MASTER-05-TC23 | B43: Verify sync esign by token succeeds with valid input (POST /api/v1/public/contracts/{id}/sync-esign). | C43: 1. Do not log in (public endpoint). 2. Send POST /api/v1/public/contracts/{id}/sync-esign and a valid request body. 3. Check the response and the data shown in the system. | D43: HTTP 200/201. Response success = true; the record/action is saved and returned in the response. | E43: Master platform is running. The target resource exists. | F43: Passed | G43: 11/10/2026 | H43: Nguyễn Nhất Sinh | O43: Verified by automated tests: DropboxSignContractServiceTest
A44: MASTER-05-TC24 | B44: Verify sync esign by token rejects invalid input (POST /api/v1/public/contracts/{id}/sync-esign). | C44: 1. Do not log in (public endpoint). 2. Send POST /api/v1/public/contracts/{id}/sync-esign with missing required fields or invalid values (empty text, wrong format, out-of-range numbers, non-existing IDs). 3. Check the response and the data in the system. | D44: HTTP 400 (or 404 for a non-existing ID) with success = false and an error message / field errors. No data is created or changed. | E44: Master platform is running. The target resource exists. | F44: Passed | G44: 11/10/2026 | H44: Nguyễn Nhất Sinh | O44: Verified by automated tests: DropboxSignContractServiceTest
A45: Security & tenant isolation
A46: MASTER-05-TC25 | B46: Verify platform admin APIs reject unauthenticated requests and tenant users. | C46: 1. Send GET /api/v1/master/contracts without an Authorization header. 2. Send the same request with a valid token of a tenant user (e.g. Tenant Admin). | D46: Step 1: HTTP 401, code UNAUTHORIZED. Step 2: HTTP 403, code FORBIDDEN (requires WORKSPACE_ADMIN). | E46: A tenant user account exists. | F46: Passed | G46: 11/10/2026 | H46: Nguyễn Nhất Sinh | O46: Verified by automated tests: DropboxSignContractServiceTest
A47: MASTER-05-TC26 | B47: Verify a Workspace Admin token cannot be used to read tenant data through tenant APIs. | C47: 1. Log in as Workspace Admin. 2. Call a tenant API (e.g. GET /api/v1/jobs) with header X-Tenant-ID = tenant A using the master token. | D47: The request is rejected (HTTP 401/403) and no tenant data is returned. | E47: Workspace Admin account exists; tenant A has data. | F47: Passed | G47: 11/10/2026 | H47: Nguyễn Nhất Sinh | O47: Verified by automated tests: DropboxSignContractServiceTest

Sheet MASTER-06
A2: Feature | B2: Enterprise Sales Leads & 4-Step B2B Deal Wizard | R2: Passed
A3: Test requirement | B3: Verify the business rules and APIs of MASTER-06 - Enterprise Sales Leads & 4-Step B2B Deal Wizard as specified in docs/features/Master-Platform/Sales-Leads-B2B-Deal-Wizard.md. | R3: Failed
A4: Number of TCs | B4: =COUNTIF(A11:A2000,"*-TC*") -> 8 | R4: Pending
A5: Testing Round | B5: Passed | C5: Failed | D5: Pending | E5: N/A | R5: N/A
A6: Round 1 | B6: =COUNTIF($F$11:$F$2000,B$5) -> 0 | C6: =COUNTIF($F$11:$F$2000,C$5) -> 0 | D6: =COUNTIF($F$11:$F$2000,D$5) -> 8 | E6: =COUNTIF($F$11:$F$2000,E$5) -> 0
A7: Round 2 | B7: =COUNTIF($I$11:$I$2000,B$5) -> 0 | C7: =COUNTIF($I$11:$I$2000,C$5) -> 0 | D7: =COUNTIF($I$11:$I$2000,D$5) -> 0 | E7: =COUNTIF($I$11:$I$2000,E$5) -> 0
A8: Round 3 | B8: =COUNTIF($L$11:$L$2000,B$5) -> 0 | C8: =COUNTIF($L$11:$L$2000,C$5) -> 0 | D8: =COUNTIF($L$11:$L$2000,D$5) -> 0 | E8: =COUNTIF($L$11:$L$2000,E$5) -> 0
A10: Test Case ID | B10: Test Case Description | C10: Test Case Procedure | D10: Expected Results | E10: Pre-conditions | F10: Round 1 | G10: Test date | H10: Tester | I10: Round 2 | J10: Test date | K10: Tester | L10: Round 3 | M10: Test date | N10: Tester | O10: Note
A11: Get all requests (GET /api/v1/master/consultations)
A12: MASTER-06-TC04 | B12: Verify get all requests succeeds with valid input (GET /api/v1/master/consultations). | C12: 1. Log in as Workspace Admin. 2. Send GET /api/v1/master/consultations. 3. Check the response and the data shown in the system. | D12: HTTP 200. Response success = true and contains the requested data. | E12: Master platform is running. The Workspace Admin account has permission for this action. | F12: Pending | H12: Nguyễn Nhất Sinh | O12: Not tested: no automated test covers this feature yet.
A13: Create request (POST /api/v1/master/consultations)
A14: MASTER-06-TC05 | B14: Verify create request succeeds with valid input (POST /api/v1/master/consultations). | C14: 1. Do not log in (public endpoint). 2. Send POST /api/v1/master/consultations and a valid request body. 3. Check the response and the data shown in the system. | D14: HTTP 200/201. Response success = true; the record/action is saved and returned in the response. | E14: Master platform is running. | F14: Pending | H14: Nguyễn Nhất Sinh | O14: Not tested: no automated test covers this feature yet.
A15: MASTER-06-TC06 | B15: Verify create request rejects invalid input (POST /api/v1/master/consultations). | C15: 1. Do not log in (public endpoint). 2. Send POST /api/v1/master/consultations with missing required fields or invalid values (empty text, wrong format, out-of-range numbers, non-existing IDs). 3. Check the response and the data in the system. | D15: HTTP 400 (or 404 for a non-existing ID) with success = false and an error message / field errors. No data is created or changed. | E15: Master platform is running. | F15: Pending | H15: Nguyễn Nhất Sinh | O15: Not tested: no automated test covers this feature yet.
A16: Get request by id (GET /api/v1/master/consultations/{id})
A17: MASTER-06-TC07 | B17: Verify get request by id succeeds with valid input (GET /api/v1/master/consultations/{id}). | C17: 1. Log in as Workspace Admin. 2. Send GET /api/v1/master/consultations/{id}. 3. Check the response and the data shown in the system. | D17: HTTP 200. Response success = true and contains the requested data. | E17: Master platform is running. The Workspace Admin account has permission for this action. The target resource exists. | F17: Pending | H17: Nguyễn Nhất Sinh | O17: Not tested: no automated test covers this feature yet.
A18: Update status (PATCH /api/v1/master/consultations/{id}/status)
A19: MASTER-06-TC08 | B19: Verify update status succeeds with valid input (PATCH /api/v1/master/consultations/{id}/status). | C19: 1. Log in as Workspace Admin. 2. Send PATCH /api/v1/master/consultations/{id}/status and a valid request body. 3. Check the response and the data shown in the system. | D19: HTTP 200. Response success = true; the changed fields are saved. | E19: Master platform is running. The Workspace Admin account has permission for this action. The target resource exists. | F19: Pending | H19: Nguyễn Nhất Sinh | O19: Not tested: no automated test covers this feature yet.
A20: MASTER-06-TC09 | B20: Verify update status rejects invalid input (PATCH /api/v1/master/consultations/{id}/status). | C20: 1. Log in as Workspace Admin. 2. Send PATCH /api/v1/master/consultations/{id}/status with missing required fields or invalid values (empty text, wrong format, out-of-range numbers, non-existing IDs). 3. Check the response and the data in the system. | D20: HTTP 400 (or 404 for a non-existing ID) with success = false and an error message / field errors. No data is created or changed. | E20: Master platform is running. The Workspace Admin account has permission for this action. The target resource exists. | F20: Pending | H20: Nguyễn Nhất Sinh | O20: Not tested: no automated test covers this feature yet.
A21: Security & tenant isolation
A22: MASTER-06-TC10 | B22: Verify platform admin APIs reject unauthenticated requests and tenant users. | C22: 1. Send GET /api/v1/master/consultations without an Authorization header. 2. Send the same request with a valid token of a tenant user (e.g. Tenant Admin). | D22: Step 1: HTTP 401, code UNAUTHORIZED. Step 2: HTTP 403, code FORBIDDEN (requires WORKSPACE_ADMIN). | E22: A tenant user account exists. | F22: Pending | H22: Nguyễn Nhất Sinh | O22: Not tested: no automated test covers this feature yet.
A23: MASTER-06-TC11 | B23: Verify a Workspace Admin token cannot be used to read tenant data through tenant APIs. | C23: 1. Log in as Workspace Admin. 2. Call a tenant API (e.g. GET /api/v1/jobs) with header X-Tenant-ID = tenant A using the master token. | D23: The request is rejected (HTTP 401/403) and no tenant data is returned. | E23: Workspace Admin account exists; tenant A has data. | F23: Pending | H23: Nguyễn Nhất Sinh | O23: Not tested: no automated test covers this feature yet.

Sheet MASTER-07
A2: Feature | B2: AI Engine Governance, Model Routing & Token Cost Metering | R2: Passed
A3: Test requirement | B3: Verify the business rules and APIs of MASTER-07 - AI Engine Governance, Model Routing & Token Cost Metering as specified in docs/features/Master-Platform/AI-Governance-Metering.md. | R3: Failed
A4: Number of TCs | B4: =COUNTIF(A11:A2000,"*-TC*") -> 27 | R4: Pending
A5: Testing Round | B5: Passed | C5: Failed | D5: Pending | E5: N/A | R5: N/A
A6: Round 1 | B6: =COUNTIF($F$11:$F$2000,B$5) -> 0 | C6: =COUNTIF($F$11:$F$2000,C$5) -> 27 | D6: =COUNTIF($F$11:$F$2000,D$5) -> 0 | E6: =COUNTIF($F$11:$F$2000,E$5) -> 0
A7: Round 2 | B7: =COUNTIF($I$11:$I$2000,B$5) -> 0 | C7: =COUNTIF($I$11:$I$2000,C$5) -> 0 | D7: =COUNTIF($I$11:$I$2000,D$5) -> 0 | E7: =COUNTIF($I$11:$I$2000,E$5) -> 0
A8: Round 3 | B8: =COUNTIF($L$11:$L$2000,B$5) -> 0 | C8: =COUNTIF($L$11:$L$2000,C$5) -> 0 | D8: =COUNTIF($L$11:$L$2000,D$5) -> 0 | E8: =COUNTIF($L$11:$L$2000,E$5) -> 0
A10: Test Case ID | B10: Test Case Description | C10: Test Case Procedure | D10: Expected Results | E10: Pre-conditions | F10: Round 1 | G10: Test date | H10: Tester | I10: Round 2 | J10: Test date | K10: Tester | L10: Round 3 | M10: Test date | N10: Tester | O10: Note
A11: Get provider keys (GET /api/v1/master/ai/keys)
A12: MASTER-07-TC03 | B12: Verify get provider keys succeeds with valid input (GET /api/v1/master/ai/keys). | C12: 1. Log in as Workspace Admin. 2. Send GET /api/v1/master/ai/keys. 3. Check the response and the data shown in the system. | D12: HTTP 200. Response success = true and contains the requested data. | E12: Master platform is running. The Workspace Admin account has permission for this action. | F12: Failed | G12: 14/10/2026 | H12: Nguyễn Nhất Sinh | O12: Failing automated tests: MultiDatabaseIntegrationTest.authenticatedOnboardApiCreatesTenantAndRejectsDuplicateAliases
A13: Save provider key (POST /api/v1/master/ai/keys)
A14: MASTER-07-TC04 | B14: Verify save provider key succeeds with valid input (POST /api/v1/master/ai/keys). | C14: 1. Log in as Workspace Admin. 2. Send POST /api/v1/master/ai/keys and a valid request body. 3. Check the response and the data shown in the system. | D14: HTTP 200/201. Response success = true; the record/action is saved and returned in the response. | E14: Master platform is running. The Workspace Admin account has permission for this action. | F14: Failed | G14: 14/10/2026 | H14: Nguyễn Nhất Sinh | O14: Failing automated tests: MultiDatabaseIntegrationTest.authenticatedOnboardApiCreatesTenantAndRejectsDuplicateAliases
A15: MASTER-07-TC05 | B15: Verify save provider key rejects invalid input (POST /api/v1/master/ai/keys). | C15: 1. Log in as Workspace Admin. 2. Send POST /api/v1/master/ai/keys with missing required fields or invalid values (empty text, wrong format, out-of-range numbers, non-existing IDs). 3. Check the response and the data in the system. | D15: HTTP 400 (or 404 for a non-existing ID) with success = false and an error message / field errors. No data is created or changed. | E15: Master platform is running. The Workspace Admin account has permission for this action. | F15: Failed | G15: 14/10/2026 | H15: Nguyễn Nhất Sinh | O15: Failing automated tests: MultiDatabaseIntegrationTest.authenticatedOnboardApiCreatesTenantAndRejectsDuplicateAliases
A16: Delete provider key (DELETE /api/v1/master/ai/keys/{id})
A17: MASTER-07-TC06 | B17: Verify delete provider key succeeds with valid input (DELETE /api/v1/master/ai/keys/{id}). | C17: 1. Log in as Workspace Admin. 2. Send DELETE /api/v1/master/ai/keys/{id}. 3. Check the response and the data shown in the system. | D17: HTTP 200/204. The record is removed (or archived) and no longer appears in lists. | E17: Master platform is running. The Workspace Admin account has permission for this action. The target resource exists. | F17: Failed | G17: 14/10/2026 | H17: Nguyễn Nhất Sinh | O17: Failing automated tests: MultiDatabaseIntegrationTest.authenticatedOnboardApiCreatesTenantAndRejectsDuplicateAliases
A18: MASTER-07-TC07 | B18: Verify delete provider key rejects invalid input (DELETE /api/v1/master/ai/keys/{id}). | C18: 1. Log in as Workspace Admin. 2. Send DELETE /api/v1/master/ai/keys/{id} with missing required fields or invalid values (empty text, wrong format, out-of-range numbers, non-existing IDs). 3. Check the response and the data in the system. | D18: HTTP 400 (or 404 for a non-existing ID) with success = false and an error message / field errors. No data is created or changed. | E18: Master platform is running. The Workspace Admin account has permission for this action. The target resource exists. | F18: Failed | G18: 14/10/2026 | H18: Nguyễn Nhất Sinh | O18: Failing automated tests: MultiDatabaseIntegrationTest.authenticatedOnboardApiCreatesTenantAndRejectsDuplicateAliases
A19: Get model pricings (GET /api/v1/master/ai/pricings)
A20: MASTER-07-TC08 | B20: Verify get model pricings succeeds with valid input (GET /api/v1/master/ai/pricings). | C20: 1. Log in as Workspace Admin. 2. Send GET /api/v1/master/ai/pricings. 3. Check the response and the data shown in the system. | D20: HTTP 200. Response success = true and contains the requested data. | E20: Master platform is running. The Workspace Admin account has permission for this action. | F20: Failed | G20: 14/10/2026 | H20: Nguyễn Nhất Sinh | O20: Failing automated tests: MultiDatabaseIntegrationTest.authenticatedOnboardApiCreatesTenantAndRejectsDuplicateAliases
A21: Save model pricing (POST /api/v1/master/ai/pricings)
A22: MASTER-07-TC09 | B22: Verify save model pricing succeeds with valid input (POST /api/v1/master/ai/pricings). | C22: 1. Log in as Workspace Admin. 2. Send POST /api/v1/master/ai/pricings and a valid request body. 3. Check the response and the data shown in the system. | D22: HTTP 200/201. Response success = true; the record/action is saved and returned in the response. | E22: Master platform is running. The Workspace Admin account has permission for this action. | F22: Failed | G22: 14/10/2026 | H22: Nguyễn Nhất Sinh | O22: Failing automated tests: MultiDatabaseIntegrationTest.authenticatedOnboardApiCreatesTenantAndRejectsDuplicateAliases
A23: MASTER-07-TC10 | B23: Verify save model pricing rejects invalid input (POST /api/v1/master/ai/pricings). | C23: 1. Log in as Workspace Admin. 2. Send POST /api/v1/master/ai/pricings with missing required fields or invalid values (empty text, wrong format, out-of-range numbers, non-existing IDs). 3. Check the response and the data in the system. | D23: HTTP 400 (or 404 for a non-existing ID) with success = false and an error message / field errors. No data is created or changed. | E23: Master platform is running. The Workspace Admin account has permission for this action. | F23: Failed | G23: 14/10/2026 | H23: Nguyễn Nhất Sinh | O23: Failing automated tests: MultiDatabaseIntegrationTest.authenticatedOnboardApiCreatesTenantAndRejectsDuplicateAliases
A24: Delete model pricing (DELETE /api/v1/master/ai/pricings/{id})
A25: MASTER-07-TC11 | B25: Verify delete model pricing succeeds with valid input (DELETE /api/v1/master/ai/pricings/{id}). | C25: 1. Log in as Workspace Admin. 2. Send DELETE /api/v1/master/ai/pricings/{id}. 3. Check the response and the data shown in the system. | D25: HTTP 200/204. The record is removed (or archived) and no longer appears in lists. | E25: Master platform is running. The Workspace Admin account has permission for this action. The target resource exists. | F25: Failed | G25: 14/10/2026 | H25: Nguyễn Nhất Sinh | O25: Failing automated tests: MultiDatabaseIntegrationTest.authenticatedOnboardApiCreatesTenantAndRejectsDuplicateAliases
A26: MASTER-07-TC12 | B26: Verify delete model pricing rejects invalid input (DELETE /api/v1/master/ai/pricings/{id}). | C26: 1. Log in as Workspace Admin. 2. Send DELETE /api/v1/master/ai/pricings/{id} with missing required fields or invalid values (empty text, wrong format, out-of-range numbers, non-existing IDs). 3. Check the response and the data in the system. | D26: HTTP 400 (or 404 for a non-existing ID) with success = false and an error message / field errors. No data is created or changed. | E26: Master platform is running. The Workspace Admin account has permission for this action. The target resource exists. | F26: Failed | G26: 14/10/2026 | H26: Nguyễn Nhất Sinh | O26: Failing automated tests: MultiDatabaseIntegrationTest.authenticatedOnboardApiCreatesTenantAndRejectsDuplicateAliases
A27: Get tenant ai quotas (GET /api/v1/master/ai/quotas)
A28: MASTER-07-TC13 | B28: Verify get tenant ai quotas succeeds with valid input (GET /api/v1/master/ai/quotas). | C28: 1. Log in as Workspace Admin. 2. Send GET /api/v1/master/ai/quotas. 3. Check the response and the data shown in the system. | D28: HTTP 200. Response success = true and contains the requested data. | E28: Master platform is running. The Workspace Admin account has permission for this action. | F28: Failed | G28: 14/10/2026 | H28: Nguyễn Nhất Sinh | O28: Failing automated tests: MultiDatabaseIntegrationTest.authenticatedOnboardApiCreatesTenantAndRejectsDuplicateAliases
A29: Update tenant ai quota (PUT /api/v1/master/ai/quotas/{id})
A30: MASTER-07-TC14 | B30: Verify update tenant ai quota succeeds with valid input (PUT /api/v1/master/ai/quotas/{id}). | C30: 1. Log in as Workspace Admin. 2. Send PUT /api/v1/master/ai/quotas/{id} and a valid request body. 3. Check the response and the data shown in the system. | D30: HTTP 200. Response success = true; the changes are saved and returned. | E30: Master platform is running. The Workspace Admin account has permission for this action. The target resource exists. | F30: Failed | G30: 14/10/2026 | H30: Nguyễn Nhất Sinh | O30: Failing automated tests: MultiDatabaseIntegrationTest.authenticatedOnboardApiCreatesTenantAndRejectsDuplicateAliases
A31: MASTER-07-TC15 | B31: Verify update tenant ai quota rejects invalid input (PUT /api/v1/master/ai/quotas/{id}). | C31: 1. Log in as Workspace Admin. 2. Send PUT /api/v1/master/ai/quotas/{id} with missing required fields or invalid values (empty text, wrong format, out-of-range numbers, non-existing IDs). 3. Check the response and the data in the system. | D31: HTTP 400 (or 404 for a non-existing ID) with success = false and an error message / field errors. No data is created or changed. | E31: Master platform is running. The Workspace Admin account has permission for this action. The target resource exists. | F31: Failed | G31: 14/10/2026 | H31: Nguyễn Nhất Sinh | O31: Failing automated tests: MultiDatabaseIntegrationTest.authenticatedOnboardApiCreatesTenantAndRejectsDuplicateAliases
A32: Config (GET /api/v1/master/ai/rate-limit)
A33: MASTER-07-TC16 | B33: Verify config succeeds with valid input (GET /api/v1/master/ai/rate-limit). | C33: 1. Log in as Workspace Admin. 2. Send GET /api/v1/master/ai/rate-limit. 3. Check the response and the data shown in the system. | D33: HTTP 200. Response success = true and contains the requested data. | E33: Master platform is running. The Workspace Admin account has permission for this action. | F33: Failed | G33: 14/10/2026 | H33: Nguyễn Nhất Sinh | O33: Failing automated tests: MultiDatabaseIntegrationTest.authenticatedOnboardApiCreatesTenantAndRejectsDuplicateAliases
A34: Config (PUT /api/v1/master/ai/rate-limit)
A35: MASTER-07-TC17 | B35: Verify config succeeds with valid input (PUT /api/v1/master/ai/rate-limit). | C35: 1. Log in as Workspace Admin. 2. Send PUT /api/v1/master/ai/rate-limit and a valid request body. 3. Check the response and the data shown in the system. | D35: HTTP 200. Response success = true; the changes are saved and returned. | E35: Master platform is running. The Workspace Admin account has permission for this action. | F35: Failed | G35: 14/10/2026 | H35: Nguyễn Nhất Sinh | O35: Failing automated tests: MultiDatabaseIntegrationTest.authenticatedOnboardApiCreatesTenantAndRejectsDuplicateAliases
A36: MASTER-07-TC18 | B36: Verify config rejects invalid input (PUT /api/v1/master/ai/rate-limit). | C36: 1. Log in as Workspace Admin. 2. Send PUT /api/v1/master/ai/rate-limit with missing required fields or invalid values (empty text, wrong format, out-of-range numbers, non-existing IDs). 3. Check the response and the data in the system. | D36: HTTP 400 (or 404 for a non-existing ID) with success = false and an error message / field errors. No data is created or changed. | E36: Master platform is running. The Workspace Admin account has permission for this action. | F36: Failed | G36: 14/10/2026 | H36: Nguyễn Nhất Sinh | O36: Failing automated tests: MultiDatabaseIntegrationTest.authenticatedOnboardApiCreatesTenantAndRejectsDuplicateAliases
A37: Get task configs (GET /api/v1/master/ai/tasks)
A38: MASTER-07-TC19 | B38: Verify get task configs succeeds with valid input (GET /api/v1/master/ai/tasks). | C38: 1. Log in as Workspace Admin. 2. Send GET /api/v1/master/ai/tasks. 3. Check the response and the data shown in the system. | D38: HTTP 200. Response success = true and contains the requested data. | E38: Master platform is running. The Workspace Admin account has permission for this action. | F38: Failed | G38: 14/10/2026 | H38: Nguyễn Nhất Sinh | O38: Failing automated tests: MultiDatabaseIntegrationTest.authenticatedOnboardApiCreatesTenantAndRejectsDuplicateAliases
A39: Update task config (PUT /api/v1/master/ai/tasks/{id})
A40: MASTER-07-TC20 | B40: Verify update task config succeeds with valid input (PUT /api/v1/master/ai/tasks/{id}). | C40: 1. Log in as Workspace Admin. 2. Send PUT /api/v1/master/ai/tasks/{id} and a valid request body. 3. Check the response and the data shown in the system. | D40: HTTP 200. Response success = true; the changes are saved and returned. | E40: Master platform is running. The Workspace Admin account has permission for this action. The target resource exists. | F40: Failed | G40: 14/10/2026 | H40: Nguyễn Nhất Sinh | O40: Failing automated tests: MultiDatabaseIntegrationTest.authenticatedOnboardApiCreatesTenantAndRejectsDuplicateAliases
A41: MASTER-07-TC21 | B41: Verify update task config rejects invalid input (PUT /api/v1/master/ai/tasks/{id}). | C41: 1. Log in as Workspace Admin. 2. Send PUT /api/v1/master/ai/tasks/{id} with missing required fields or invalid values (empty text, wrong format, out-of-range numbers, non-existing IDs). 3. Check the response and the data in the system. | D41: HTTP 400 (or 404 for a non-existing ID) with success = false and an error message / field errors. No data is created or changed. | E41: Master platform is running. The Workspace Admin account has permission for this action. The target resource exists. | F41: Failed | G41: 14/10/2026 | H41: Nguyễn Nhất Sinh | O41: Failing automated tests: MultiDatabaseIntegrationTest.authenticatedOnboardApiCreatesTenantAndRejectsDuplicateAliases
A42: Provider (POST /api/v1/master/ai/test-connection)
A43: MASTER-07-TC22 | B43: Verify provider succeeds with valid input (POST /api/v1/master/ai/test-connection). | C43: 1. Log in as Workspace Admin. 2. Send POST /api/v1/master/ai/test-connection and a valid request body. 3. Check the response and the data shown in the system. | D43: HTTP 200/201. Response success = true; the record/action is saved and returned in the response. | E43: Master platform is running. The Workspace Admin account has permission for this action. | F43: Failed | G43: 14/10/2026 | H43: Nguyễn Nhất Sinh | O43: Failing automated tests: MultiDatabaseIntegrationTest.authenticatedOnboardApiCreatesTenantAndRejectsDuplicateAliases
A44: MASTER-07-TC23 | B44: Verify provider rejects invalid input (POST /api/v1/master/ai/test-connection). | C44: 1. Log in as Workspace Admin. 2. Send POST /api/v1/master/ai/test-connection with missing required fields or invalid values (empty text, wrong format, out-of-range numbers, non-existing IDs). 3. Check the response and the data in the system. | D44: HTTP 400 (or 404 for a non-existing ID) with success = false and an error message / field errors. No data is created or changed. | E44: Master platform is running. The Workspace Admin account has permission for this action. | F44: Failed | G44: 14/10/2026 | H44: Nguyễn Nhất Sinh | O44: Failing automated tests: MultiDatabaseIntegrationTest.authenticatedOnboardApiCreatesTenantAndRejectsDuplicateAliases
A45: Get ai usage report (GET /api/v1/master/ai/usage-report)
A46: MASTER-07-TC24 | B46: Verify get ai usage report succeeds with valid input (GET /api/v1/master/ai/usage-report). | C46: 1. Log in as Workspace Admin. 2. Send GET /api/v1/master/ai/usage-report. 3. Check the response and the data shown in the system. | D46: HTTP 200. Response success = true and contains the requested data. | E46: Master platform is running. The Workspace Admin account has permission for this action. | F46: Failed | G46: 14/10/2026 | H46: Nguyễn Nhất Sinh | O46: Failing automated tests: MultiDatabaseIntegrationTest.authenticatedOnboardApiCreatesTenantAndRejectsDuplicateAliases
A47: Get system settings (GET /api/v1/master/system/settings)
A48: MASTER-07-TC25 | B48: Verify get system settings succeeds with valid input (GET /api/v1/master/system/settings). | C48: 1. Log in as Workspace Admin. 2. Send GET /api/v1/master/system/settings. 3. Check the response and the data shown in the system. | D48: HTTP 200. Response success = true and contains the requested data. | E48: Master platform is running. The Workspace Admin account has permission for this action. | F48: Failed | G48: 14/10/2026 | H48: Nguyễn Nhất Sinh | O48: Failing automated tests: MultiDatabaseIntegrationTest.authenticatedOnboardApiCreatesTenantAndRejectsDuplicateAliases
A49: Save system setting (POST /api/v1/master/system/settings)
A50: MASTER-07-TC26 | B50: Verify save system setting succeeds with valid input (POST /api/v1/master/system/settings). | C50: 1. Log in as Workspace Admin. 2. Send POST /api/v1/master/system/settings and a valid request body. 3. Check the response and the data shown in the system. | D50: HTTP 200/201. Response success = true; the record/action is saved and returned in the response. | E50: Master platform is running. The Workspace Admin account has permission for this action. | F50: Failed | G50: 14/10/2026 | H50: Nguyễn Nhất Sinh | O50: Failing automated tests: MultiDatabaseIntegrationTest.authenticatedOnboardApiCreatesTenantAndRejectsDuplicateAliases
A51: MASTER-07-TC27 | B51: Verify save system setting rejects invalid input (POST /api/v1/master/system/settings). | C51: 1. Log in as Workspace Admin. 2. Send POST /api/v1/master/system/settings with missing required fields or invalid values (empty text, wrong format, out-of-range numbers, non-existing IDs). 3. Check the response and the data in the system. | D51: HTTP 400 (or 404 for a non-existing ID) with success = false and an error message / field errors. No data is created or changed. | E51: Master platform is running. The Workspace Admin account has permission for this action. | F51: Failed | G51: 14/10/2026 | H51: Nguyễn Nhất Sinh | O51: Failing automated tests: MultiDatabaseIntegrationTest.authenticatedOnboardApiCreatesTenantAndRejectsDuplicateAliases
A52: Security & tenant isolation
A53: MASTER-07-TC28 | B53: Verify platform admin APIs reject unauthenticated requests and tenant users. | C53: 1. Send GET /api/v1/master/ai/keys without an Authorization header. 2. Send the same request with a valid token of a tenant user (e.g. Tenant Admin). | D53: Step 1: HTTP 401, code UNAUTHORIZED. Step 2: HTTP 403, code FORBIDDEN (requires WORKSPACE_ADMIN). | E53: A tenant user account exists. | F53: Failed | G53: 14/10/2026 | H53: Nguyễn Nhất Sinh | O53: Failing automated tests: MultiDatabaseIntegrationTest.authenticatedOnboardApiCreatesTenantAndRejectsDuplicateAliases
A54: MASTER-07-TC29 | B54: Verify a Workspace Admin token cannot be used to read tenant data through tenant APIs. | C54: 1. Log in as Workspace Admin. 2. Call a tenant API (e.g. GET /api/v1/jobs) with header X-Tenant-ID = tenant A using the master token. | D54: The request is rejected (HTTP 401/403) and no tenant data is returned. | E54: Workspace Admin account exists; tenant A has data. | F54: Failed | G54: 14/10/2026 | H54: Nguyễn Nhất Sinh | O54: Failing automated tests: MultiDatabaseIntegrationTest.authenticatedOnboardApiCreatesTenantAndRejectsDuplicateAliases

Sheet MASTER-08
A2: Feature | B2: Platform Financial Analytics (ARR/NRR), Audit Logs & Auto Email Alerts | R2: Passed
A3: Test requirement | B3: Verify the business rules and APIs of MASTER-08 - Platform Financial Analytics (ARR/NRR), Audit Logs & Auto Email Alerts as specified in docs/features/Master-Platform/Platform-Analytics-Notifications.md. | R3: Failed
A4: Number of TCs | B4: =COUNTIF(A11:A2000,"*-TC*") -> 5 | R4: Pending
A5: Testing Round | B5: Passed | C5: Failed | D5: Pending | E5: N/A | R5: N/A
A6: Round 1 | B6: =COUNTIF($F$11:$F$2000,B$5) -> 0 | C6: =COUNTIF($F$11:$F$2000,C$5) -> 0 | D6: =COUNTIF($F$11:$F$2000,D$5) -> 5 | E6: =COUNTIF($F$11:$F$2000,E$5) -> 0
A7: Round 2 | B7: =COUNTIF($I$11:$I$2000,B$5) -> 0 | C7: =COUNTIF($I$11:$I$2000,C$5) -> 0 | D7: =COUNTIF($I$11:$I$2000,D$5) -> 0 | E7: =COUNTIF($I$11:$I$2000,E$5) -> 0
A8: Round 3 | B8: =COUNTIF($L$11:$L$2000,B$5) -> 0 | C8: =COUNTIF($L$11:$L$2000,C$5) -> 0 | D8: =COUNTIF($L$11:$L$2000,D$5) -> 0 | E8: =COUNTIF($L$11:$L$2000,E$5) -> 0
A10: Test Case ID | B10: Test Case Description | C10: Test Case Procedure | D10: Expected Results | E10: Pre-conditions | F10: Round 1 | G10: Test date | H10: Tester | I10: Round 2 | J10: Test date | K10: Tester | L10: Round 3 | M10: Test date | N10: Tester | O10: Note
A11: Get ai quota usage (GET /api/v1/master/analytics/ai-quota)
A12: MASTER-08-TC04 | B12: Verify get ai quota usage succeeds with valid input (GET /api/v1/master/analytics/ai-quota). | C12: 1. Log in as Workspace Admin. 2. Send GET /api/v1/master/analytics/ai-quota. 3. Check the response and the data shown in the system. | D12: HTTP 200. Response success = true and contains the requested data. | E12: Master platform is running. The Workspace Admin account has permission for this action. | F12: Pending | H12: Nguyễn Minh Hiếu | O12: Not tested: no automated test covers this feature yet.
A13: Get system audit logs (GET /api/v1/master/analytics/logs)
A14: MASTER-08-TC05 | B14: Verify get system audit logs succeeds with valid input (GET /api/v1/master/analytics/logs). | C14: 1. Log in as Workspace Admin. 2. Send GET /api/v1/master/analytics/logs. 3. Check the response and the data shown in the system. | D14: HTTP 200. Response success = true and contains the requested data. | E14: Master platform is running. The Workspace Admin account has permission for this action. | F14: Pending | H14: Nguyễn Minh Hiếu | O14: Not tested: no automated test covers this feature yet.
A15: Get revenue analytics (GET /api/v1/master/analytics/revenue)
A16: MASTER-08-TC06 | B16: Verify get revenue analytics succeeds with valid input (GET /api/v1/master/analytics/revenue). | C16: 1. Log in as Workspace Admin. 2. Send GET /api/v1/master/analytics/revenue. 3. Check the response and the data shown in the system. | D16: HTTP 200. Response success = true and contains the requested data. | E16: Master platform is running. The Workspace Admin account has permission for this action. | F16: Pending | H16: Nguyễn Minh Hiếu | O16: Not tested: no automated test covers this feature yet.
A17: Security & tenant isolation
A18: MASTER-08-TC07 | B18: Verify platform admin APIs reject unauthenticated requests and tenant users. | C18: 1. Send GET /api/v1/master/analytics/ai-quota without an Authorization header. 2. Send the same request with a valid token of a tenant user (e.g. Tenant Admin). | D18: Step 1: HTTP 401, code UNAUTHORIZED. Step 2: HTTP 403, code FORBIDDEN (requires WORKSPACE_ADMIN). | E18: A tenant user account exists. | F18: Pending | H18: Nguyễn Minh Hiếu | O18: Not tested: no automated test covers this feature yet.
A19: MASTER-08-TC08 | B19: Verify a Workspace Admin token cannot be used to read tenant data through tenant APIs. | C19: 1. Log in as Workspace Admin. 2. Call a tenant API (e.g. GET /api/v1/jobs) with header X-Tenant-ID = tenant A using the master token. | D19: The request is rejected (HTTP 401/403) and no tenant data is returned. | E19: Workspace Admin account exists; tenant A has data. | F19: Pending | H19: Nguyễn Minh Hiếu | O19: Not tested: no automated test covers this feature yet.

Sheet ASSESS-01
A2: Feature | B2: Multiple Choice Test | R2: Passed
A3: Test requirement | B3: Verify the business rules and APIs of ASSESS-01 - Multiple Choice Test as specified in docs/features/Technical-Assessment/Multiple-Choice-Test.md. | R3: Failed
A4: Number of TCs | B4: =COUNTIF(A11:A2000,"*-TC*") -> 38 | R4: Pending
A5: Testing Round | B5: Passed | C5: Failed | D5: Pending | E5: N/A | R5: N/A
A6: Round 1 | B6: =COUNTIF($F$11:$F$2000,B$5) -> 38 | C6: =COUNTIF($F$11:$F$2000,C$5) -> 0 | D6: =COUNTIF($F$11:$F$2000,D$5) -> 0 | E6: =COUNTIF($F$11:$F$2000,E$5) -> 0
A7: Round 2 | B7: =COUNTIF($I$11:$I$2000,B$5) -> 0 | C7: =COUNTIF($I$11:$I$2000,C$5) -> 0 | D7: =COUNTIF($I$11:$I$2000,D$5) -> 0 | E7: =COUNTIF($I$11:$I$2000,E$5) -> 0
A8: Round 3 | B8: =COUNTIF($L$11:$L$2000,B$5) -> 0 | C8: =COUNTIF($L$11:$L$2000,C$5) -> 0 | D8: =COUNTIF($L$11:$L$2000,D$5) -> 0 | E8: =COUNTIF($L$11:$L$2000,E$5) -> 0
A10: Test Case ID | B10: Test Case Description | C10: Test Case Procedure | D10: Expected Results | E10: Pre-conditions | F10: Round 1 | G10: Test date | H10: Tester | I10: Round 2 | J10: Test date | K10: Tester | L10: Round 3 | M10: Test date | N10: Tester | O10: Note
A11: Job test (POST /api/v1/assessments/create_draft_test)
A12: ASSESS-01-TC19 | B12: Verify job test succeeds with valid input (POST /api/v1/assessments/create_draft_test). | C12: 1. Log in as Recruiter of tenant A. 2. Send POST /api/v1/assessments/create_draft_test with header X-Tenant-ID = tenant A and a valid request body. 3. Check the response and the data shown in the system. | D12: HTTP 200/201. Response success = true; the record/action is saved and returned in the response. | E12: Tenant A is ACTIVE. The Recruiter account has permission for this action. | F12: Passed | G12: 08/10/2026 | H12: Lê Mỹ Lộc | O12: Verified by automated tests: ApiResponseTest, AssessmentFlowTest, AssessmentInvitationServiceTest ...
A13: ASSESS-01-TC20 | B13: Verify job test rejects invalid input (POST /api/v1/assessments/create_draft_test). | C13: 1. Log in as Recruiter of tenant A. 2. Send POST /api/v1/assessments/create_draft_test with header X-Tenant-ID = tenant A with missing required fields or invalid values (empty text, wrong format, out-of-range numbers, non-existing IDs). 3. Check the response and the data in the system. | D13: HTTP 400 (or 404 for a non-existing ID) with success = false and an error message / field errors. No data is created or changed. | E13: Tenant A is ACTIVE. The Recruiter account has permission for this action. | F13: Passed | G13: 08/10/2026 | H13: Lê Mỹ Lộc | O13: Verified by automated tests: ApiResponseTest, AssessmentFlowTest, AssessmentInvitationServiceTest ...
A14: Tenant (GET /api/v1/assessments/list_tenant_tests)
A15: ASSESS-01-TC21 | B15: Verify tenant succeeds with valid input (GET /api/v1/assessments/list_tenant_tests). | C15: 1. Log in as Recruiter of tenant A. 2. Send GET /api/v1/assessments/list_tenant_tests with header X-Tenant-ID = tenant A. 3. Check the response and the data shown in the system. | D15: HTTP 200. Response success = true and contains the requested data of tenant A only. | E15: Tenant A is ACTIVE. The Recruiter account has permission for this action. | F15: Passed | G15: 08/10/2026 | H15: Lê Mỹ Lộc | O15: Verified by automated tests: ApiResponseTest, AssessmentFlowTest, AssessmentInvitationServiceTest ...
A16: Id (GET /api/v1/assessments/get_test_metadata/{id})
A17: ASSESS-01-TC22 | B17: Verify id succeeds with valid input (GET /api/v1/assessments/get_test_metadata/{id}). | C17: 1. Log in as Recruiter of tenant A. 2. Send GET /api/v1/assessments/get_test_metadata/{id} with header X-Tenant-ID = tenant A. 3. Check the response and the data shown in the system. | D17: HTTP 200. Response success = true and contains the requested data of tenant A only. | E17: Tenant A is ACTIVE. The Recruiter account has permission for this action. The target resource exists. | F17: Passed | G17: 08/10/2026 | H17: Lê Mỹ Lộc | O17: Verified by automated tests: ApiResponseTest, AssessmentFlowTest, AssessmentInvitationServiceTest ...
A18: Metadata (PUT /api/v1/assessments/update_draft_test/{id})
A19: ASSESS-01-TC23 | B19: Verify metadata succeeds with valid input (PUT /api/v1/assessments/update_draft_test/{id}). | C19: 1. Log in as Recruiter of tenant A. 2. Send PUT /api/v1/assessments/update_draft_test/{id} with header X-Tenant-ID = tenant A and a valid request body. 3. Check the response and the data shown in the system. | D19: HTTP 200. Response success = true; the changes are saved and returned. | E19: Tenant A is ACTIVE. The Recruiter account has permission for this action. The target resource exists. | F19: Passed | G19: 08/10/2026 | H19: Lê Mỹ Lộc | O19: Verified by automated tests: ApiResponseTest, AssessmentFlowTest, AssessmentInvitationServiceTest ...
A20: ASSESS-01-TC24 | B20: Verify metadata rejects invalid input (PUT /api/v1/assessments/update_draft_test/{id}). | C20: 1. Log in as Recruiter of tenant A. 2. Send PUT /api/v1/assessments/update_draft_test/{id} with header X-Tenant-ID = tenant A with missing required fields or invalid values (empty text, wrong format, out-of-range numbers, non-existing IDs). 3. Check the response and the data in the system. | D20: HTTP 400 (or 404 for a non-existing ID) with success = false and an error message / field errors. No data is created or changed. | E20: Tenant A is ACTIVE. The Recruiter account has permission for this action. The target resource exists. | F20: Passed | G20: 08/10/2026 | H20: Lê Mỹ Lộc | O20: Verified by automated tests: ApiResponseTest, AssessmentFlowTest, AssessmentInvitationServiceTest ...
A21: Job test (GET /api/v1/assessments/{id}/list_questions)
A22: ASSESS-01-TC25 | B22: Verify job test succeeds with valid input (GET /api/v1/assessments/{id}/list_questions). | C22: 1. Log in as Recruiter of tenant A. 2. Send GET /api/v1/assessments/{id}/list_questions with header X-Tenant-ID = tenant A. 3. Check the response and the data shown in the system. | D22: HTTP 200. Response success = true and contains the requested data of tenant A only. | E22: Tenant A is ACTIVE. The Recruiter account has permission for this action. The target resource exists. | F22: Passed | G22: 08/10/2026 | H22: Lê Mỹ Lộc | O22: Verified by automated tests: ApiResponseTest, AssessmentFlowTest, AssessmentInvitationServiceTest ...
A23: Job test (POST /api/v1/assessments/{id}/create_question)
A24: ASSESS-01-TC26 | B24: Verify job test succeeds with valid input (POST /api/v1/assessments/{id}/create_question). | C24: 1. Log in as Recruiter of tenant A. 2. Send POST /api/v1/assessments/{id}/create_question with header X-Tenant-ID = tenant A and a valid request body. 3. Check the response and the data shown in the system. | D24: HTTP 200/201. Response success = true; the record/action is saved and returned in the response. | E24: Tenant A is ACTIVE. The Recruiter account has permission for this action. The target resource exists. | F24: Passed | G24: 08/10/2026 | H24: Lê Mỹ Lộc | O24: Verified by automated tests: ApiResponseTest, AssessmentFlowTest, AssessmentInvitationServiceTest ...
A25: ASSESS-01-TC27 | B25: Verify job test rejects invalid input (POST /api/v1/assessments/{id}/create_question). | C25: 1. Log in as Recruiter of tenant A. 2. Send POST /api/v1/assessments/{id}/create_question with header X-Tenant-ID = tenant A with missing required fields or invalid values (empty text, wrong format, out-of-range numbers, non-existing IDs). 3. Check the response and the data in the system. | D25: HTTP 400 (or 404 for a non-existing ID) with success = false and an error message / field errors. No data is created or changed. | E25: Tenant A is ACTIVE. The Recruiter account has permission for this action. The target resource exists. | F25: Passed | G25: 08/10/2026 | H25: Lê Mỹ Lộc | O25: Verified by automated tests: ApiResponseTest, AssessmentFlowTest, AssessmentInvitationServiceTest ...
A26: Options (PUT /api/v1/assessments/{id}/update_question/{id})
A27: ASSESS-01-TC28 | B27: Verify options succeeds with valid input (PUT /api/v1/assessments/{id}/update_question/{id}). | C27: 1. Log in as Recruiter of tenant A. 2. Send PUT /api/v1/assessments/{id}/update_question/{id} with header X-Tenant-ID = tenant A and a valid request body. 3. Check the response and the data shown in the system. | D27: HTTP 200. Response success = true; the changes are saved and returned. | E27: Tenant A is ACTIVE. The Recruiter account has permission for this action. The target resource exists. | F27: Passed | G27: 08/10/2026 | H27: Lê Mỹ Lộc | O27: Verified by automated tests: ApiResponseTest, AssessmentFlowTest, AssessmentInvitationServiceTest ...
A28: ASSESS-01-TC29 | B28: Verify options rejects invalid input (PUT /api/v1/assessments/{id}/update_question/{id}). | C28: 1. Log in as Recruiter of tenant A. 2. Send PUT /api/v1/assessments/{id}/update_question/{id} with header X-Tenant-ID = tenant A with missing required fields or invalid values (empty text, wrong format, out-of-range numbers, non-existing IDs). 3. Check the response and the data in the system. | D28: HTTP 400 (or 404 for a non-existing ID) with success = false and an error message / field errors. No data is created or changed. | E28: Tenant A is ACTIVE. The Recruiter account has permission for this action. The target resource exists. | F28: Passed | G28: 08/10/2026 | H28: Lê Mỹ Lộc | O28: Verified by automated tests: ApiResponseTest, AssessmentFlowTest, AssessmentInvitationServiceTest ...
A29: Options (DELETE /api/v1/assessments/{id}/delete_question/{id})
A30: ASSESS-01-TC30 | B30: Verify options succeeds with valid input (DELETE /api/v1/assessments/{id}/delete_question/{id}). | C30: 1. Log in as Recruiter of tenant A. 2. Send DELETE /api/v1/assessments/{id}/delete_question/{id} with header X-Tenant-ID = tenant A. 3. Check the response and the data shown in the system. | D30: HTTP 200/204. The record is removed (or archived) and no longer appears in lists. | E30: Tenant A is ACTIVE. The Recruiter account has permission for this action. The target resource exists. | F30: Passed | G30: 08/10/2026 | H30: Lê Mỹ Lộc | O30: Verified by automated tests: ApiResponseTest, AssessmentFlowTest, AssessmentInvitationServiceTest ...
A31: ASSESS-01-TC31 | B31: Verify options rejects invalid input (DELETE /api/v1/assessments/{id}/delete_question/{id}). | C31: 1. Log in as Recruiter of tenant A. 2. Send DELETE /api/v1/assessments/{id}/delete_question/{id} with header X-Tenant-ID = tenant A with missing required fields or invalid values (empty text, wrong format, out-of-range numbers, non-existing IDs). 3. Check the response and the data in the system. | D31: HTTP 400 (or 404 for a non-existing ID) with success = false and an error message / field errors. No data is created or changed. | E31: Tenant A is ACTIVE. The Recruiter account has permission for this action. The target resource exists. | F31: Passed | G31: 08/10/2026 | H31: Lê Mỹ Lộc | O31: Verified by automated tests: ApiResponseTest, AssessmentFlowTest, AssessmentInvitationServiceTest ...
A32: Job test (POST /api/v1/assessments/{id}/publish_test)
A33: ASSESS-01-TC32 | B33: Verify job test succeeds with valid input (POST /api/v1/assessments/{id}/publish_test). | C33: 1. Log in as Recruiter of tenant A. 2. Send POST /api/v1/assessments/{id}/publish_test with header X-Tenant-ID = tenant A and a valid request body. 3. Check the response and the data shown in the system. | D33: HTTP 200/201. Response success = true; the record/action is saved and returned in the response. | E33: Tenant A is ACTIVE. The Recruiter account has permission for this action. The target resource exists. | F33: Passed | G33: 08/10/2026 | H33: Lê Mỹ Lộc | O33: Verified by automated tests: ApiResponseTest, AssessmentFlowTest, AssessmentInvitationServiceTest ...
A34: ASSESS-01-TC33 | B34: Verify job test rejects invalid input (POST /api/v1/assessments/{id}/publish_test). | C34: 1. Log in as Recruiter of tenant A. 2. Send POST /api/v1/assessments/{id}/publish_test with header X-Tenant-ID = tenant A with missing required fields or invalid values (empty text, wrong format, out-of-range numbers, non-existing IDs). 3. Check the response and the data in the system. | D34: HTTP 400 (or 404 for a non-existing ID) with success = false and an error message / field errors. No data is created or changed. | E34: Tenant A is ACTIVE. The Recruiter account has permission for this action. The target resource exists. | F34: Passed | G34: 08/10/2026 | H34: Lê Mỹ Lộc | O34: Verified by automated tests: ApiResponseTest, AssessmentFlowTest, AssessmentInvitationServiceTest ...
A35: Submission (POST /api/v1/assessments/{id}/start_submission)
A36: ASSESS-01-TC34 | B36: Verify submission succeeds with valid input (POST /api/v1/assessments/{id}/start_submission). | C36: 1. Log in as Recruiter of tenant A. 2. Send POST /api/v1/assessments/{id}/start_submission with header X-Tenant-ID = tenant A and a valid request body. 3. Check the response and the data shown in the system. | D36: HTTP 200/201. Response success = true; the record/action is saved and returned in the response. | E36: Tenant A is ACTIVE. The Recruiter account has permission for this action. The target resource exists. | F36: Passed | G36: 08/10/2026 | H36: Lê Mỹ Lộc | O36: Verified by automated tests: ApiResponseTest, AssessmentFlowTest, AssessmentInvitationServiceTest ...
A37: ASSESS-01-TC35 | B37: Verify submission rejects invalid input (POST /api/v1/assessments/{id}/start_submission). | C37: 1. Log in as Recruiter of tenant A. 2. Send POST /api/v1/assessments/{id}/start_submission with header X-Tenant-ID = tenant A with missing required fields or invalid values (empty text, wrong format, out-of-range numbers, non-existing IDs). 3. Check the response and the data in the system. | D37: HTTP 400 (or 404 for a non-existing ID) with success = false and an error message / field errors. No data is created or changed. | E37: Tenant A is ACTIVE. The Recruiter account has permission for this action. The target resource exists. | F37: Passed | G37: 08/10/2026 | H37: Lê Mỹ Lộc | O37: Verified by automated tests: ApiResponseTest, AssessmentFlowTest, AssessmentInvitationServiceTest ...
A38: Deadline (GET /api/v1/submissions/{id}/get_submission)
A39: ASSESS-01-TC36 | B39: Verify deadline succeeds with valid input (GET /api/v1/submissions/{id}/get_submission). | C39: 1. Log in as Recruiter of tenant A. 2. Send GET /api/v1/submissions/{id}/get_submission with header X-Tenant-ID = tenant A. 3. Check the response and the data shown in the system. | D39: HTTP 200. Response success = true and contains the requested data of tenant A only. | E39: Tenant A is ACTIVE. The Recruiter account has permission for this action. The target resource exists. | F39: Passed | G39: 08/10/2026 | H39: Lê Mỹ Lộc | O39: Verified by automated tests: ApiResponseTest, AssessmentFlowTest, AssessmentInvitationServiceTest ...
A40: Answers (POST /api/v1/submissions/{id}/save_answers)
A41: ASSESS-01-TC37 | B41: Verify answers succeeds with valid input (POST /api/v1/submissions/{id}/save_answers). | C41: 1. Log in as Recruiter of tenant A. 2. Send POST /api/v1/submissions/{id}/save_answers with header X-Tenant-ID = tenant A and a valid request body. 3. Check the response and the data shown in the system. | D41: HTTP 200/201. Response success = true; the record/action is saved and returned in the response. | E41: Tenant A is ACTIVE. The Recruiter account has permission for this action. The target resource exists. | F41: Passed | G41: 08/10/2026 | H41: Lê Mỹ Lộc | O41: Verified by automated tests: ApiResponseTest, AssessmentFlowTest, AssessmentInvitationServiceTest ...
A42: ASSESS-01-TC38 | B42: Verify answers rejects invalid input (POST /api/v1/submissions/{id}/save_answers). | C42: 1. Log in as Recruiter of tenant A. 2. Send POST /api/v1/submissions/{id}/save_answers with header X-Tenant-ID = tenant A with missing required fields or invalid values (empty text, wrong format, out-of-range numbers, non-existing IDs). 3. Check the response and the data in the system. | D42: HTTP 400 (or 404 for a non-existing ID) with success = false and an error message / field errors. No data is created or changed. | E42: Tenant A is ACTIVE. The Recruiter account has permission for this action. The target resource exists. | F42: Passed | G42: 08/10/2026 | H42: Lê Mỹ Lộc | O42: Verified by automated tests: ApiResponseTest, AssessmentFlowTest, AssessmentInvitationServiceTest ...
A43: Answers (POST /api/v1/submissions/{id}/submit_test)
A44: ASSESS-01-TC39 | B44: Verify answers succeeds with valid input (POST /api/v1/submissions/{id}/submit_test). | C44: 1. Log in as Recruiter of tenant A. 2. Send POST /api/v1/submissions/{id}/submit_test with header X-Tenant-ID = tenant A and a valid request body. 3. Check the response and the data shown in the system. | D44: HTTP 200/201. Response success = true; the record/action is saved and returned in the response. | E44: Tenant A is ACTIVE. The Recruiter account has permission for this action. The target resource exists. | F44: Passed | G44: 08/10/2026 | H44: Lê Mỹ Lộc | O44: Verified by automated tests: ApiResponseTest, AssessmentFlowTest, AssessmentInvitationServiceTest ...
A45: ASSESS-01-TC40 | B45: Verify answers rejects invalid input (POST /api/v1/submissions/{id}/submit_test). | C45: 1. Log in as Recruiter of tenant A. 2. Send POST /api/v1/submissions/{id}/submit_test with header X-Tenant-ID = tenant A with missing required fields or invalid values (empty text, wrong format, out-of-range numbers, non-existing IDs). 3. Check the response and the data in the system. | D45: HTTP 400 (or 404 for a non-existing ID) with success = false and an error message / field errors. No data is created or changed. | E45: Tenant A is ACTIVE. The Recruiter account has permission for this action. The target resource exists. | F45: Passed | G45: 08/10/2026 | H45: Lê Mỹ Lộc | O45: Verified by automated tests: ApiResponseTest, AssessmentFlowTest, AssessmentInvitationServiceTest ...
A46: Tenant (GET /api/v1/question-bank/list_questions)
A47: ASSESS-01-TC41 | B47: Verify tenant succeeds with valid input (GET /api/v1/question-bank/list_questions). | C47: 1. Log in as Recruiter of tenant A. 2. Send GET /api/v1/question-bank/list_questions with header X-Tenant-ID = tenant A. 3. Check the response and the data shown in the system. | D47: HTTP 200. Response success = true and contains the requested data of tenant A only. | E47: Tenant A is ACTIVE. The Recruiter account has permission for this action. | F47: Passed | G47: 08/10/2026 | H47: Lê Mỹ Lộc | O47: Verified by automated tests: ApiResponseTest, AssessmentFlowTest, AssessmentInvitationServiceTest ...
A48: Metadata (GET /api/v1/question-bank/get_question/{id})
A49: ASSESS-01-TC42 | B49: Verify metadata succeeds with valid input (GET /api/v1/question-bank/get_question/{id}). | C49: 1. Log in as Recruiter of tenant A. 2. Send GET /api/v1/question-bank/get_question/{id} with header X-Tenant-ID = tenant A. 3. Check the response and the data shown in the system. | D49: HTTP 200. Response success = true and contains the requested data of tenant A only. | E49: Tenant A is ACTIVE. The Recruiter account has permission for this action. The target resource exists. | F49: Passed | G49: 08/10/2026 | H49: Lê Mỹ Lộc | O49: Verified by automated tests: ApiResponseTest, AssessmentFlowTest, AssessmentInvitationServiceTest ...
A50: Assessment (POST /api/v1/question-bank/create_questions)
A51: ASSESS-01-TC43 | B51: Verify assessment succeeds with valid input (POST /api/v1/question-bank/create_questions). | C51: 1. Log in as Recruiter of tenant A. 2. Send POST /api/v1/question-bank/create_questions with header X-Tenant-ID = tenant A and a valid request body. 3. Check the response and the data shown in the system. | D51: HTTP 200/201. Response success = true; the record/action is saved and returned in the response. | E51: Tenant A is ACTIVE. The Recruiter account has permission for this action. | F51: Passed | G51: 08/10/2026 | H51: Lê Mỹ Lộc | O51: Verified by automated tests: ApiResponseTest, AssessmentFlowTest, AssessmentInvitationServiceTest ...
A52: ASSESS-01-TC44 | B52: Verify assessment rejects invalid input (POST /api/v1/question-bank/create_questions). | C52: 1. Log in as Recruiter of tenant A. 2. Send POST /api/v1/question-bank/create_questions with header X-Tenant-ID = tenant A with missing required fields or invalid values (empty text, wrong format, out-of-range numbers, non-existing IDs). 3. Check the response and the data in the system. | D52: HTTP 400 (or 404 for a non-existing ID) with success = false and an error message / field errors. No data is created or changed. | E52: Tenant A is ACTIVE. The Recruiter account has permission for this action. | F52: Passed | G52: 08/10/2026 | H52: Lê Mỹ Lộc | O52: Verified by automated tests: ApiResponseTest, AssessmentFlowTest, AssessmentInvitationServiceTest ...
A53: Options (PUT /api/v1/question-bank/update_question/{id})
A54: ASSESS-01-TC45 | B54: Verify options succeeds with valid input (PUT /api/v1/question-bank/update_question/{id}). | C54: 1. Log in as Recruiter of tenant A. 2. Send PUT /api/v1/question-bank/update_question/{id} with header X-Tenant-ID = tenant A and a valid request body. 3. Check the response and the data shown in the system. | D54: HTTP 200. Response success = true; the changes are saved and returned. | E54: Tenant A is ACTIVE. The Recruiter account has permission for this action. The target resource exists. | F54: Passed | G54: 08/10/2026 | H54: Lê Mỹ Lộc | O54: Verified by automated tests: ApiResponseTest, AssessmentFlowTest, AssessmentInvitationServiceTest ...
A55: ASSESS-01-TC46 | B55: Verify options rejects invalid input (PUT /api/v1/question-bank/update_question/{id}). | C55: 1. Log in as Recruiter of tenant A. 2. Send PUT /api/v1/question-bank/update_question/{id} with header X-Tenant-ID = tenant A with missing required fields or invalid values (empty text, wrong format, out-of-range numbers, non-existing IDs). 3. Check the response and the data in the system. | D55: HTTP 400 (or 404 for a non-existing ID) with success = false and an error message / field errors. No data is created or changed. | E55: Tenant A is ACTIVE. The Recruiter account has permission for this action. The target resource exists. | F55: Passed | G55: 08/10/2026 | H55: Lê Mỹ Lộc | O55: Verified by automated tests: ApiResponseTest, AssessmentFlowTest, AssessmentInvitationServiceTest ...
A56: Atomically (PUT /api/v1/question-bank/archive_questions)
A57: ASSESS-01-TC47 | B57: Verify atomically succeeds with valid input (PUT /api/v1/question-bank/archive_questions). | C57: 1. Log in as Recruiter of tenant A. 2. Send PUT /api/v1/question-bank/archive_questions with header X-Tenant-ID = tenant A and a valid request body. 3. Check the response and the data shown in the system. | D57: HTTP 200. Response success = true; the changes are saved and returned. | E57: Tenant A is ACTIVE. The Recruiter account has permission for this action. | F57: Passed | G57: 08/10/2026 | H57: Lê Mỹ Lộc | O57: Verified by automated tests: ApiResponseTest, AssessmentFlowTest, AssessmentInvitationServiceTest ...
A58: ASSESS-01-TC48 | B58: Verify atomically rejects invalid input (PUT /api/v1/question-bank/archive_questions). | C58: 1. Log in as Recruiter of tenant A. 2. Send PUT /api/v1/question-bank/archive_questions with header X-Tenant-ID = tenant A with missing required fields or invalid values (empty text, wrong format, out-of-range numbers, non-existing IDs). 3. Check the response and the data in the system. | D58: HTTP 400 (or 404 for a non-existing ID) with success = false and an error message / field errors. No data is created or changed. | E58: Tenant A is ACTIVE. The Recruiter account has permission for this action. | F58: Passed | G58: 08/10/2026 | H58: Lê Mỹ Lộc | O58: Verified by automated tests: ApiResponseTest, AssessmentFlowTest, AssessmentInvitationServiceTest ...
A59: Structure (GET /api/v1/assessments/jobs/{id}/configuration)
A60: ASSESS-01-TC49 | B60: Verify structure succeeds with valid input (GET /api/v1/assessments/jobs/{id}/configuration). | C60: 1. Log in as Recruiter of tenant A. 2. Send GET /api/v1/assessments/jobs/{id}/configuration with header X-Tenant-ID = tenant A. 3. Check the response and the data shown in the system. | D60: HTTP 200. Response success = true and contains the requested data of tenant A only. | E60: Tenant A is ACTIVE. The Recruiter account has permission for this action. The target resource exists. | F60: Passed | G60: 08/10/2026 | H60: Lê Mỹ Lộc | O60: Verified by automated tests: ApiResponseTest, AssessmentFlowTest, AssessmentInvitationServiceTest ...
A61: Save (PUT /api/v1/assessments/jobs/{id}/configuration)
A62: ASSESS-01-TC50 | B62: Verify save succeeds with valid input (PUT /api/v1/assessments/jobs/{id}/configuration). | C62: 1. Log in as Recruiter of tenant A. 2. Send PUT /api/v1/assessments/jobs/{id}/configuration with header X-Tenant-ID = tenant A and a valid request body. 3. Check the response and the data shown in the system. | D62: HTTP 200. Response success = true; the changes are saved and returned. | E62: Tenant A is ACTIVE. The Recruiter account has permission for this action. The target resource exists. | F62: Passed | G62: 08/10/2026 | H62: Lê Mỹ Lộc | O62: Verified by automated tests: ApiResponseTest, AssessmentFlowTest, AssessmentInvitationServiceTest ...
A63: ASSESS-01-TC51 | B63: Verify save rejects invalid input (PUT /api/v1/assessments/jobs/{id}/configuration). | C63: 1. Log in as Recruiter of tenant A. 2. Send PUT /api/v1/assessments/jobs/{id}/configuration with header X-Tenant-ID = tenant A with missing required fields or invalid values (empty text, wrong format, out-of-range numbers, non-existing IDs). 3. Check the response and the data in the system. | D63: HTTP 400 (or 404 for a non-existing ID) with success = false and an error message / field errors. No data is created or changed. | E63: Tenant A is ACTIVE. The Recruiter account has permission for this action. The target resource exists. | F63: Passed | G63: 08/10/2026 | H63: Lê Mỹ Lộc | O63: Verified by automated tests: ApiResponseTest, AssessmentFlowTest, AssessmentInvitationServiceTest ...
A64: Generate (POST /api/v1/assessments/jobs/{id}/generate)
A65: ASSESS-01-TC52 | B65: Verify generate succeeds with valid input (POST /api/v1/assessments/jobs/{id}/generate). | C65: 1. Log in as Recruiter of tenant A. 2. Send POST /api/v1/assessments/jobs/{id}/generate with header X-Tenant-ID = tenant A and a valid request body. 3. Check the response and the data shown in the system. | D65: HTTP 200/201. Response success = true; the record/action is saved and returned in the response. | E65: Tenant A is ACTIVE. The Recruiter account has permission for this action. The target resource exists. | F65: Passed | G65: 08/10/2026 | H65: Lê Mỹ Lộc | O65: Verified by automated tests: ApiResponseTest, AssessmentFlowTest, AssessmentInvitationServiceTest ...
A66: ASSESS-01-TC53 | B66: Verify generate rejects invalid input (POST /api/v1/assessments/jobs/{id}/generate). | C66: 1. Log in as Recruiter of tenant A. 2. Send POST /api/v1/assessments/jobs/{id}/generate with header X-Tenant-ID = tenant A with missing required fields or invalid values (empty text, wrong format, out-of-range numbers, non-existing IDs). 3. Check the response and the data in the system. | D66: HTTP 400 (or 404 for a non-existing ID) with success = false and an error message / field errors. No data is created or changed. | E66: Tenant A is ACTIVE. The Recruiter account has permission for this action. The target resource exists. | F66: Passed | G66: 08/10/2026 | H66: Lê Mỹ Lộc | O66: Verified by automated tests: ApiResponseTest, AssessmentFlowTest, AssessmentInvitationServiceTest ...
A67: Status (GET /api/v1/assessments/jobs/{id}/automation_status)
A68: ASSESS-01-TC54 | B68: Verify status succeeds with valid input (GET /api/v1/assessments/jobs/{id}/automation_status). | C68: 1. Log in as Recruiter of tenant A. 2. Send GET /api/v1/assessments/jobs/{id}/automation_status with header X-Tenant-ID = tenant A. 3. Check the response and the data shown in the system. | D68: HTTP 200. Response success = true and contains the requested data of tenant A only. | E68: Tenant A is ACTIVE. The Recruiter account has permission for this action. The target resource exists. | F68: Passed | G68: 08/10/2026 | H68: Lê Mỹ Lộc | O68: Verified by automated tests: ApiResponseTest, AssessmentFlowTest, AssessmentInvitationServiceTest ...
A69: Security & tenant isolation
A70: ASSESS-01-TC55 | B70: Verify protected APIs of this feature reject unauthenticated and unauthorized users. | C70: 1. Send POST /api/v1/assessments/create_draft_test without an Authorization header. 2. Send the same request with a valid token of a role that is not allowed (e.g. Candidate calling a staff API). | D70: Step 1: HTTP 401, code UNAUTHORIZED. Step 2: HTTP 403, code FORBIDDEN. No data is returned or changed. | E70: Accounts of an allowed role and a not-allowed role exist in tenant A. | F70: Passed | G70: 08/10/2026 | H70: Lê Mỹ Lộc | O70: Verified by automated tests: ApiResponseTest, AssessmentFlowTest, AssessmentInvitationServiceTest ...
A71: ASSESS-01-TC56 | B71: Verify tenant data isolation: a tenant B user cannot read or change tenant A data. | C71: 1. Log in as Recruiter of tenant B. 2. Send GET /api/v1/assessments/get_test_metadata/{id} using a resource ID that belongs to tenant A, with header X-Tenant-ID = tenant A. 3. Open the related list screen of tenant B. | D71: Step 2: the tenant in the JWT (tenant B) is used, so the request returns HTTP 404 (or an empty result); no tenant A data is returned or changed. Step 3: only tenant B records are listed. | E71: Tenant A and tenant B are ACTIVE and both have data for this feature. | F71: Passed | G71: 08/10/2026 | H71: Lê Mỹ Lộc | O71: Verified by automated tests: ApiResponseTest, AssessmentFlowTest, AssessmentInvitationServiceTest ...

Sheet ASSESS-02
A2: Feature | B2: Coding Challenge | R2: Passed
A3: Test requirement | B3: Verify the business rules and APIs of ASSESS-02 - Coding Challenge as specified in docs/features/Technical-Assessment/Coding-Challenge.md. | R3: Failed
A4: Number of TCs | B4: =COUNTIF(A11:A2000,"*-TC*") -> 5 | R4: Pending
A5: Testing Round | B5: Passed | C5: Failed | D5: Pending | E5: N/A | R5: N/A
A6: Round 1 | B6: =COUNTIF($F$11:$F$2000,B$5) -> 0 | C6: =COUNTIF($F$11:$F$2000,C$5) -> 0 | D6: =COUNTIF($F$11:$F$2000,D$5) -> 5 | E6: =COUNTIF($F$11:$F$2000,E$5) -> 0
A7: Round 2 | B7: =COUNTIF($I$11:$I$2000,B$5) -> 0 | C7: =COUNTIF($I$11:$I$2000,C$5) -> 0 | D7: =COUNTIF($I$11:$I$2000,D$5) -> 0 | E7: =COUNTIF($I$11:$I$2000,E$5) -> 0
A8: Round 3 | B8: =COUNTIF($L$11:$L$2000,B$5) -> 0 | C8: =COUNTIF($L$11:$L$2000,C$5) -> 0 | D8: =COUNTIF($L$11:$L$2000,D$5) -> 0 | E8: =COUNTIF($L$11:$L$2000,E$5) -> 0
A10: Test Case ID | B10: Test Case Description | C10: Test Case Procedure | D10: Expected Results | E10: Pre-conditions | F10: Round 1 | G10: Test date | H10: Tester | I10: Round 2 | J10: Test date | K10: Tester | L10: Round 3 | M10: Test date | N10: Tester | O10: Note
A11: POST /api/v1/attempts/{id}/coding-submissions (POST /api/v1/attempts/{id}/coding-submissions)
A12: ASSESS-02-TC03 | B12: Verify post /api/v1/attempts/{id}/coding-submissions succeeds with valid input (POST /api/v1/attempts/{id}/coding-submissions). | C12: 1. Log in as Recruiter of tenant A. 2. Send POST /api/v1/attempts/{id}/coding-submissions with header X-Tenant-ID = tenant A and a valid request body. 3. Check the response and the data shown in the system. | D12: HTTP 200/201. Response success = true; the record/action is saved and returned in the response. | E12: Tenant A is ACTIVE. The Recruiter account has permission for this action. The target resource exists. | F12: Pending | H12: Lê Mỹ Lộc | O12: Not tested: API not implemented yet.
A13: ASSESS-02-TC04 | B13: Verify post /api/v1/attempts/{id}/coding-submissions rejects invalid input (POST /api/v1/attempts/{id}/coding-submissions). | C13: 1. Log in as Recruiter of tenant A. 2. Send POST /api/v1/attempts/{id}/coding-submissions with header X-Tenant-ID = tenant A with missing required fields or invalid values (empty text, wrong format, out-of-range numbers, non-existing IDs). 3. Check the response and the data in the system. | D13: HTTP 400 (or 404 for a non-existing ID) with success = false and an error message / field errors. No data is created or changed. | E13: Tenant A is ACTIVE. The Recruiter account has permission for this action. The target resource exists. | F13: Pending | H13: Lê Mỹ Lộc | O13: Not tested: API not implemented yet.
A14: GET /api/v1/coding-submissions/{id} (GET /api/v1/coding-submissions/{id})
A15: ASSESS-02-TC05 | B15: Verify get /api/v1/coding-submissions/{id} succeeds with valid input (GET /api/v1/coding-submissions/{id}). | C15: 1. Log in as Recruiter of tenant A. 2. Send GET /api/v1/coding-submissions/{id} with header X-Tenant-ID = tenant A. 3. Check the response and the data shown in the system. | D15: HTTP 200. Response success = true and contains the requested data of tenant A only. | E15: Tenant A is ACTIVE. The Recruiter account has permission for this action. The target resource exists. | F15: Pending | H15: Lê Mỹ Lộc | O15: Not tested: API not implemented yet.
A16: Security & tenant isolation
A17: ASSESS-02-TC06 | B17: Verify protected APIs of this feature reject unauthenticated and unauthorized users. | C17: 1. Send POST /api/v1/attempts/{id}/coding-submissions without an Authorization header. 2. Send the same request with a valid token of a role that is not allowed (e.g. Candidate calling a staff API). | D17: Step 1: HTTP 401, code UNAUTHORIZED. Step 2: HTTP 403, code FORBIDDEN. No data is returned or changed. | E17: Accounts of an allowed role and a not-allowed role exist in tenant A. | F17: Pending | H17: Lê Mỹ Lộc | O17: Not tested: no automated test covers this feature yet.
A18: ASSESS-02-TC07 | B18: Verify tenant data isolation: a tenant B user cannot read or change tenant A data. | C18: 1. Log in as Recruiter of tenant B. 2. Send POST /api/v1/attempts/{id}/coding-submissions using a resource ID that belongs to tenant A, with header X-Tenant-ID = tenant A. 3. Open the related list screen of tenant B. | D18: Step 2: the tenant in the JWT (tenant B) is used, so the request returns HTTP 404 (or an empty result); no tenant A data is returned or changed. Step 3: only tenant B records are listed. | E18: Tenant A and tenant B are ACTIVE and both have data for this feature. | F18: Pending | H18: Lê Mỹ Lộc | O18: Not tested: no automated test covers this feature yet.

Sheet ASSESS-03
A2: Feature | B2: Auto Grading | R2: Passed
A3: Test requirement | B3: Verify the business rules and APIs of ASSESS-03 - Auto Grading as specified in docs/features/Technical-Assessment/Auto-Grading.md. | R3: Failed
A4: Number of TCs | B4: =COUNTIF(A11:A2000,"*-TC*") -> 0 | R4: Pending
A5: Testing Round | B5: Passed | C5: Failed | D5: Pending | E5: N/A | R5: N/A
A6: Round 1 | B6: =COUNTIF($F$11:$F$2000,B$5) -> 0 | C6: =COUNTIF($F$11:$F$2000,C$5) -> 0 | D6: =COUNTIF($F$11:$F$2000,D$5) -> 0 | E6: =COUNTIF($F$11:$F$2000,E$5) -> 0
A7: Round 2 | B7: =COUNTIF($I$11:$I$2000,B$5) -> 0 | C7: =COUNTIF($I$11:$I$2000,C$5) -> 0 | D7: =COUNTIF($I$11:$I$2000,D$5) -> 0 | E7: =COUNTIF($I$11:$I$2000,E$5) -> 0
A8: Round 3 | B8: =COUNTIF($L$11:$L$2000,B$5) -> 0 | C8: =COUNTIF($L$11:$L$2000,C$5) -> 0 | D8: =COUNTIF($L$11:$L$2000,D$5) -> 0 | E8: =COUNTIF($L$11:$L$2000,E$5) -> 0
A10: Test Case ID | B10: Test Case Description | C10: Test Case Procedure | D10: Expected Results | E10: Pre-conditions | F10: Round 1 | G10: Test date | H10: Tester | I10: Round 2 | J10: Test date | K10: Tester | L10: Round 3 | M10: Test date | N10: Tester | O10: Note

Sheet ASSESS-04
A2: Feature | B2: Timer Control | R2: Passed
A3: Test requirement | B3: Verify the business rules and APIs of ASSESS-04 - Timer Control as specified in docs/features/Technical-Assessment/Timer-Control.md. | R3: Failed
A4: Number of TCs | B4: =COUNTIF(A11:A2000,"*-TC*") -> 5 | R4: Pending
A5: Testing Round | B5: Passed | C5: Failed | D5: Pending | E5: N/A | R5: N/A
A6: Round 1 | B6: =COUNTIF($F$11:$F$2000,B$5) -> 5 | C6: =COUNTIF($F$11:$F$2000,C$5) -> 0 | D6: =COUNTIF($F$11:$F$2000,D$5) -> 0 | E6: =COUNTIF($F$11:$F$2000,E$5) -> 0
A7: Round 2 | B7: =COUNTIF($I$11:$I$2000,B$5) -> 0 | C7: =COUNTIF($I$11:$I$2000,C$5) -> 0 | D7: =COUNTIF($I$11:$I$2000,D$5) -> 0 | E7: =COUNTIF($I$11:$I$2000,E$5) -> 0
A8: Round 3 | B8: =COUNTIF($L$11:$L$2000,B$5) -> 0 | C8: =COUNTIF($L$11:$L$2000,C$5) -> 0 | D8: =COUNTIF($L$11:$L$2000,D$5) -> 0 | E8: =COUNTIF($L$11:$L$2000,E$5) -> 0
A10: Test Case ID | B10: Test Case Description | C10: Test Case Procedure | D10: Expected Results | E10: Pre-conditions | F10: Round 1 | G10: Test date | H10: Tester | I10: Round 2 | J10: Test date | K10: Tester | L10: Round 3 | M10: Test date | N10: Tester | O10: Note
A11: Deadline (GET /api/v1/submissions/{id}/get_submission)
A12: ASSESS-04-TC03 | B12: Verify deadline succeeds with valid input (GET /api/v1/submissions/{id}/get_submission). | C12: 1. Log in as Candidate of tenant A. 2. Send GET /api/v1/submissions/{id}/get_submission with header X-Tenant-ID = tenant A. 3. Check the response and the data shown in the system. | D12: HTTP 200. Response success = true and contains the requested data of tenant A only. | E12: Tenant A is ACTIVE. The Candidate account has permission for this action. The target resource exists. | F12: Passed | G12: 08/10/2026 | H12: Lê Mỹ Lộc | O12: Verified by automated tests: AssessmentFlowTest, SubmissionServiceStaffListTest
A13: Answers (POST /api/v1/submissions/{id}/submit_test)
A14: ASSESS-04-TC04 | B14: Verify answers succeeds with valid input (POST /api/v1/submissions/{id}/submit_test). | C14: 1. Log in as Candidate of tenant A. 2. Send POST /api/v1/submissions/{id}/submit_test with header X-Tenant-ID = tenant A and a valid request body. 3. Check the response and the data shown in the system. | D14: HTTP 200/201. Response success = true; the record/action is saved and returned in the response. | E14: Tenant A is ACTIVE. The Candidate account has permission for this action. The target resource exists. | F14: Passed | G14: 08/10/2026 | H14: Lê Mỹ Lộc | O14: Verified by automated tests: AssessmentFlowTest, SubmissionServiceStaffListTest
A15: ASSESS-04-TC05 | B15: Verify answers rejects invalid input (POST /api/v1/submissions/{id}/submit_test). | C15: 1. Log in as Candidate of tenant A. 2. Send POST /api/v1/submissions/{id}/submit_test with header X-Tenant-ID = tenant A with missing required fields or invalid values (empty text, wrong format, out-of-range numbers, non-existing IDs). 3. Check the response and the data in the system. | D15: HTTP 400 (or 404 for a non-existing ID) with success = false and an error message / field errors. No data is created or changed. | E15: Tenant A is ACTIVE. The Candidate account has permission for this action. The target resource exists. | F15: Passed | G15: 08/10/2026 | H15: Lê Mỹ Lộc | O15: Verified by automated tests: AssessmentFlowTest, SubmissionServiceStaffListTest
A16: Security & tenant isolation
A17: ASSESS-04-TC06 | B17: Verify protected APIs of this feature reject unauthenticated and unauthorized users. | C17: 1. Send GET /api/v1/submissions/{id}/get_submission without an Authorization header. 2. Send the same request with a valid token of a role that is not allowed (e.g. Candidate calling a staff API). | D17: Step 1: HTTP 401, code UNAUTHORIZED. Step 2: HTTP 403, code FORBIDDEN. No data is returned or changed. | E17: Accounts of an allowed role and a not-allowed role exist in tenant A. | F17: Passed | G17: 08/10/2026 | H17: Lê Mỹ Lộc | O17: Verified by automated tests: AssessmentFlowTest, SubmissionServiceStaffListTest
A18: ASSESS-04-TC07 | B18: Verify tenant data isolation: a tenant B user cannot read or change tenant A data. | C18: 1. Log in as Candidate of tenant B. 2. Send GET /api/v1/submissions/{id}/get_submission using a resource ID that belongs to tenant A, with header X-Tenant-ID = tenant A. 3. Open the related list screen of tenant B. | D18: Step 2: the tenant in the JWT (tenant B) is used, so the request returns HTTP 404 (or an empty result); no tenant A data is returned or changed. Step 3: only tenant B records are listed. | E18: Tenant A and tenant B are ACTIVE and both have data for this feature. | F18: Passed | G18: 08/10/2026 | H18: Lê Mỹ Lộc | O18: Verified by automated tests: AssessmentFlowTest, SubmissionServiceStaffListTest

Sheet ASSESS-05
A2: Feature | B2: Anti-cheating Detection | R2: Passed
A3: Test requirement | B3: Verify the business rules and APIs of ASSESS-05 - Anti-cheating Detection as specified in docs/features/Technical-Assessment/Anti-Cheating.md. | R3: Failed
A4: Number of TCs | B4: =COUNTIF(A11:A2000,"*-TC*") -> 7 | R4: Pending
A5: Testing Round | B5: Passed | C5: Failed | D5: Pending | E5: N/A | R5: N/A
A6: Round 1 | B6: =COUNTIF($F$11:$F$2000,B$5) -> 4 | C6: =COUNTIF($F$11:$F$2000,C$5) -> 0 | D6: =COUNTIF($F$11:$F$2000,D$5) -> 3 | E6: =COUNTIF($F$11:$F$2000,E$5) -> 0
A7: Round 2 | B7: =COUNTIF($I$11:$I$2000,B$5) -> 0 | C7: =COUNTIF($I$11:$I$2000,C$5) -> 0 | D7: =COUNTIF($I$11:$I$2000,D$5) -> 0 | E7: =COUNTIF($I$11:$I$2000,E$5) -> 0
A8: Round 3 | B8: =COUNTIF($L$11:$L$2000,B$5) -> 0 | C8: =COUNTIF($L$11:$L$2000,C$5) -> 0 | D8: =COUNTIF($L$11:$L$2000,D$5) -> 0 | E8: =COUNTIF($L$11:$L$2000,E$5) -> 0
A10: Test Case ID | B10: Test Case Description | C10: Test Case Procedure | D10: Expected Results | E10: Pre-conditions | F10: Round 1 | G10: Test date | H10: Tester | I10: Round 2 | J10: Test date | K10: Tester | L10: Round 3 | M10: Test date | N10: Tester | O10: Note
A11: POST /api/v1/attempts/{id}/proctor-events (POST /api/v1/attempts/{id}/proctor-events)
A12: ASSESS-05-TC03 | B12: Verify post /api/v1/attempts/{id}/proctor-events succeeds with valid input (POST /api/v1/attempts/{id}/proctor-events). | C12: 1. Log in as Recruiter of tenant A. 2. Send POST /api/v1/attempts/{id}/proctor-events with header X-Tenant-ID = tenant A and a valid request body. 3. Check the response and the data shown in the system. | D12: HTTP 200/201. Response success = true; the record/action is saved and returned in the response. | E12: Tenant A is ACTIVE. The Recruiter account has permission for this action. The target resource exists. | F12: Pending | H12: Lê Mỹ Lộc | O12: Not tested: API not implemented yet.
A13: ASSESS-05-TC04 | B13: Verify post /api/v1/attempts/{id}/proctor-events rejects invalid input (POST /api/v1/attempts/{id}/proctor-events). | C13: 1. Log in as Recruiter of tenant A. 2. Send POST /api/v1/attempts/{id}/proctor-events with header X-Tenant-ID = tenant A with missing required fields or invalid values (empty text, wrong format, out-of-range numbers, non-existing IDs). 3. Check the response and the data in the system. | D13: HTTP 400 (or 404 for a non-existing ID) with success = false and an error message / field errors. No data is created or changed. | E13: Tenant A is ACTIVE. The Recruiter account has permission for this action. The target resource exists. | F13: Pending | H13: Lê Mỹ Lộc | O13: Not tested: API not implemented yet.
A14: GET /api/v1/attempts/{id}/proctor-report (GET /api/v1/attempts/{id}/proctor-report)
A15: ASSESS-05-TC05 | B15: Verify get /api/v1/attempts/{id}/proctor-report succeeds with valid input (GET /api/v1/attempts/{id}/proctor-report). | C15: 1. Log in as Recruiter of tenant A. 2. Send GET /api/v1/attempts/{id}/proctor-report with header X-Tenant-ID = tenant A. 3. Check the response and the data shown in the system. | D15: HTTP 200. Response success = true and contains the requested data of tenant A only. | E15: Tenant A is ACTIVE. The Recruiter account has permission for this action. The target resource exists. | F15: Pending | H15: Lê Mỹ Lộc | O15: Not tested: API not implemented yet.
A16: Interview (POST /api/v1/ai-interviews/{id}/proctor-events)
A17: ASSESS-05-TC06 | B17: Verify interview succeeds with valid input (POST /api/v1/ai-interviews/{id}/proctor-events). | C17: 1. Log in as Recruiter of tenant A. 2. Send POST /api/v1/ai-interviews/{id}/proctor-events with header X-Tenant-ID = tenant A and a valid request body. 3. Check the response and the data shown in the system. | D17: HTTP 200/201. Response success = true; the record/action is saved and returned in the response. | E17: Tenant A is ACTIVE. The Recruiter account has permission for this action. The target resource exists. | F17: Passed | G17: 08/10/2026 | H17: Lê Mỹ Lộc | O17: Verified by automated tests: AiInterviewCandidateTest, AiInterviewVoiceServiceTest
A18: ASSESS-05-TC07 | B18: Verify interview rejects invalid input (POST /api/v1/ai-interviews/{id}/proctor-events). | C18: 1. Log in as Recruiter of tenant A. 2. Send POST /api/v1/ai-interviews/{id}/proctor-events with header X-Tenant-ID = tenant A with missing required fields or invalid values (empty text, wrong format, out-of-range numbers, non-existing IDs). 3. Check the response and the data in the system. | D18: HTTP 400 (or 404 for a non-existing ID) with success = false and an error message / field errors. No data is created or changed. | E18: Tenant A is ACTIVE. The Recruiter account has permission for this action. The target resource exists. | F18: Passed | G18: 08/10/2026 | H18: Lê Mỹ Lộc | O18: Verified by automated tests: AiInterviewCandidateTest, AiInterviewVoiceServiceTest
A19: Security & tenant isolation
A20: ASSESS-05-TC08 | B20: Verify protected APIs of this feature reject unauthenticated and unauthorized users. | C20: 1. Send POST /api/v1/attempts/{id}/proctor-events without an Authorization header. 2. Send the same request with a valid token of a role that is not allowed (e.g. Candidate calling a staff API). | D20: Step 1: HTTP 401, code UNAUTHORIZED. Step 2: HTTP 403, code FORBIDDEN. No data is returned or changed. | E20: Accounts of an allowed role and a not-allowed role exist in tenant A. | F20: Passed | G20: 08/10/2026 | H20: Lê Mỹ Lộc | O20: Verified by automated tests: AiInterviewCandidateTest, AiInterviewVoiceServiceTest
A21: ASSESS-05-TC09 | B21: Verify tenant data isolation: a tenant B user cannot read or change tenant A data. | C21: 1. Log in as Recruiter of tenant B. 2. Send POST /api/v1/attempts/{id}/proctor-events using a resource ID that belongs to tenant A, with header X-Tenant-ID = tenant A. 3. Open the related list screen of tenant B. | D21: Step 2: the tenant in the JWT (tenant B) is used, so the request returns HTTP 404 (or an empty result); no tenant A data is returned or changed. Step 3: only tenant B records are listed. | E21: Tenant A and tenant B are ACTIVE and both have data for this feature. | F21: Passed | G21: 08/10/2026 | H21: Lê Mỹ Lộc | O21: Verified by automated tests: AiInterviewCandidateTest, AiInterviewVoiceServiceTest

Sheet AUTH-01
A2: Feature | B2: User Registration | R2: Passed
A3: Test requirement | B3: Verify the business rules and APIs of AUTH-01 - User Registration as specified in docs/features/Authentication/User-Registration.md. | R3: Failed
A4: Number of TCs | B4: =COUNTIF(A11:A2000,"*-TC*") -> 4 | R4: Pending
A5: Testing Round | B5: Passed | C5: Failed | D5: Pending | E5: N/A | R5: N/A
A6: Round 1 | B6: =COUNTIF($F$11:$F$2000,B$5) -> 0 | C6: =COUNTIF($F$11:$F$2000,C$5) -> 0 | D6: =COUNTIF($F$11:$F$2000,D$5) -> 4 | E6: =COUNTIF($F$11:$F$2000,E$5) -> 0
A7: Round 2 | B7: =COUNTIF($I$11:$I$2000,B$5) -> 0 | C7: =COUNTIF($I$11:$I$2000,C$5) -> 0 | D7: =COUNTIF($I$11:$I$2000,D$5) -> 0 | E7: =COUNTIF($I$11:$I$2000,E$5) -> 0
A8: Round 3 | B8: =COUNTIF($L$11:$L$2000,B$5) -> 0 | C8: =COUNTIF($L$11:$L$2000,C$5) -> 0 | D8: =COUNTIF($L$11:$L$2000,D$5) -> 0 | E8: =COUNTIF($L$11:$L$2000,E$5) -> 0
A10: Test Case ID | B10: Test Case Description | C10: Test Case Procedure | D10: Expected Results | E10: Pre-conditions | F10: Round 1 | G10: Test date | H10: Tester | I10: Round 2 | J10: Test date | K10: Tester | L10: Round 3 | M10: Test date | N10: Tester | O10: Note
A11: POST /api/v1/auth/register (POST /api/v1/auth/register)
A12: AUTH-01-TC05 | B12: Verify post /api/v1/auth/register succeeds with valid input (POST /api/v1/auth/register). | C12: 1. Log in as Recruiter of tenant A. 2. Send POST /api/v1/auth/register with header X-Tenant-ID = tenant A and a valid request body. 3. Check the response and the data shown in the system. | D12: HTTP 200/201. Response success = true; the record/action is saved and returned in the response. | E12: Tenant A is ACTIVE. The Recruiter account has permission for this action. | F12: Pending | H12: Nguyễn Nhất Sinh | O12: Not tested: API not implemented yet.
A13: AUTH-01-TC06 | B13: Verify post /api/v1/auth/register rejects invalid input (POST /api/v1/auth/register). | C13: 1. Log in as Recruiter of tenant A. 2. Send POST /api/v1/auth/register with header X-Tenant-ID = tenant A with missing required fields or invalid values (empty text, wrong format, out-of-range numbers, non-existing IDs). 3. Check the response and the data in the system. | D13: HTTP 400 (or 404 for a non-existing ID) with success = false and an error message / field errors. No data is created or changed. | E13: Tenant A is ACTIVE. The Recruiter account has permission for this action. | F13: Pending | H13: Nguyễn Nhất Sinh | O13: Not tested: API not implemented yet.
A14: Security & tenant isolation
A15: AUTH-01-TC07 | B15: Verify protected APIs of this feature reject unauthenticated and unauthorized users. | C15: 1. Send POST /api/v1/auth/register without an Authorization header. 2. Send the same request with a valid token of a role that is not allowed (e.g. Candidate calling a staff API). | D15: Step 1: HTTP 401, code UNAUTHORIZED. Step 2: HTTP 403, code FORBIDDEN. No data is returned or changed. | E15: Accounts of an allowed role and a not-allowed role exist in tenant A. | F15: Pending | H15: Nguyễn Nhất Sinh | O15: Not tested: no automated test covers this feature yet.
A16: AUTH-01-TC08 | B16: Verify tenant data isolation: a tenant B user cannot read or change tenant A data. | C16: 1. Log in as Recruiter of tenant B. 2. Send POST /api/v1/auth/register using a resource ID that belongs to tenant A, with header X-Tenant-ID = tenant A. 3. Open the related list screen of tenant B. | D16: Step 2: the tenant in the JWT (tenant B) is used, so the request returns HTTP 404 (or an empty result); no tenant A data is returned or changed. Step 3: only tenant B records are listed. | E16: Tenant A and tenant B are ACTIVE and both have data for this feature. | F16: Pending | H16: Nguyễn Nhất Sinh | O16: Not tested: no automated test covers this feature yet.

Sheet AUTH-02
A2: Feature | B2: Login & JWT Authentication | R2: Passed
A3: Test requirement | B3: Verify the business rules and APIs of AUTH-02 - Login & JWT Authentication as specified in docs/features/Authentication/Login-JWT.md. | R3: Failed
A4: Number of TCs | B4: =COUNTIF(A11:A2000,"*-TC*") -> 18 | R4: Pending
A5: Testing Round | B5: Passed | C5: Failed | D5: Pending | E5: N/A | R5: N/A
A6: Round 1 | B6: =COUNTIF($F$11:$F$2000,B$5) -> 18 | C6: =COUNTIF($F$11:$F$2000,C$5) -> 0 | D6: =COUNTIF($F$11:$F$2000,D$5) -> 0 | E6: =COUNTIF($F$11:$F$2000,E$5) -> 0
A7: Round 2 | B7: =COUNTIF($I$11:$I$2000,B$5) -> 0 | C7: =COUNTIF($I$11:$I$2000,C$5) -> 0 | D7: =COUNTIF($I$11:$I$2000,D$5) -> 0 | E7: =COUNTIF($I$11:$I$2000,E$5) -> 0
A8: Round 3 | B8: =COUNTIF($L$11:$L$2000,B$5) -> 0 | C8: =COUNTIF($L$11:$L$2000,C$5) -> 0 | D8: =COUNTIF($L$11:$L$2000,D$5) -> 0 | E8: =COUNTIF($L$11:$L$2000,E$5) -> 0
A10: Test Case ID | B10: Test Case Description | C10: Test Case Procedure | D10: Expected Results | E10: Pre-conditions | F10: Round 1 | G10: Test date | H10: Tester | I10: Round 2 | J10: Test date | K10: Tester | L10: Round 3 | M10: Test date | N10: Tester | O10: Note
A11: Login (POST /api/v1/tenant/auth/login)
A12: AUTH-02-TC07 | B12: Verify login succeeds with valid input (POST /api/v1/tenant/auth/login). | C12: 1. Do not log in (public endpoint). 2. Send POST /api/v1/tenant/auth/login and a valid request body. 3. Check the response and the data shown in the system. | D12: HTTP 200/201. Response success = true; the record/action is saved and returned in the response. | E12: Tenant A is ACTIVE. | F12: Passed | G12: 14/10/2026 | H12: Nguyễn Nhất Sinh | O12: Verified by automated tests: AccountProfileServiceTest, InviteMailSenderTest, TenantAuthControllerTest ...
A13: AUTH-02-TC08 | B13: Verify login rejects invalid input (POST /api/v1/tenant/auth/login). | C13: 1. Do not log in (public endpoint). 2. Send POST /api/v1/tenant/auth/login with missing required fields or invalid values (empty text, wrong format, out-of-range numbers, non-existing IDs). 3. Check the response and the data in the system. | D13: HTTP 400 (or 404 for a non-existing ID) with success = false and an error message / field errors. No data is created or changed. | E13: Tenant A is ACTIVE. | F13: Passed | G13: 14/10/2026 | H13: Nguyễn Nhất Sinh | O13: Verified by automated tests: AccountProfileServiceTest, InviteMailSenderTest, TenantAuthControllerTest ...
A14: Refresh (POST /api/v1/tenant/auth/refresh)
A15: AUTH-02-TC09 | B15: Verify refresh succeeds with valid input (POST /api/v1/tenant/auth/refresh). | C15: 1. Do not log in (public endpoint). 2. Send POST /api/v1/tenant/auth/refresh and a valid request body. 3. Check the response and the data shown in the system. | D15: HTTP 200/201. Response success = true; the record/action is saved and returned in the response. | E15: Tenant A is ACTIVE. | F15: Passed | G15: 14/10/2026 | H15: Nguyễn Nhất Sinh | O15: Verified by automated tests: AccountProfileServiceTest, InviteMailSenderTest, TenantAuthControllerTest ...
A16: AUTH-02-TC10 | B16: Verify refresh rejects invalid input (POST /api/v1/tenant/auth/refresh). | C16: 1. Do not log in (public endpoint). 2. Send POST /api/v1/tenant/auth/refresh with missing required fields or invalid values (empty text, wrong format, out-of-range numbers, non-existing IDs). 3. Check the response and the data in the system. | D16: HTTP 400 (or 404 for a non-existing ID) with success = false and an error message / field errors. No data is created or changed. | E16: Tenant A is ACTIVE. | F16: Passed | G16: 14/10/2026 | H16: Nguyễn Nhất Sinh | O16: Verified by automated tests: AccountProfileServiceTest, InviteMailSenderTest, TenantAuthControllerTest ...
A17: Logout (POST /api/v1/tenant/auth/logout)
A18: AUTH-02-TC11 | B18: Verify logout succeeds with valid input (POST /api/v1/tenant/auth/logout). | C18: 1. Do not log in (public endpoint). 2. Send POST /api/v1/tenant/auth/logout and a valid request body. 3. Check the response and the data shown in the system. | D18: HTTP 200/201. Response success = true; the record/action is saved and returned in the response. | E18: Tenant A is ACTIVE. | F18: Passed | G18: 14/10/2026 | H18: Nguyễn Nhất Sinh | O18: Verified by automated tests: AccountProfileServiceTest, InviteMailSenderTest, TenantAuthControllerTest ...
A19: AUTH-02-TC12 | B19: Verify logout rejects invalid input (POST /api/v1/tenant/auth/logout). | C19: 1. Do not log in (public endpoint). 2. Send POST /api/v1/tenant/auth/logout with missing required fields or invalid values (empty text, wrong format, out-of-range numbers, non-existing IDs). 3. Check the response and the data in the system. | D19: HTTP 400 (or 404 for a non-existing ID) with success = false and an error message / field errors. No data is created or changed. | E19: Tenant A is ACTIVE. | F19: Passed | G19: 14/10/2026 | H19: Nguyễn Nhất Sinh | O19: Verified by automated tests: AccountProfileServiceTest, InviteMailSenderTest, TenantAuthControllerTest ...
A20: Password (POST /api/v1/tenant/auth/forgot-password)
A21: AUTH-02-TC13 | B21: Verify password succeeds with valid input (POST /api/v1/tenant/auth/forgot-password). | C21: 1. Do not log in (public endpoint). 2. Send POST /api/v1/tenant/auth/forgot-password and a valid request body. 3. Check the response and the data shown in the system. | D21: HTTP 200/201. Response success = true; the record/action is saved and returned in the response. | E21: Tenant A is ACTIVE. | F21: Passed | G21: 14/10/2026 | H21: Nguyễn Nhất Sinh | O21: Verified by automated tests: AccountProfileServiceTest, InviteMailSenderTest, TenantAuthControllerTest ...
A22: AUTH-02-TC14 | B22: Verify password rejects invalid input (POST /api/v1/tenant/auth/forgot-password). | C22: 1. Do not log in (public endpoint). 2. Send POST /api/v1/tenant/auth/forgot-password with missing required fields or invalid values (empty text, wrong format, out-of-range numbers, non-existing IDs). 3. Check the response and the data in the system. | D22: HTTP 400 (or 404 for a non-existing ID) with success = false and an error message / field errors. No data is created or changed. | E22: Tenant A is ACTIVE. | F22: Passed | G22: 14/10/2026 | H22: Nguyễn Nhất Sinh | O22: Verified by automated tests: AccountProfileServiceTest, InviteMailSenderTest, TenantAuthControllerTest ...
A23: Reset password (POST /api/v1/tenant/auth/reset-password)
A24: AUTH-02-TC15 | B24: Verify reset password succeeds with valid input (POST /api/v1/tenant/auth/reset-password). | C24: 1. Do not log in (public endpoint). 2. Send POST /api/v1/tenant/auth/reset-password and a valid request body. 3. Check the response and the data shown in the system. | D24: HTTP 200/201. Response success = true; the record/action is saved and returned in the response. | E24: Tenant A is ACTIVE. | F24: Passed | G24: 14/10/2026 | H24: Nguyễn Nhất Sinh | O24: Verified by automated tests: AccountProfileServiceTest, InviteMailSenderTest, TenantAuthControllerTest ...
A25: AUTH-02-TC16 | B25: Verify reset password rejects invalid input (POST /api/v1/tenant/auth/reset-password). | C25: 1. Do not log in (public endpoint). 2. Send POST /api/v1/tenant/auth/reset-password with missing required fields or invalid values (empty text, wrong format, out-of-range numbers, non-existing IDs). 3. Check the response and the data in the system. | D25: HTTP 400 (or 404 for a non-existing ID) with success = false and an error message / field errors. No data is created or changed. | E25: Tenant A is ACTIVE. | F25: Passed | G25: 14/10/2026 | H25: Nguyễn Nhất Sinh | O25: Verified by automated tests: AccountProfileServiceTest, InviteMailSenderTest, TenantAuthControllerTest ...
A26: Change password (POST /api/v1/tenant/auth/change-password)
A27: AUTH-02-TC17 | B27: Verify change password succeeds with valid input (POST /api/v1/tenant/auth/change-password). | C27: 1. Log in as Admin of tenant A. 2. Send POST /api/v1/tenant/auth/change-password with header X-Tenant-ID = tenant A and a valid request body. 3. Check the response and the data shown in the system. | D27: HTTP 200/201. Response success = true; the record/action is saved and returned in the response. | E27: Tenant A is ACTIVE. The Admin account has permission for this action. | F27: Passed | G27: 14/10/2026 | H27: Nguyễn Nhất Sinh | O27: Verified by automated tests: AccountProfileServiceTest, InviteMailSenderTest, TenantAuthControllerTest ...
A28: AUTH-02-TC18 | B28: Verify change password rejects invalid input (POST /api/v1/tenant/auth/change-password). | C28: 1. Log in as Admin of tenant A. 2. Send POST /api/v1/tenant/auth/change-password with header X-Tenant-ID = tenant A with missing required fields or invalid values (empty text, wrong format, out-of-range numbers, non-existing IDs). 3. Check the response and the data in the system. | D28: HTTP 400 (or 404 for a non-existing ID) with success = false and an error message / field errors. No data is created or changed. | E28: Tenant A is ACTIVE. The Admin account has permission for this action. | F28: Passed | G28: 14/10/2026 | H28: Nguyễn Nhất Sinh | O28: Verified by automated tests: AccountProfileServiceTest, InviteMailSenderTest, TenantAuthControllerTest ...
A29: Get current user (GET /api/v1/tenant/auth/me)
A30: AUTH-02-TC19 | B30: Verify get current user succeeds with valid input (GET /api/v1/tenant/auth/me). | C30: 1. Log in as Admin of tenant A. 2. Send GET /api/v1/tenant/auth/me with header X-Tenant-ID = tenant A. 3. Check the response and the data shown in the system. | D30: HTTP 200. Response success = true and contains the requested data of tenant A only. | E30: Tenant A is ACTIVE. The Admin account has permission for this action. | F30: Passed | G30: 14/10/2026 | H30: Nguyễn Nhất Sinh | O30: Verified by automated tests: AccountProfileServiceTest, InviteMailSenderTest, TenantAuthControllerTest ...
A31: Profile (GET /api/v1/tenant/auth/profile)
A32: AUTH-02-TC20 | B32: Verify profile succeeds with valid input (GET /api/v1/tenant/auth/profile). | C32: 1. Log in as Admin of tenant A. 2. Send GET /api/v1/tenant/auth/profile with header X-Tenant-ID = tenant A. 3. Check the response and the data shown in the system. | D32: HTTP 200. Response success = true and contains the requested data of tenant A only. | E32: Tenant A is ACTIVE. The Admin account has permission for this action. | F32: Passed | G32: 14/10/2026 | H32: Nguyễn Nhất Sinh | O32: Verified by automated tests: AccountProfileServiceTest, InviteMailSenderTest, TenantAuthControllerTest ...
A33: Update profile (PUT /api/v1/tenant/auth/profile)
A34: AUTH-02-TC21 | B34: Verify update profile succeeds with valid input (PUT /api/v1/tenant/auth/profile). | C34: 1. Log in as Admin of tenant A. 2. Send PUT /api/v1/tenant/auth/profile with header X-Tenant-ID = tenant A and a valid request body. 3. Check the response and the data shown in the system. | D34: HTTP 200. Response success = true; the changes are saved and returned. | E34: Tenant A is ACTIVE. The Admin account has permission for this action. | F34: Passed | G34: 14/10/2026 | H34: Nguyễn Nhất Sinh | O34: Verified by automated tests: AccountProfileServiceTest, InviteMailSenderTest, TenantAuthControllerTest ...
A35: AUTH-02-TC22 | B35: Verify update profile rejects invalid input (PUT /api/v1/tenant/auth/profile). | C35: 1. Log in as Admin of tenant A. 2. Send PUT /api/v1/tenant/auth/profile with header X-Tenant-ID = tenant A with missing required fields or invalid values (empty text, wrong format, out-of-range numbers, non-existing IDs). 3. Check the response and the data in the system. | D35: HTTP 400 (or 404 for a non-existing ID) with success = false and an error message / field errors. No data is created or changed. | E35: Tenant A is ACTIVE. The Admin account has permission for this action. | F35: Passed | G35: 14/10/2026 | H35: Nguyễn Nhất Sinh | O35: Verified by automated tests: AccountProfileServiceTest, InviteMailSenderTest, TenantAuthControllerTest ...
A36: Security & tenant isolation
A37: AUTH-02-TC23 | B37: Verify protected APIs of this feature reject unauthenticated and unauthorized users. | C37: 1. Send POST /api/v1/tenant/auth/change-password without an Authorization header. 2. Send the same request with a valid token of a role that is not allowed (e.g. Candidate calling a staff API). | D37: Step 1: HTTP 401, code UNAUTHORIZED. Step 2: HTTP 403, code FORBIDDEN. No data is returned or changed. | E37: Accounts of an allowed role and a not-allowed role exist in tenant A. | F37: Passed | G37: 14/10/2026 | H37: Nguyễn Nhất Sinh | O37: Verified by automated tests: AccountProfileServiceTest, InviteMailSenderTest, TenantAuthControllerTest ...
A38: AUTH-02-TC24 | B38: Verify tenant data isolation: a tenant B user cannot read or change tenant A data. | C38: 1. Log in as Admin of tenant B. 2. Send POST /api/v1/tenant/auth/change-password using a resource ID that belongs to tenant A, with header X-Tenant-ID = tenant A. 3. Open the related list screen of tenant B. | D38: Step 2: the tenant in the JWT (tenant B) is used, so the request returns HTTP 404 (or an empty result); no tenant A data is returned or changed. Step 3: only tenant B records are listed. | E38: Tenant A and tenant B are ACTIVE and both have data for this feature. | F38: Passed | G38: 14/10/2026 | H38: Nguyễn Nhất Sinh | O38: Verified by automated tests: AccountProfileServiceTest, InviteMailSenderTest, TenantAuthControllerTest ...

Sheet AUTH-03
A2: Feature | B2: Google OAuth Login | R2: Passed
A3: Test requirement | B3: Verify the business rules and APIs of AUTH-03 - Google OAuth Login as specified in docs/features/Authentication/Google-OAuth.md. | R3: Failed
A4: Number of TCs | B4: =COUNTIF(A11:A2000,"*-TC*") -> 4 | R4: Pending
A5: Testing Round | B5: Passed | C5: Failed | D5: Pending | E5: N/A | R5: N/A
A6: Round 1 | B6: =COUNTIF($F$11:$F$2000,B$5) -> 2 | C6: =COUNTIF($F$11:$F$2000,C$5) -> 0 | D6: =COUNTIF($F$11:$F$2000,D$5) -> 0 | E6: =COUNTIF($F$11:$F$2000,E$5) -> 2
A7: Round 2 | B7: =COUNTIF($I$11:$I$2000,B$5) -> 0 | C7: =COUNTIF($I$11:$I$2000,C$5) -> 0 | D7: =COUNTIF($I$11:$I$2000,D$5) -> 0 | E7: =COUNTIF($I$11:$I$2000,E$5) -> 0
A8: Round 3 | B8: =COUNTIF($L$11:$L$2000,B$5) -> 0 | C8: =COUNTIF($L$11:$L$2000,C$5) -> 0 | D8: =COUNTIF($L$11:$L$2000,D$5) -> 0 | E8: =COUNTIF($L$11:$L$2000,E$5) -> 0
A10: Test Case ID | B10: Test Case Description | C10: Test Case Procedure | D10: Expected Results | E10: Pre-conditions | F10: Round 1 | G10: Test date | H10: Tester | I10: Round 2 | J10: Test date | K10: Tester | L10: Round 3 | M10: Test date | N10: Tester | O10: Note
A11: Login with google (POST /api/v1/tenant/auth/google)
A12: AUTH-03-TC06 | B12: Verify login with google succeeds with valid input (POST /api/v1/tenant/auth/google). | C12: 1. Do not log in (public endpoint). 2. Send POST /api/v1/tenant/auth/google and a valid request body. 3. Check the response and the data shown in the system. | D12: HTTP 200/201. Response success = true; the record/action is saved and returned in the response. | E12: Tenant A is ACTIVE. | F12: Passed | G12: 08/10/2026 | H12: Nguyễn Nhất Sinh | O12: Verified by automated tests: CandidateAuthControllerTest, CandidateAuthServiceTest
A13: AUTH-03-TC07 | B13: Verify login with google rejects invalid input (POST /api/v1/tenant/auth/google). | C13: 1. Do not log in (public endpoint). 2. Send POST /api/v1/tenant/auth/google with missing required fields or invalid values (empty text, wrong format, out-of-range numbers, non-existing IDs). 3. Check the response and the data in the system. | D13: HTTP 400 (or 404 for a non-existing ID) with success = false and an error message / field errors. No data is created or changed. | E13: Tenant A is ACTIVE. | F13: Passed | G13: 08/10/2026 | H13: Nguyễn Nhất Sinh | O13: Verified by automated tests: CandidateAuthControllerTest, CandidateAuthServiceTest
A14: Security & tenant isolation
A15: AUTH-03-TC08 | B15: Verify protected APIs of this feature reject unauthenticated and unauthorized users. | C15: 1. Send without an Authorization header. 2. Send the same request with a valid token of a role that is not allowed (e.g. Candidate calling a staff API). | D15: Step 1: HTTP 401, code UNAUTHORIZED. Step 2: HTTP 403, code FORBIDDEN. No data is returned or changed. | E15: Accounts of an allowed role and a not-allowed role exist in tenant A. | F15: N/A | H15: Nguyễn Nhất Sinh | O15: All endpoints of this feature are public (permitAll).
A16: AUTH-03-TC09 | B16: Verify tenant data isolation: a tenant B user cannot read or change tenant A data. | C16: 1. Log in as Recruiter of tenant B. 2. Send using a resource ID that belongs to tenant A, with header X-Tenant-ID = tenant A. 3. Open the related list screen of tenant B. | D16: Step 2: the tenant in the JWT (tenant B) is used, so the request returns HTTP 404 (or an empty result); no tenant A data is returned or changed. Step 3: only tenant B records are listed. | E16: Tenant A and tenant B are ACTIVE and both have data for this feature. | F16: N/A | H16: Nguyễn Nhất Sinh | O16: All endpoints of this feature are public (permitAll).

Sheet AUTH-04
A2: Feature | B2: Role-Based Access Control (RBAC) | R2: Passed
A3: Test requirement | B3: Verify the business rules and APIs of AUTH-04 - Role-Based Access Control (RBAC) as specified in docs/features/Authentication/RBAC.md. | R3: Failed
A4: Number of TCs | B4: =COUNTIF(A11:A2000,"*-TC*") -> 17 | R4: Pending
A5: Testing Round | B5: Passed | C5: Failed | D5: Pending | E5: N/A | R5: N/A
A6: Round 1 | B6: =COUNTIF($F$11:$F$2000,B$5) -> 17 | C6: =COUNTIF($F$11:$F$2000,C$5) -> 0 | D6: =COUNTIF($F$11:$F$2000,D$5) -> 0 | E6: =COUNTIF($F$11:$F$2000,E$5) -> 0
A7: Round 2 | B7: =COUNTIF($I$11:$I$2000,B$5) -> 0 | C7: =COUNTIF($I$11:$I$2000,C$5) -> 0 | D7: =COUNTIF($I$11:$I$2000,D$5) -> 0 | E7: =COUNTIF($I$11:$I$2000,E$5) -> 0
A8: Round 3 | B8: =COUNTIF($L$11:$L$2000,B$5) -> 0 | C8: =COUNTIF($L$11:$L$2000,C$5) -> 0 | D8: =COUNTIF($L$11:$L$2000,D$5) -> 0 | E8: =COUNTIF($L$11:$L$2000,E$5) -> 0
A10: Test Case ID | B10: Test Case Description | C10: Test Case Procedure | D10: Expected Results | E10: Pre-conditions | F10: Round 1 | G10: Test date | H10: Tester | I10: Round 2 | J10: Test date | K10: Tester | L10: Round 3 | M10: Test date | N10: Tester | O10: Note
A11: List (GET /api/v1/tenant/roles)
A12: AUTH-04-TC12 | B12: Verify list succeeds with valid input (GET /api/v1/tenant/roles). | C12: 1. Log in as Admin of tenant A. 2. Send GET /api/v1/tenant/roles with header X-Tenant-ID = tenant A. 3. Check the response and the data shown in the system. | D12: HTTP 200. Response success = true and contains the requested data of tenant A only. | E12: Tenant A is ACTIVE. The Admin account has permission for this action. | F12: Passed | G12: 14/10/2026 | H12: Nguyễn Nhất Sinh | O12: Verified by automated tests: AccountProfileServiceTest, JobAssignmentServiceTest, MemberInvitationServiceTest ...
A13: Create (POST /api/v1/tenant/roles)
A14: AUTH-04-TC13 | B14: Verify create succeeds with valid input (POST /api/v1/tenant/roles). | C14: 1. Log in as Admin of tenant A. 2. Send POST /api/v1/tenant/roles with header X-Tenant-ID = tenant A and a valid request body. 3. Check the response and the data shown in the system. | D14: HTTP 200/201. Response success = true; the record/action is saved and returned in the response. | E14: Tenant A is ACTIVE. The Admin account has permission for this action. | F14: Passed | G14: 14/10/2026 | H14: Nguyễn Nhất Sinh | O14: Verified by automated tests: AccountProfileServiceTest, JobAssignmentServiceTest, MemberInvitationServiceTest ...
A15: AUTH-04-TC14 | B15: Verify create rejects invalid input (POST /api/v1/tenant/roles). | C15: 1. Log in as Admin of tenant A. 2. Send POST /api/v1/tenant/roles with header X-Tenant-ID = tenant A with missing required fields or invalid values (empty text, wrong format, out-of-range numbers, non-existing IDs). 3. Check the response and the data in the system. | D15: HTTP 400 (or 404 for a non-existing ID) with success = false and an error message / field errors. No data is created or changed. | E15: Tenant A is ACTIVE. The Admin account has permission for this action. | F15: Passed | G15: 14/10/2026 | H15: Nguyễn Nhất Sinh | O15: Verified by automated tests: AccountProfileServiceTest, JobAssignmentServiceTest, MemberInvitationServiceTest ...
A16: Name (PUT /api/v1/tenant/roles/{id})
A17: AUTH-04-TC15 | B17: Verify name succeeds with valid input (PUT /api/v1/tenant/roles/{id}). | C17: 1. Log in as Admin of tenant A. 2. Send PUT /api/v1/tenant/roles/{id} with header X-Tenant-ID = tenant A and a valid request body. 3. Check the response and the data shown in the system. | D17: HTTP 200. Response success = true; the changes are saved and returned. | E17: Tenant A is ACTIVE. The Admin account has permission for this action. The target resource exists. | F17: Passed | G17: 14/10/2026 | H17: Nguyễn Nhất Sinh | O17: Verified by automated tests: AccountProfileServiceTest, JobAssignmentServiceTest, MemberInvitationServiceTest ...
A18: AUTH-04-TC16 | B18: Verify name rejects invalid input (PUT /api/v1/tenant/roles/{id}). | C18: 1. Log in as Admin of tenant A. 2. Send PUT /api/v1/tenant/roles/{id} with header X-Tenant-ID = tenant A with missing required fields or invalid values (empty text, wrong format, out-of-range numbers, non-existing IDs). 3. Check the response and the data in the system. | D18: HTTP 400 (or 404 for a non-existing ID) with success = false and an error message / field errors. No data is created or changed. | E18: Tenant A is ACTIVE. The Admin account has permission for this action. The target resource exists. | F18: Passed | G18: 14/10/2026 | H18: Nguyễn Nhất Sinh | O18: Verified by automated tests: AccountProfileServiceTest, JobAssignmentServiceTest, MemberInvitationServiceTest ...
A19: Delete (DELETE /api/v1/tenant/roles/{id})
A20: AUTH-04-TC17 | B20: Verify delete succeeds with valid input (DELETE /api/v1/tenant/roles/{id}). | C20: 1. Log in as Admin of tenant A. 2. Send DELETE /api/v1/tenant/roles/{id} with header X-Tenant-ID = tenant A. 3. Check the response and the data shown in the system. | D20: HTTP 200/204. The record is removed (or archived) and no longer appears in lists. | E20: Tenant A is ACTIVE. The Admin account has permission for this action. The target resource exists. | F20: Passed | G20: 14/10/2026 | H20: Nguyễn Nhất Sinh | O20: Verified by automated tests: AccountProfileServiceTest, JobAssignmentServiceTest, MemberInvitationServiceTest ...
A21: AUTH-04-TC18 | B21: Verify delete rejects invalid input (DELETE /api/v1/tenant/roles/{id}). | C21: 1. Log in as Admin of tenant A. 2. Send DELETE /api/v1/tenant/roles/{id} with header X-Tenant-ID = tenant A with missing required fields or invalid values (empty text, wrong format, out-of-range numbers, non-existing IDs). 3. Check the response and the data in the system. | D21: HTTP 400 (or 404 for a non-existing ID) with success = false and an error message / field errors. No data is created or changed. | E21: Tenant A is ACTIVE. The Admin account has permission for this action. The target resource exists. | F21: Passed | G21: 14/10/2026 | H21: Nguyễn Nhất Sinh | O21: Verified by automated tests: AccountProfileServiceTest, JobAssignmentServiceTest, MemberInvitationServiceTest ...
A22: Get matrix (GET /api/v1/tenant/role-permissions)
A23: AUTH-04-TC19 | B23: Verify get matrix succeeds with valid input (GET /api/v1/tenant/role-permissions). | C23: 1. Log in as Admin of tenant A. 2. Send GET /api/v1/tenant/role-permissions with header X-Tenant-ID = tenant A. 3. Check the response and the data shown in the system. | D23: HTTP 200. Response success = true and contains the requested data of tenant A only. | E23: Tenant A is ACTIVE. The Admin account has permission for this action. | F23: Passed | G23: 14/10/2026 | H23: Nguyễn Nhất Sinh | O23: Verified by automated tests: AccountProfileServiceTest, JobAssignmentServiceTest, MemberInvitationServiceTest ...
A24: Replace (PUT /api/v1/tenant/role-permissions)
A25: AUTH-04-TC20 | B25: Verify replace succeeds with valid input (PUT /api/v1/tenant/role-permissions). | C25: 1. Log in as Admin of tenant A. 2. Send PUT /api/v1/tenant/role-permissions with header X-Tenant-ID = tenant A and a valid request body. 3. Check the response and the data shown in the system. | D25: HTTP 200. Response success = true; the changes are saved and returned. | E25: Tenant A is ACTIVE. The Admin account has permission for this action. | F25: Passed | G25: 14/10/2026 | H25: Nguyễn Nhất Sinh | O25: Verified by automated tests: AccountProfileServiceTest, JobAssignmentServiceTest, MemberInvitationServiceTest ...
A26: AUTH-04-TC21 | B26: Verify replace rejects invalid input (PUT /api/v1/tenant/role-permissions). | C26: 1. Log in as Admin of tenant A. 2. Send PUT /api/v1/tenant/role-permissions with header X-Tenant-ID = tenant A with missing required fields or invalid values (empty text, wrong format, out-of-range numbers, non-existing IDs). 3. Check the response and the data in the system. | D26: HTTP 400 (or 404 for a non-existing ID) with success = false and an error message / field errors. No data is created or changed. | E26: Tenant A is ACTIVE. The Admin account has permission for this action. | F26: Passed | G26: 14/10/2026 | H26: Nguyễn Nhất Sinh | O26: Verified by automated tests: AccountProfileServiceTest, JobAssignmentServiceTest, MemberInvitationServiceTest ...
A27: Assign role (PUT /api/v1/tenant/users/{id}/role)
A28: AUTH-04-TC22 | B28: Verify assign role succeeds with valid input (PUT /api/v1/tenant/users/{id}/role). | C28: 1. Log in as Admin of tenant A. 2. Send PUT /api/v1/tenant/users/{id}/role with header X-Tenant-ID = tenant A and a valid request body. 3. Check the response and the data shown in the system. | D28: HTTP 200. Response success = true; the changes are saved and returned. | E28: Tenant A is ACTIVE. The Admin account has permission for this action. The target resource exists. | F28: Passed | G28: 14/10/2026 | H28: Nguyễn Nhất Sinh | O28: Verified by automated tests: AccountProfileServiceTest, JobAssignmentServiceTest, MemberInvitationServiceTest ...
A29: AUTH-04-TC23 | B29: Verify assign role rejects invalid input (PUT /api/v1/tenant/users/{id}/role). | C29: 1. Log in as Admin of tenant A. 2. Send PUT /api/v1/tenant/users/{id}/role with header X-Tenant-ID = tenant A with missing required fields or invalid values (empty text, wrong format, out-of-range numbers, non-existing IDs). 3. Check the response and the data in the system. | D29: HTTP 400 (or 404 for a non-existing ID) with success = false and an error message / field errors. No data is created or changed. | E29: Tenant A is ACTIVE. The Admin account has permission for this action. The target resource exists. | F29: Passed | G29: 14/10/2026 | H29: Nguyễn Nhất Sinh | O29: Verified by automated tests: AccountProfileServiceTest, JobAssignmentServiceTest, MemberInvitationServiceTest ...
A30: Login (POST /api/v1/tenant/auth/login)
A31: AUTH-04-TC24 | B31: Verify login succeeds with valid input (POST /api/v1/tenant/auth/login). | C31: 1. Do not log in (public endpoint). 2. Send POST /api/v1/tenant/auth/login and a valid request body. 3. Check the response and the data shown in the system. | D31: HTTP 200/201. Response success = true; the record/action is saved and returned in the response. | E31: Tenant A is ACTIVE. | F31: Passed | G31: 14/10/2026 | H31: Nguyễn Nhất Sinh | O31: Verified by automated tests: AccountProfileServiceTest, JobAssignmentServiceTest, MemberInvitationServiceTest ...
A32: AUTH-04-TC25 | B32: Verify login rejects invalid input (POST /api/v1/tenant/auth/login). | C32: 1. Do not log in (public endpoint). 2. Send POST /api/v1/tenant/auth/login with missing required fields or invalid values (empty text, wrong format, out-of-range numbers, non-existing IDs). 3. Check the response and the data in the system. | D32: HTTP 400 (or 404 for a non-existing ID) with success = false and an error message / field errors. No data is created or changed. | E32: Tenant A is ACTIVE. | F32: Passed | G32: 14/10/2026 | H32: Nguyễn Nhất Sinh | O32: Verified by automated tests: AccountProfileServiceTest, JobAssignmentServiceTest, MemberInvitationServiceTest ...
A33: Get current user (GET /api/v1/tenant/auth/me)
A34: AUTH-04-TC26 | B34: Verify get current user succeeds with valid input (GET /api/v1/tenant/auth/me). | C34: 1. Log in as Admin of tenant A. 2. Send GET /api/v1/tenant/auth/me with header X-Tenant-ID = tenant A. 3. Check the response and the data shown in the system. | D34: HTTP 200. Response success = true and contains the requested data of tenant A only. | E34: Tenant A is ACTIVE. The Admin account has permission for this action. | F34: Passed | G34: 14/10/2026 | H34: Nguyễn Nhất Sinh | O34: Verified by automated tests: AccountProfileServiceTest, JobAssignmentServiceTest, MemberInvitationServiceTest ...
A35: Security & tenant isolation
A36: AUTH-04-TC27 | B36: Verify protected APIs of this feature reject unauthenticated and unauthorized users. | C36: 1. Send GET /api/v1/tenant/roles without an Authorization header. 2. Send the same request with a valid token of a role that is not allowed (e.g. Candidate calling a staff API). | D36: Step 1: HTTP 401, code UNAUTHORIZED. Step 2: HTTP 403, code FORBIDDEN. No data is returned or changed. | E36: Accounts of an allowed role and a not-allowed role exist in tenant A. | F36: Passed | G36: 14/10/2026 | H36: Nguyễn Nhất Sinh | O36: Verified by automated tests: AccountProfileServiceTest, JobAssignmentServiceTest, MemberInvitationServiceTest ...
A37: AUTH-04-TC28 | B37: Verify tenant data isolation: a tenant B user cannot read or change tenant A data. | C37: 1. Log in as Admin of tenant B. 2. Send PUT /api/v1/tenant/roles/{id} using a resource ID that belongs to tenant A, with header X-Tenant-ID = tenant A. 3. Open the related list screen of tenant B. | D37: Step 2: the tenant in the JWT (tenant B) is used, so the request returns HTTP 404 (or an empty result); no tenant A data is returned or changed. Step 3: only tenant B records are listed. | E37: Tenant A and tenant B are ACTIVE and both have data for this feature. | F37: Passed | G37: 14/10/2026 | H37: Nguyễn Nhất Sinh | O37: Verified by automated tests: AccountProfileServiceTest, JobAssignmentServiceTest, MemberInvitationServiceTest ...

Sheet AUTH-05
A2: Feature | B2: User Profile Management | R2: Passed
A3: Test requirement | B3: Verify the business rules and APIs of AUTH-05 - User Profile Management as specified in docs/features/Authentication/User-Profile.md. | R3: Failed
A4: Number of TCs | B4: =COUNTIF(A11:A2000,"*-TC*") -> 7 | R4: Pending
A5: Testing Round | B5: Passed | C5: Failed | D5: Pending | E5: N/A | R5: N/A
A6: Round 1 | B6: =COUNTIF($F$11:$F$2000,B$5) -> 0 | C6: =COUNTIF($F$11:$F$2000,C$5) -> 0 | D6: =COUNTIF($F$11:$F$2000,D$5) -> 7 | E6: =COUNTIF($F$11:$F$2000,E$5) -> 0
A7: Round 2 | B7: =COUNTIF($I$11:$I$2000,B$5) -> 0 | C7: =COUNTIF($I$11:$I$2000,C$5) -> 0 | D7: =COUNTIF($I$11:$I$2000,D$5) -> 0 | E7: =COUNTIF($I$11:$I$2000,E$5) -> 0
A8: Round 3 | B8: =COUNTIF($L$11:$L$2000,B$5) -> 0 | C8: =COUNTIF($L$11:$L$2000,C$5) -> 0 | D8: =COUNTIF($L$11:$L$2000,D$5) -> 0 | E8: =COUNTIF($L$11:$L$2000,E$5) -> 0
A10: Test Case ID | B10: Test Case Description | C10: Test Case Procedure | D10: Expected Results | E10: Pre-conditions | F10: Round 1 | G10: Test date | H10: Tester | I10: Round 2 | J10: Test date | K10: Tester | L10: Round 3 | M10: Test date | N10: Tester | O10: Note
A11: GET /api/v1/users/me (GET /api/v1/users/me)
A12: AUTH-05-TC04 | B12: Verify get /api/v1/users/me succeeds with valid input (GET /api/v1/users/me). | C12: 1. Log in as Admin of tenant A. 2. Send GET /api/v1/users/me with header X-Tenant-ID = tenant A. 3. Check the response and the data shown in the system. | D12: HTTP 200. Response success = true and contains the requested data of tenant A only. | E12: Tenant A is ACTIVE. The Admin account has permission for this action. | F12: Pending | H12: Nguyễn Nhất Sinh | O12: Not tested: API not implemented yet.
A13: PUT /api/v1/users/me (PUT /api/v1/users/me)
A14: AUTH-05-TC05 | B14: Verify put /api/v1/users/me succeeds with valid input (PUT /api/v1/users/me). | C14: 1. Log in as Admin of tenant A. 2. Send PUT /api/v1/users/me with header X-Tenant-ID = tenant A and a valid request body. 3. Check the response and the data shown in the system. | D14: HTTP 200. Response success = true; the changes are saved and returned. | E14: Tenant A is ACTIVE. The Admin account has permission for this action. | F14: Pending | H14: Nguyễn Nhất Sinh | O14: Not tested: API not implemented yet.
A15: AUTH-05-TC06 | B15: Verify put /api/v1/users/me rejects invalid input (PUT /api/v1/users/me). | C15: 1. Log in as Admin of tenant A. 2. Send PUT /api/v1/users/me with header X-Tenant-ID = tenant A with missing required fields or invalid values (empty text, wrong format, out-of-range numbers, non-existing IDs). 3. Check the response and the data in the system. | D15: HTTP 400 (or 404 for a non-existing ID) with success = false and an error message / field errors. No data is created or changed. | E15: Tenant A is ACTIVE. The Admin account has permission for this action. | F15: Pending | H15: Nguyễn Nhất Sinh | O15: Not tested: API not implemented yet.
A16: POST /api/v1/users/me/avatar (POST /api/v1/users/me/avatar)
A17: AUTH-05-TC07 | B17: Verify post /api/v1/users/me/avatar succeeds with valid input (POST /api/v1/users/me/avatar). | C17: 1. Log in as Admin of tenant A. 2. Send POST /api/v1/users/me/avatar with header X-Tenant-ID = tenant A and a valid request body. 3. Check the response and the data shown in the system. | D17: HTTP 200/201. Response success = true; the record/action is saved and returned in the response. | E17: Tenant A is ACTIVE. The Admin account has permission for this action. | F17: Pending | H17: Nguyễn Nhất Sinh | O17: Not tested: API not implemented yet.
A18: AUTH-05-TC08 | B18: Verify post /api/v1/users/me/avatar rejects invalid input (POST /api/v1/users/me/avatar). | C18: 1. Log in as Admin of tenant A. 2. Send POST /api/v1/users/me/avatar with header X-Tenant-ID = tenant A with missing required fields or invalid values (empty text, wrong format, out-of-range numbers, non-existing IDs). 3. Check the response and the data in the system. | D18: HTTP 400 (or 404 for a non-existing ID) with success = false and an error message / field errors. No data is created or changed. | E18: Tenant A is ACTIVE. The Admin account has permission for this action. | F18: Pending | H18: Nguyễn Nhất Sinh | O18: Not tested: API not implemented yet.
A19: Security & tenant isolation
A20: AUTH-05-TC09 | B20: Verify protected APIs of this feature reject unauthenticated and unauthorized users. | C20: 1. Send GET /api/v1/users/me without an Authorization header. 2. Send the same request with a valid token of a role that is not allowed (e.g. Candidate calling a staff API). | D20: Step 1: HTTP 401, code UNAUTHORIZED. Step 2: HTTP 403, code FORBIDDEN. No data is returned or changed. | E20: Accounts of an allowed role and a not-allowed role exist in tenant A. | F20: Pending | H20: Nguyễn Nhất Sinh | O20: Not tested: no automated test covers this feature yet.
A21: AUTH-05-TC10 | B21: Verify tenant data isolation: a tenant B user cannot read or change tenant A data. | C21: 1. Log in as Admin of tenant B. 2. Send GET /api/v1/users/me using a resource ID that belongs to tenant A, with header X-Tenant-ID = tenant A. 3. Open the related list screen of tenant B. | D21: Step 2: the tenant in the JWT (tenant B) is used, so the request returns HTTP 404 (or an empty result); no tenant A data is returned or changed. Step 3: only tenant B records are listed. | E21: Tenant A and tenant B are ACTIVE and both have data for this feature. | F21: Pending | H21: Nguyễn Nhất Sinh | O21: Not tested: no automated test covers this feature yet.

Sheet COMPANY-01
A2: Feature | B2: View & Update Company Profile | R2: Passed
A3: Test requirement | B3: Verify the business rules and APIs of COMPANY-01 - View & Update Company Profile as specified in docs/features/Company-Management/Company-Profile.md. | R3: Failed
A4: Number of TCs | B4: =COUNTIF(A11:A2000,"*-TC*") -> 8 | R4: Pending
A5: Testing Round | B5: Passed | C5: Failed | D5: Pending | E5: N/A | R5: N/A
A6: Round 1 | B6: =COUNTIF($F$11:$F$2000,B$5) -> 8 | C6: =COUNTIF($F$11:$F$2000,C$5) -> 0 | D6: =COUNTIF($F$11:$F$2000,D$5) -> 0 | E6: =COUNTIF($F$11:$F$2000,E$5) -> 0
A7: Round 2 | B7: =COUNTIF($I$11:$I$2000,B$5) -> 0 | C7: =COUNTIF($I$11:$I$2000,C$5) -> 0 | D7: =COUNTIF($I$11:$I$2000,D$5) -> 0 | E7: =COUNTIF($I$11:$I$2000,E$5) -> 0
A8: Round 3 | B8: =COUNTIF($L$11:$L$2000,B$5) -> 0 | C8: =COUNTIF($L$11:$L$2000,C$5) -> 0 | D8: =COUNTIF($L$11:$L$2000,D$5) -> 0 | E8: =COUNTIF($L$11:$L$2000,E$5) -> 0
A10: Test Case ID | B10: Test Case Description | C10: Test Case Procedure | D10: Expected Results | E10: Pre-conditions | F10: Round 1 | G10: Test date | H10: Tester | I10: Round 2 | J10: Test date | K10: Tester | L10: Round 3 | M10: Test date | N10: Tester | O10: Note
A11: Tenant (GET /api/v1/tenant/company/profile)
A12: COMPANY-01-TC08 | B12: Verify tenant succeeds with valid input (GET /api/v1/tenant/company/profile). | C12: 1. Log in as Tenant Admin of tenant A. 2. Send GET /api/v1/tenant/company/profile with header X-Tenant-ID = tenant A. 3. Check the response and the data shown in the system. | D12: HTTP 200. Response success = true and contains the requested data of tenant A only. | E12: Tenant A is ACTIVE. The Tenant Admin account has permission for this action. | F12: Passed | G12: 14/10/2026 | H12: Lê Công Cường | O12: Verified by automated tests: CompanyDirectoryServiceTest, CompanyProfileControllerTest, CompanyProfileServiceTest
A13: Update profile (PUT /api/v1/tenant/company/profile)
